Workbook
Name dd_OrderMonth: Dashboard!$E$7
Name dd_PaymentMethod: Dashboard!$B$7
Name Slicer_Category: #N/A
Name Slicer_Customer_Age_Group: #N/A
Name Slicer_Order_Month: #N/A
Name Slicer_Order_Status: #N/A
Name Slicer_Order_Year: #N/A
Name Slicer_Payment_Method1: #N/A

Sheet Dashboard
B2: E-COMMERCE SALES ANALYTICS
B4: Sales Performance • Revenue • Profitability • Customer Insights
B5: Business Performance Overview
Q7: SLICER
B8: TOTAL REVENUE | E8: TOTAL PROFIT | H8: UNITS SOLD | K8: TOTAL ORDERS | N8: PROFIT MARGIN
B10: =GETPIVOTDATA("Total Revenue ",Analysis!$A$1) -> 13596053 | E10: =GETPIVOTDATA("Total Profit ",Analysis!$A$1) -> 4935773 | H10: =GETPIVOTDATA("Units Sold ",Analysis!$A$1) -> 8906 | K10: =GETPIVOTDATA("[Measures].[Count of Order_ID]",Analysis!$O$14) -> 5000 | N10: =IFERROR(E10/B10,0) -> 0.36302984
B94: Source: E-Commerce Sales Dataset | Analysis Period: 2025–2026
E96: Built using Microsoft Excel | Data Analysis & Visualization

Sheet Business_Insights
B1: E-Commerce Sales Analytics — Business Insights
B5: Executive Summary The e-commerce business generated approximately ₹13.60M in net revenue from 5,000 orders, selling 8,906 units and generating approximately ₹4.94M in profit, resulting in an overall 36.3% profit margin.
B9: # | C9: Business Area | D9: Insight | E9: Business Recommendation
B10: 1 | C10: Revenue | D10: Identify the highest-revenue category | E10: Focus inventory and marketing on the strongest category
B11: 2 | C11: Profitability | D11: Identify the most profitable category | E11: Prioritize high-margin products
B12: 3 | C12: Products | D12: Identify the Top 10 products | E12: Maintain stock availability for high-performing products
B13: 4 | C13: Geography | D13: Identify the highest-revenue cities | E13: Increase marketing in strong-performing locations
B14: 5 | C14: Customers | D14: Identify the strongest age group | E14: Target campaigns toward the strongest customer segment
B15: 6 | C15: Payments | D15: Identify the leading payment method | E15: Optimize the checkout experience for preferred methods
B16: 7 | C16: Discounts | D16: Analyze how discounts affect profit | E16: Avoid excessive discounting where margins decline
B17: 8 | C17: Orders | D17: Identify the dominant order status | E17: Investigate cancelled/pending orders if significant
B20: Key Takeaways
B22: • Generated ₹13.60M revenue and ₹4.94M profit with a 36% overall profit margin across 5,000 orders. • Electronics emerged as the leading revenue-generating category, making it a key contributor to overall business performance. • The 26–35 customer segment generated the highest revenue, identifying a high-value customer group for targeted marketing. • Revenue showed noticeable seasonal fluctuations, with performance peaking around October–November and declining during several low-performing months. • Profitability was strongest at moderate discount levels, while higher discounts showed a clear decline in profit, highlighting the need for controlled promotional pricing.

Sheet Analysis
A1: Total Revenue | B1: Total Profit | C1: Units Sold | F1: Row Labels | G1: Total Revenue | H1: Total Profit | I1: Units Sold | K1: Row Labels | L1: Total Revenue | O1: Row Labels | P1: Total Revenue | Q1: Total Profit
A2: 13596053 | B2: 4935773 | C2: 8906 | F2: Air Fryer | G2: 1210298.2 | H2: 309398.25 | I2: 231 | K2: Cash on Delivery | L2: 1375731.4 | O2: 0 | P2: 1993556 | Q2: 855796
F3: Running Shoes | G3: 1077993.2 | H3: 369093.15 | I3: 417 | K3: Credit Card | L3: 2874731.7 | O3: 0.05 | P3: 3110280 | Q3: 1250710.1
A4: Row Labels | B4: Total evenue | C4: Total Profit | F4: Smart Watch | G4: 1076463.7 | H4: 307863.7 | I4: 366 | K4: Debit Card | L4: 2303140.5 | O4: 0.1 | P4: 3678600.6 | Q4: 1385720.6
A5: Apr | B5: 1497043.4 | C5: 548253.45 | F5: Wireless Headphones | G5: 1054328.1 | H5: 319628.1 | I5: 474 | K5: Net Banking | L5: 1626252.7 | O5: 0.15 | P5: 2378991 | Q5: 804041.05
A6: Feb | B6: 1386576.6 | C6: 494146.65 | F6: Coffee Maker | G6: 736714.45 | H6: 210214.45 | I6: 234 | K6: UPI | L6: 4574115.4 | O6: 0.2 | P6: 1412241.6 | Q6: 410011.6
A7: Jan | B7: 1497672.9 | C7: 548002.9 | F7: Non-Stick Cookware Set | G7: 693428.7 | H7: 212828.7 | I7: 178 | K7: Wallet | L7: 842081.3 | O7: 0.25 | P7: 646150.5 | Q7: 162900.5
A8: Jun | B8: 1431582.4 | C8: 529022.4 | F8: Bluetooth Speaker | G8: 596950.65 | H8: 197110.65 | I8: 357 | K8: Grand Total | L8: 13596053 | O8: 0.3 | P8: 376233.2 | Q8: 66593.2
A9: Mar | B9: 1704774.4 | C9: 617444.4 | F9: Denim Jeans | G9: 583907.9 | H9: 238457.9 | I9: 329 | O9: Grand Total | P9: 13596053 | Q9: 4935773
A10: May | B10: 1645399.5 | C10: 594689.5 | F10: Dumbbell Set | G10: 560150.85 | H10: 193300.85 | I10: 253
A11: Aug | B11: 857893.8 | C11: 305083.8 | F11: Cricket Bat | G11: 544912.2 | H11: 193662.2 | I11: 281 | K11: Row Labels | L11: Total Revenue | M11: Units Sold
A12: Dec | B12: 737109.3 | C12: 267219.3 | F12: Grand Total | G12: 8135147.9 | H12: 2551558 | I12: 3120 | K12: 18-25 | L12: 3011851.8 | M12: 2010
A13: Jul | B13: 758875.4 | C13: 276865.4 | K13: 26-35 | L13: 5843467.8 | M13: 3816
A14: Nov | B14: 714928.3 | C14: 256768.3 | K14: 36-45 | L14: 3849209.6 | M14: 2492 | O14: Count of Order_ID
A15: Oct | B15: 692871.6 | C15: 251681.6 | F15: Row Labels | G15: Total Revenue | H15: Total Profit | K15: 46-55 | L15: 858317.55 | M15: 561 | O15: 5000
A16: Sep | B16: 671325.3 | C16: 246595.3 | F16: Delhi | G16: 719261.95 | H16: 255721.95 | K16: 56+ | L16: 33206.3 | M16: 27
A17: Grand Total | B17: 13596053 | C17: 4935773 | F17: Surat | G17: 684742.65 | H17: 245782.65 | K17: Grand Total | L17: 13596053 | M17: 8906
F18: Kochi | G18: 646354.35 | H18: 230014.35
F19: Coimbatore | G19: 622928.8 | H19: 220518.8
A20: Row Labels | B20: Total Revenue | C20: Total Profit | D20: Units Sold | F20: Mumbai | G20: 622816.6 | H20: 225936.6 | K20: Row Labels | L20: Total Revenue | M20: Units Sold
A21: Beauty | B21: 1248415.3 | C21: 592215.3 | D21: 1643 | F21: Bengaluru | G21: 614128.15 | H21: 224128.15 | K21: Cancelled | L21: 615298.4 | M21: 403
A22: Books | B22: 1120834.9 | C22: 538214.95 | D22: 1347 | F22: Ahmedabad | G22: 596833.5 | H22: 215423.5 | K22: Delivered | L22: 12236356 | M22: 8014
A23: Electronics | B23: 3380694.3 | C23: 1064314.3 | D23: 1782 | F23: Nagpur | G23: 593655.05 | H23: 211755.05 | K23: Returned | L23: 744398.75 | M23: 489
A24: Fashion | B24: 2739757.3 | C24: 1055427.3 | D24: 1654 | F24: Ranchi | G24: 593018.15 | H24: 209088.15 | K24: Grand Total | L24: 13596053 | M24: 8906
A25: Home & Kitchen | B25: 3223975.9 | C25: 968405.9 | D25: 1092 | F25: Lucknow | G25: 585140.25 | H25: 208890.25
A26: Sports & Fitness | B26: 1882375.3 | C26: 717195.25 | D26: 1388 | F26: Grand Total | G26: 6278879.4 | H26: 2247259.5
A27: Grand Total | B27: 13596053 | C27: 4935773 | D27: 8906

Sheet Ecommerce_Sales
A1: Order_ID | B1: Order_Date | C1: Customer_ID | D1: Customer_Name | E1: Gender | F1: Age | G1: City | H1: Region | I1: Product_ID | J1: Product_Name | K1: Category | L1: Sub_Category | M1: Quantity | N1: Unit_Price | O1: Discount | P1: Cost | Q1: Payment_Method | R1: Order_Status | S1: Sales_Channel | T1: Rating | U1: Gross_Sales | V1: Discount_Amount | W1: Net_Revenue | X1: Total_Cost | Y1: Profit | Z1: Profit_Margin | AA1: Order_Month | AB1: Order_Year | AC1: Customer_Age_Group
A2: ORD104877 | B2: 45658 | C2: CUST1411 | D2: Riya Verma | E2: Female | F2: 24 | G2: Bokaro | H2: East | I2: P012 | J2: Air Fryer | K2: Home & Kitchen | L2: Kitchen | M2: 1 | N2: 5999 | O2: 0.1 | P2: 3900 | Q2: UPI | R2: Delivered | S2: Mobile App | T2: 3 | U2: =M2*N2 -> 5999 | V2: =tbl_EcommerceSales[[#This Row],[Gross_Sales]]*tbl_EcommerceSales[[#This Row],[Discount]] -> 599.9 | W2: =tbl_EcommerceSales[[#This Row],[Gross_Sales]]-tbl_EcommerceSales[[#This Row],[Discount_Amount]] -> 5399.1 | X2: =tbl_EcommerceSales[[#This Row],[Quantity]] * _xlfn.XLOOKUP(tbl_EcommerceSales[[#This Row],[Product_ID]], Product_Master!A:A, Product_Master!F:F) -> 3900 | Y2: =tbl_EcommerceSales[[#This Row],[Net_Revenue]]-tbl_EcommerceSales[[#This Row],[Total_Cost]] -> 1499.1 | Z2: =IFERROR(#REF!/tbl_EcommerceSales[[#This Row],[Total_Cost]], 0) -> 0 | AA2: =TEXT(tbl_EcommerceSales[[#This Row],[Order_Date]],"mmm") -> Jan | AB2: =YEAR(tbl_EcommerceSales[[#This Row],[Order_Date]]) -> 2025 | AC2: =IF(tbl_EcommerceSales[[#This Row],[Age]]<18,"Under 18",IF(tbl_EcommerceSales[[#This Row],[Age]]<=25,"18-25",IF(tbl_EcommerceSales[[#This Row],[Age]]<=35,"26-35",IF(tbl_EcommerceSales[[#This Row],[Age]]<=45,"36-45",IF(tbl_EcommerceSales[[#This Row],[Age]]<=55,"46-55","56+"))))) -> 18-25
A3: ORD104594 | B3: 45658 | C3: CUST1943 | D3: Aditi Saxena | E3: Female | F3: 47 | G3: Amritsar | H3: North | I3: P025 | J3: Moisturizer | K3: Beauty | L3: Skincare | M3: 1 | N3: 699 | O3: 0.1 | P3: 310 | Q3: Debit Card | R3: Delivered | S3: Mobile App | T3: 4 | U3: =M3*N3 -> 699 | V3: =tbl_EcommerceSales[[#This Row],[Gross_Sales]]*tbl_EcommerceSales[[#This Row],[Discount]] -> 69.9 | W3: =tbl_EcommerceSales[[#This Row],[Gross_Sales]]-tbl_EcommerceSales[[#This Row],[Discount_Amount]] -> 629.1 | X3: =tbl_EcommerceSales[[#This Row],[Quantity]] * _xlfn.XLOOKUP(tbl_EcommerceSales[[#This Row],[Product_ID]], Product_Master!A:A, Product_Master!F:F) -> 310 | Y3: =tbl_EcommerceSales[[#This Row],[Net_Revenue]]-tbl_EcommerceSales[[#This Row],[Total_Cost]] -> 319.1 | Z3: =IFERROR(#REF!/tbl_EcommerceSales[[#This Row],[Total_Cost]], 0) -> 0 | AA3: =TEXT(tbl_EcommerceSales[[#This Row],[Order_Date]],"mmm") -> Jan | AB3: =YEAR(tbl_EcommerceSales[[#This Row],[Order_Date]]) -> 2025 | AC3: =IF(tbl_EcommerceSales[[#This Row],[Age]]<18,"Under 18",IF(tbl_EcommerceSales[[#This Row],[Age]]<=25,"18-25",IF(tbl_EcommerceSales[[#This Row],[Age]]<=35,"26-35",IF(tbl_EcommerceSales[[#This Row],[Age]]<=45,"36-45",IF(tbl_EcommerceSales[[#This Row],[Age]]<=55,"46-55","56+"))))) -> 46-55
A4: ORD100846 | B4: 45658 | C4: CUST0744 | D4: Sanya Malhotra | E4: Male | F4: 24 | G4: Amritsar | H4: North | I4: P025 | J4: Moisturizer | K4: Beauty | L4: Skincare | M4: 1 | N4: 699 | O4: 0.2 | P4: 310 | Q4: UPI | R4: Delivered | S4: Mobile App | T4: 5 | U4: =M4*N4 -> 699 | V4: =tbl_EcommerceSales[[#This Row],[Gross_Sales]]*tbl_EcommerceSales[[#This Row],[Discount]] -> 139.8 | W4: =tbl_EcommerceSales[[#This Row],[Gross_Sales]]-tbl_EcommerceSales[[#This Row],[Discount_Amount]] -> 559.2 | X4: =tbl_EcommerceSales[[#This Row],[Quantity]] * _xlfn.XLOOKUP(tbl_EcommerceSales[[#This Row],[Product_ID]], Product_Master!A:A, Product_Master!F:F) -> 310 | Y4: =tbl_EcommerceSales[[#This Row],[Net_Revenue]]-tbl_EcommerceSales[[#This Row],[Total_Cost]] -> 249.2 | Z4: =IFERROR(#REF!/tbl_EcommerceSales[[#This Row],[Total_Cost]], 0) -> 0 | AA4: =TEXT(tbl_EcommerceSales[[#This Row],[Order_Date]],"mmm") -> Jan | AB4: =YEAR(tbl_EcommerceSales[[#This Row],[Order_Date]]) -> 2025 | AC4: =IF(tbl_EcommerceSales[[#This Row],[Age]]<18,"Under 18",IF(tbl_EcommerceSales[[#This Row],[Age]]<=25,"18-25",IF(tbl_EcommerceSales[[#This Row],[Age]]<=35,"26-35",IF(tbl_EcommerceSales[[#This Row],[Age]]<=45,"36-45",IF(tbl_EcommerceSales[[#This Row],[Age]]<=55,"46-55","56+"))))) -> 18-25
A5: ORD101485 | B5: 45658 | C5: CUST1433 | D5: Meera Singh | E5: Female | F5: 42 | G5: Patna | H5: East | I5: P008 | J5: Cotton T-Shirt | K5: Fashion | L5: Clothing | M5: 2 | N5: 799 | O5: 0.1 | P5: 780 | Q5: UPI | R5: Delivered | S5: Website | T5: 5 | U5: =M5*N5 -> 1598 | V5: =tbl_EcommerceSales[[#This Row],[Gross_Sales]]*tbl_EcommerceSales[[#This Row],[Discount]] -> 159.8 | W5: =tbl_EcommerceSales[[#This Row],[Gross_Sales]]-tbl_EcommerceSales[[#This Row],[Discount_Amount]] -> 1438.2 | X5: =tbl_EcommerceSales[[#This Row],[Quantity]] * _xlfn.XLOOKUP(tbl_EcommerceSales[[#This Row],[Product_ID]], Product_Master!A:A, Product_Master!F:F) -> 780 | Y5: =tbl_EcommerceSales[[#This Row],[Net_Revenue]]-tbl_EcommerceSales[[#This Row],[Total_Cost]] -> 658.2 | Z5: =IFERROR(#REF!/tbl_EcommerceSales[[#This Row],[Total_Cost]], 0) -> 0 | AA5: =TEXT(tbl_EcommerceSales[[#This Row],[Order_Date]],"mmm") -> Jan | AB5: =YEAR(tbl_EcommerceSales[[#This Row],[Order_Date]]) -> 2025 | AC5: =IF(tbl_EcommerceSales[[#This Row],[Age]]<18,"Under 18",IF(tbl_EcommerceSales[[#This Row],[Age]]<=25,"18-25",IF(tbl_EcommerceSales[[#This Row],[Age]]<=35,"26-35",IF(tbl_EcommerceSales[[#This Row],[Age]]<=45,"36-45",IF(tbl_EcommerceSales[[#This Row],[Age]]<=55,"46-55","56+"))))) -> 36-45
A6: ORD104728 | B6: 45658 | C6: CUST0422 | D6: Kabir Gupta | E6: Male | F6: 34 | G6: Kolkata | H6: East | I6: P021 | J6: Face Wash | K6: Beauty | L6: Skincare | M6: 2 | N6: 499 | O6: 0.15 | P6: 440 | Q6: UPI | R6: Delivered | S6: Mobile App | T6: 5 | U6: =M6*N6 -> 998 | V6: =tbl_EcommerceSales[[#This Row],[Gross_Sales]]*tbl_EcommerceSales[[#This Row],[Discount]] -> 149.7 | W6: =tbl_EcommerceSales[[#This Row],[Gross_Sales]]-tbl_EcommerceSales[[#This Row],[Discount_Amount]] -> 848.3 | X6: =tbl_EcommerceSales[[#This Row],[Quantity]] * _xlfn.XLOOKUP(tbl_EcommerceSales[[#This Row],[Product_ID]], Product_Master!A:A, Product_Master!F:F) -> 440 | Y6: =tbl_EcommerceSales[[#This Row],[Net_Revenue]]-tbl_EcommerceSales[[#This Row],[Total_Cost]] -> 408.3 | Z6: =IFERROR(#REF!/tbl_EcommerceSales[[#This Row],[Total_Cost]], 0) -> 0 | AA6: =TEXT(tbl_EcommerceSales[[#This Row],[Order_Date]],"mmm") -> Jan | AB6: =YEAR(tbl_EcommerceSales[[#This Row],[Order_Date]]) -> 2025 | AC6: =IF(tbl_EcommerceSales[[#This Row],[Age]]<18,"Under 18",IF(tbl_EcommerceSales[[#This Row],[Age]]<=25,"18-25",IF(tbl_EcommerceSales[[#This Row],[Age]]<=35,"26-35",IF(tbl_EcommerceSales[[#This Row],[Age]]<=45,"36-45",IF(tbl_EcommerceSales[[#This Row],[Age]]<=55,"46-55","56+"))))) -> 26-35
A7: ORD100558 | B7: 45658 | C7: CUST0105 | D7: Zoya Singh | E7: Male | F7: 42 | G7: Amritsar | H7: North | I7: P022 | J7: Sunscreen SPF 50 | K7: Beauty | L7: Skincare | M7: 1 | N7: 799 | O7: 0.15 | P7: 360 | Q7: UPI | R7: Delivered | S7: Mobile App | T7: 5 | U7: =M7*N7 -> 799 | V7: =tbl_EcommerceSales[[#This Row],[Gross_Sales]]*tbl_EcommerceSales[[#This Row],[Discount]] -> 119.85 | W7: =tbl_EcommerceSales[[#This Row],[Gross_Sales]]-tbl_EcommerceSales[[#This Row],[Discount_Amount]] -> 679.15 | X7: =tbl_EcommerceSales[[#This Row],[Quantity]] * _xlfn.XLOOKUP(tbl_EcommerceSales[[#This Row],[Product_ID]], Product_Master!A:A, Product_Master!F:F) -> 360 | Y7: =tbl_EcommerceSales[[#This Row],[Net_Revenue]]-tbl_EcommerceSales[[#This Row],[Total_Cost]] -> 319.15 | Z7: =IFERROR(#REF!/tbl_EcommerceSales[[#This Row],[Total_Cost]], 0) -> 0 | AA7: =TEXT(tbl_EcommerceSales[[#This Row],[Order_Date]],"mmm") -> Jan | AB7: =YEAR(tbl_EcommerceSales[[#This Row],[Order_Date]]) -> 2025 | AC7: =IF(tbl_EcommerceSales[[#This Row],[Age]]<18,"Under 18",IF(tbl_EcommerceSales[[#This Row],[Age]]<=25,"18-25",IF(tbl_EcommerceSales[[#This Row],[Age]]<=35,"26-35",IF(tbl_EcommerceSales[[#This Row],[Age]]<=45,"36-45",IF(tbl_EcommerceSales[[#This Row],[Age]]<=55,"46-55","56+"))))) -> 36-45
A8: ORD101536 | B8: 45658 | C8: CUST1894 | D8: Kabir Gupta | E8: Male | F8: 44 | G8: Hyderabad | H8: South | I8: P007 | J8: Running Shoes | K8: Fashion | L8: Footwear | M8: 1 | N8: 2899 | O8: 0.05 | P8: 1700 | Q8: Cash on Delivery | R8: Delivered | S8: Mobile App | T8: 5 | U8: =M8*N8 -> 2899 | V8: =tbl_EcommerceSales[[#This Row],[Gross_Sales]]*tbl_EcommerceSales[[#This Row],[Discount]] -> 144.95 | W8: =tbl_EcommerceSales[[#This Row],[Gross_Sales]]-tbl_EcommerceSales[[#This Row],[Discount_Amount]] -> 2754.05 | X8: =tbl_EcommerceSales[[#This Row],[Quantity]] * _xlfn.XLOOKUP(tbl_EcommerceSales[[#This Row],[Product_ID]], Product_Master!A:A, Product_Master!F:F) -> 1700 | Y8: =tbl_EcommerceSales[[#This Row],[Net_Revenue]]-tbl_EcommerceSales[[#This Row],[Total_Cost]] -> 1054.05 | Z8: =IFERROR(#REF!/tbl_EcommerceSales[[#This Row],[Total_Cost]], 0) -> 0 | AA8: =TEXT(tbl_EcommerceSales[[#This Row],[Order_Date]],"mmm") -> Jan | AB8: =YEAR(tbl_EcommerceSales[[#This Row],[Order_Date]]) -> 2025 | AC8: =IF(tbl_EcommerceSales[[#This Row],[Age]]<18,"Under 18",IF(tbl_EcommerceSales[[#This Row],[Age]]<=25,"18-25",IF(tbl_EcommerceSales[[#This Row],[Age]]<=35,"26-35",IF(tbl_EcommerceSales[[#This Row],[Age]]<=45,"36-45",IF(tbl_EcommerceSales[[#This Row],[Age]]<=55,"46-55","56+"))))) -> 36-45
A9: ORD100734 | B9: 45658 | C9: CUST0559 | D9: Isha Mehta | E9: Male | F9: 22 | G9: Kolkata | H9: East | I9: P001 | J9: Wireless Headphones | K9: Electronics | L9: Audio | M9: 1 | N9: 2499 | O9: 0.1 | P9: 1550 | Q9: UPI | R9: Delivered | S9: Mobile App | T9: 3 | U9: =M9*N9 -> 2499 | V9: =tbl_EcommerceSales[[#This Row],[Gross_Sales]]*tbl_EcommerceSales[[#This Row],[Discount]] -> 249.9 | W9: =tbl_EcommerceSales[[#This Row],[Gross_Sales]]-tbl_EcommerceSales[[#This Row],[Discount_Amount]] -> 2249.1 | X9: =tbl_EcommerceSales[[#This Row],[Quantity]] * _xlfn.XLOOKUP(tbl_EcommerceSales[[#This Row],[Product_ID]], Product_Master!A:A, Product_Master!F:F) -> 1550 | Y9: =tbl_EcommerceSales[[#This Row],[Net_Revenue]]-tbl_EcommerceSales[[#This Row],[Total_Cost]] -> 699.1 | Z9: =IFERROR(#REF!/tbl_EcommerceSales[[#This Row],[Total_Cost]], 0) -> 0 | AA9: =TEXT(tbl_EcommerceSales[[#This Row],[Order_Date]],"mmm") -> Jan | AB9: =YEAR(tbl_EcommerceSales[[#This Row],[Order_Date]]) -> 2025 | AC9: =IF(tbl_EcommerceSales[[#This Row],[Age]]<18,"Under 18",IF(tbl_EcommerceSales[[#This Row],[Age]]<=25,"18-25",IF(tbl_EcommerceSales[[#This Row],[Age]]<=35,"26-35",IF(tbl_EcommerceSales[[#This Row],[Age]]<=45,"36-45",IF(tbl_EcommerceSales[[#This Row],[Age]]<=55,"46-55","56+"))))) -> 18-25
A10: ORD104917 | B10: 45658 | C10: CUST2028 | D10: Rahul Kumar | E10: Male | F10: 20 | G10: Nagpur | H10: West | I10: P030 | J10: Self Help Book | K10: Books | L10: Self Development | M10: 1 | N10: 599 | O10: 0.05 | P10: 260 | Q10: UPI | R10: Returned | S10: Website | T10: 5 | U10: =M10*N10 -> 599 | V10: =tbl_EcommerceSales[[#This Row],[Gross_Sales]]*tbl_EcommerceSales[[#This Row],[Discount]] -> 29.95 | W10: =tbl_EcommerceSales[[#This Row],[Gross_Sales]]-tbl_EcommerceSales[[#This Row],[Discount_Amount]] -> 569.05 | X10: =tbl_EcommerceSales[[#This Row],[Quantity]] * _xlfn.XLOOKUP(tbl_EcommerceSales[[#This Row],[Product_ID]], Product_Master!A:A, Product_Master!F:F) -> 260 | Y10: =tbl_EcommerceSales[[#This Row],[Net_Revenue]]-tbl_EcommerceSales[[#This Row],[Total_Cost]] -> 309.05 | Z10: =IFERROR(#REF!/tbl_EcommerceSales[[#This Row],[Total_Cost]], 0) -> 0 | AA10: =TEXT(tbl_EcommerceSales[[#This Row],[Order_Date]],"mmm") -> Jan | AB10: =YEAR(tbl_EcommerceSales[[#This Row],[Order_Date]]) -> 2025 | AC10: =IF(tbl_EcommerceSales[[#This Row],[Age]]<18,"Under 18",IF(tbl_EcommerceSales[[#This Row],[Age]]<=25,"18-25",IF(tbl_EcommerceSales[[#This Row],[Age]]<=35,"26-35",IF(tbl_EcommerceSales[[#This Row],[Age]]<=45,"36-45",IF(tbl_EcommerceSales[[#This Row],[Age]]<=55,"46-55","56+"))))) -> 18-25
A11: ORD100475 | B11: 45658 | C11: CUST1049 | D11: Meera Singh | E11: Male | F11: 45 | G11: Dehradun | H11: North | I11: P001 | J11: Wireless Headphones | K11: Electronics | L11: Audio | M11: 1 | N11: 2499 | O11: 0.3 | P11: 1550 | Q11: UPI | R11: Delivered | S11: Website | T11: 4 | U11: =M11*N11 -> 2499 | V11: =tbl_EcommerceSales[[#This Row],[Gross_Sales]]*tbl_EcommerceSales[[#This Row],[Discount]] -> 749.7 | W11: =tbl_EcommerceSales[[#This Row],[Gross_Sales]]-tbl_EcommerceSales[[#This Row],[Discount_Amount]] -> 1749.3 | X11: =tbl_EcommerceSales[[#This Row],[Quantity]] * _xlfn.XLOOKUP(tbl_EcommerceSales[[#This Row],[Product_ID]], Product_Master!A:A, Product_Master!F:F) -> 1550 | Y11: =tbl_EcommerceSales[[#This Row],[Net_Revenue]]-tbl_EcommerceSales[[#This Row],[Total_Cost]] -> 199.3 | Z11: =IFERROR(#REF!/tbl_EcommerceSales[[#This Row],[Total_Cost]], 0) -> 0 | AA11: =TEXT(tbl_EcommerceSales[[#This Row],[Order_Date]],"mmm") -> Jan | AB11: =YEAR(tbl_EcommerceSales[[#This Row],[Order_Date]]) -> 2025 | AC11: =IF(tbl_EcommerceSales[[#This Row],[Age]]<18,"Under 18",IF(tbl_EcommerceSales[[#This Row],[Age]]<=25,"18-25",IF(tbl_EcommerceSales[[#This Row],[Age]]<=35,"26-35",IF(tbl_EcommerceSales[[#This Row],[Age]]<=45,"36-45",IF(tbl_EcommerceSales[[#This Row],[Age]]<=55,"46-55","56+"))))) -> 36-45
A12: ORD102624 | B12: 45658 | C12: CUST1512 | D12: Sanya Malhotra | E12: Female | F12: 43 | G12: Mumbai | H12: West | I12: P021 | J12: Face Wash | K12: Beauty | L12: Skincare | M12: 2 | N12: 499 | O12: 0.1 | P12: 440 | Q12: Debit Card | R12: Delivered | S12: Mobile App | T12: 4 | U12: =M12*N12 -> 998 | V12: =tbl_EcommerceSales[[#This Row],[Gross_Sales]]*tbl_EcommerceSales[[#This Row],[Discount]] -> 99.8 | W12: =tbl_EcommerceSales[[#This Row],[Gross_Sales]]-tbl_EcommerceSales[[#This Row],[Discount_Amount]] -> 898.2 | X12: =tbl_EcommerceSales[[#This Row],[Quantity]] * _xlfn.XLOOKUP(tbl_EcommerceSales[[#This Row],[Product_ID]], Product_Master!A:A, Product_Master!F:F) -> 440 | Y12: =tbl_EcommerceSales[[#This Row],[Net_Revenue]]-tbl_EcommerceSales[[#This Row],[Total_Cost]] -> 458.2 | Z12: =IFERROR(#REF!/tbl_EcommerceSales[[#This Row],[Total_Cost]], 0) -> 0 | AA12: =TEXT(tbl_EcommerceSales[[#This Row],[Order_Date]],"mmm") -> Jan | AB12: =YEAR(tbl_EcommerceSales[[#This Row],[Order_Date]]) -> 2025 | AC12: =IF(tbl_EcommerceSales[[#This Row],[Age]]<18,"Under 18",IF(tbl_EcommerceSales[[#This Row],[Age]]<=25,"18-25",IF(tbl_EcommerceSales[[#This Row],[Age]]<=35,"26-35",IF(tbl_EcommerceSales[[#This Row],[Age]]<=45,"36-45",IF(tbl_EcommerceSales[[#This Row],[Age]]<=55,"46-55","56+"))))) -> 36-45
A13: ORD103827 | B13: 45658 | C13: CUST0030 | D13: Pooja Kapoor | E13: Female | F13: 36 | G13: Bhubaneswar | H13: East | I13: P007 | J13: Running Shoes | K13: Fashion | L13: Footwear | M13: 1 | N13: 2899 | O13: 0.05 | P13: 1700 | Q13: UPI | R13: Delivered | S13: Website | T13: 5 | U13: =M13*N13 -> 2899 | V13: =tbl_EcommerceSales[[#This Row],[Gross_Sales]]*tbl_EcommerceSales[[#This Row],[Discount]] -> 144.95 | W13: =tbl_EcommerceSales[[#This Row],[Gross_Sales]]-tbl_EcommerceSales[[#This Row],[Discount_Amount]] -> 2754.05 | X13: =tbl_EcommerceSales[[#This Row],[Quantity]] * _xlfn.XLOOKUP(tbl_EcommerceSales[[#This Row],[Product_ID]], Product_Master!A:A, Product_Master!F:F) -> 1700 | Y13: =tbl_EcommerceSales[[#This Row],[Net_Revenue]]-tbl_EcommerceSales[[#This Row],[Total_Cost]] -> 1054.05 | Z13: =IFERROR(#REF!/tbl_EcommerceSales[[#This Row],[Total_Cost]], 0) -> 0 | AA13: =TEXT(tbl_EcommerceSales[[#This Row],[Order_Date]],"mmm") -> Jan | AB13: =YEAR(tbl_EcommerceSales[[#This Row],[Order_Date]]) -> 2025 | AC13: =IF(tbl_EcommerceSales[[#This Row],[Age]]<18,"Under 18",IF(tbl_EcommerceSales[[#This Row],[Age]]<=25,"18-25",IF(tbl_EcommerceSales[[#This Row],[Age]]<=35,"26-35",IF(tbl_EcommerceSales[[#This Row],[Age]]<=45,"36-45",IF(tbl_EcommerceSales[[#This Row],[Age]]<=55,"46-55","56+"))))) -> 36-45
... A26: ORD100661 | B26: 45660 | C26: CUST1356 | D26: Rahul Kumar | E26: Male | F26: 35 | G26: Surat | H26: West | I26: P022 | J26: Sunscreen SPF 50 | K26: Beauty | L26: Skincare | M26: 1 | N26: 799 | O26: 0.1 | P26: 360 | Q26: Net Banking | R26: Delivered | S26: Mobile App | T26: 2 | U26: =M26*N26 -> 799 | V26: =tbl_EcommerceSales[[#This Row],[Gross_Sales]]*tbl_EcommerceSales[[#This Row],[Discount]] -> 79.9 | W26: =tbl_EcommerceSales[[#This Row],[Gross_Sales]]-tbl_EcommerceSales[[#This Row],[Discount_Amount]] -> 719.1 | X26: =tbl_EcommerceSales[[#This Row],[Quantity]] * _xlfn.XLOOKUP(tbl_EcommerceSales[[#This Row],[Product_ID]], Product_Master!A:A, Product_Master!F:F) -> 360 | Y26: =tbl_EcommerceSales[[#This Row],[Net_Revenue]]-tbl_EcommerceSales[[#This Row],[Total_Cost]] -> 359.1 | Z26: =IFERROR(#REF!/tbl_EcommerceSales[[#This Row],[Total_Cost]], 0) -> 0 | AA26: =TEXT(tbl_EcommerceSales[[#This Row],[Order_Date]],"mmm") -> Jan | AB26: =YEAR(tbl_EcommerceSales[[#This Row],[Order_Date]]) -> 2025 | AC26: =IF(tbl_EcommerceSales[[#This Row],[Age]]<18,"Under 18",IF(tbl_EcommerceSales[[#This Row],[Age]]<=25,"18-25",IF(tbl_EcommerceSales[[#This Row],[Age]]<=35,"26-35",IF(tbl_EcommerceSales[[#This Row],[Age]]<=45,"36-45",IF(tbl_EcommerceSales[[#This Row],[Age]]<=55,"46-55","56+"))))) -> 26-35
A27: ORD101122 | B27: 45660 | C27: CUST0253 | D27: Kavya Patel | E27: Female | F27: 32 | G27: Bokaro | H27: East | I27: P028 | J27: Data Analytics Book | K27: Books | L27: Technology | M27: 4 | N27: 1099 | O27: 0.05 | P27: 2080 | Q27: Debit Card | R27: Cancelled | S27: Website | U27: =M27*N27 -> 4396 | V27: =tbl_EcommerceSales[[#This Row],[Gross_Sales]]*tbl_EcommerceSales[[#This Row],[Discount]] -> 219.8 | W27: =tbl_EcommerceSales[[#This Row],[Gross_Sales]]-tbl_EcommerceSales[[#This Row],[Discount_Amount]] -> 4176.2 | X27: =tbl_EcommerceSales[[#This Row],[Quantity]] * _xlfn.XLOOKUP(tbl_EcommerceSales[[#This Row],[Product_ID]], Product_Master!A:A, Product_Master!F:F) -> 2080 | Y27: =tbl_EcommerceSales[[#This Row],[Net_Revenue]]-tbl_EcommerceSales[[#This Row],[Total_Cost]] -> 2096.2 | Z27: =IFERROR(#REF!/tbl_EcommerceSales[[#This Row],[Total_Cost]], 0) -> 0 | AA27: =TEXT(tbl_EcommerceSales[[#This Row],[Order_Date]],"mmm") -> Jan | AB27: =YEAR(tbl_EcommerceSales[[#This Row],[Order_Date]]) -> 2025 | AC27: =IF(tbl_EcommerceSales[[#This Row],[Age]]<18,"Under 18",IF(tbl_EcommerceSales[[#This Row],[Age]]<=25,"18-25",IF(tbl_EcommerceSales[[#This Row],[Age]]<=35,"26-35",IF(tbl_EcommerceSales[[#This Row],[Age]]<=45,"36-45",IF(tbl_EcommerceSales[[#This Row],[Age]]<=55,"46-55","56+"))))) -> 26-35
A28: ORD103448 | B28: 45660 | C28: CUST1478 | D28: Kabir Gupta | E28: Female | F28: 29 | G28: Nashik | H28: West | I28: P024 | J28: Perfume | K28: Beauty | L28: Fragrance | M28: 2 | N28: 1799 | O28: 0.05 | P28: 1800 | Q28: Net Banking | R28: Returned | S28: Mobile App | T28: 4 | U28: =M28*N28 -> 3598 | V28: =tbl_EcommerceSales[[#This Row],[Gross_Sales]]*tbl_EcommerceSales[[#This Row],[Discount]] -> 179.9 | W28: =tbl_EcommerceSales[[#This Row],[Gross_Sales]]-tbl_EcommerceSales[[#This Row],[Discount_Amount]] -> 3418.1 | X28: =tbl_EcommerceSales[[#This Row],[Quantity]] * _xlfn.XLOOKUP(tbl_EcommerceSales[[#This Row],[Product_ID]], Product_Master!A:A, Product_Master!F:F) -> 1800 | Y28: =tbl_EcommerceSales[[#This Row],[Net_Revenue]]-tbl_EcommerceSales[[#This Row],[Total_Cost]] -> 1618.1 | Z28: =IFERROR(#REF!/tbl_EcommerceSales[[#This Row],[Total_Cost]], 0) -> 0 | AA28: =TEXT(tbl_EcommerceSales[[#This Row],[Order_Date]],"mmm") -> Jan | AB28: =YEAR(tbl_EcommerceSales[[#This Row],[Order_Date]]) -> 2025 | AC28: =IF(tbl_EcommerceSales[[#This Row],[Age]]<18,"Under 18",IF(tbl_EcommerceSales[[#This Row],[Age]]<=25,"18-25",IF(tbl_EcommerceSales[[#This Row],[Age]]<=35,"26-35",IF(tbl_EcommerceSales[[#This Row],[Age]]<=45,"36-45",IF(tbl_EcommerceSales[[#This Row],[Age]]<=55,"46-55","56+"))))) -> 26-35
A29: ORD102882 | B29: 45660 | C29: CUST1663 | D29: Shivam Mehta | E29: Female | F29: 29 | G29: Chandigarh | H29: North | I29: P006 | J29: Laptop Backpack | K29: Fashion | L29: Bags | M29: 1 | N29: 1799 | O29: 0.2 | P29: 950 | Q29: UPI | R29: Delivered | S29: Mobile App | T29: 3 | U29: =M29*N29 -> 1799 | V29: =tbl_EcommerceSales[[#This Row],[Gross_Sales]]*tbl_EcommerceSales[[#This Row],[Discount]] -> 359.8 | W29: =tbl_EcommerceSales[[#This Row],[Gross_Sales]]-tbl_EcommerceSales[[#This Row],[Discount_Amount]] -> 1439.2 | X29: =tbl_EcommerceSales[[#This Row],[Quantity]] * _xlfn.XLOOKUP(tbl_EcommerceSales[[#This Row],[Product_ID]], Product_Master!A:A, Product_Master!F:F) -> 950 | Y29: =tbl_EcommerceSales[[#This Row],[Net_Revenue]]-tbl_EcommerceSales[[#This Row],[Total_Cost]] -> 489.2 | Z29: =IFERROR(#REF!/tbl_EcommerceSales[[#This Row],[Total_Cost]], 0) -> 0 | AA29: =TEXT(tbl_EcommerceSales[[#This Row],[Order_Date]],"mmm") -> Jan | AB29: =YEAR(tbl_EcommerceSales[[#This Row],[Order_Date]]) -> 2025 | AC29: =IF(tbl_EcommerceSales[[#This Row],[Age]]<18,"Under 18",IF(tbl_EcommerceSales[[#This Row],[Age]]<=25,"18-25",IF(tbl_EcommerceSales[[#This Row],[Age]]<=35,"26-35",IF(tbl_EcommerceSales[[#This Row],[Age]]<=45,"36-45",IF(tbl_EcommerceSales[[#This Row],[Age]]<=55,"46-55","56+"))))) -> 26-35
A30: ORD101165 | B30: 45660 | C30: CUST0805 | D30: Akash Bansal | E30: Male | F30: 22 | G30: Delhi | H30: North | I30: P020 | J30: Resistance Bands | K30: Sports & Fitness | L30: Fitness | M30: 4 | N30: 699 | O30: 0.1 | P30: 1280 | Q30: Debit Card | R30: Cancelled | S30: Mobile App | U30: =M30*N30 -> 2796 | V30: =tbl_EcommerceSales[[#This Row],[Gross_Sales]]*tbl_EcommerceSales[[#This Row],[Discount]] -> 279.6 | W30: =tbl_EcommerceSales[[#This Row],[Gross_Sales]]-tbl_EcommerceSales[[#This Row],[Discount_Amount]] -> 2516.4 | X30: =tbl_EcommerceSales[[#This Row],[Quantity]] * _xlfn.XLOOKUP(tbl_EcommerceSales[[#This Row],[Product_ID]], Product_Master!A:A, Product_Master!F:F) -> 1280 | Y30: =tbl_EcommerceSales[[#This Row],[Net_Revenue]]-tbl_EcommerceSales[[#This Row],[Total_Cost]] -> 1236.4 | Z30: =IFERROR(#REF!/tbl_EcommerceSales[[#This Row],[Total_Cost]], 0) -> 0 | AA30: =TEXT(tbl_EcommerceSales[[#This Row],[Order_Date]],"mmm") -> Jan | AB30: =YEAR(tbl_EcommerceSales[[#This Row],[Order_Date]]) -> 2025 | AC30: =IF(tbl_EcommerceSales[[#This Row],[Age]]<18,"Under 18",IF(tbl_EcommerceSales[[#This Row],[Age]]<=25,"18-25",IF(tbl_EcommerceSales[[#This Row],[Age]]<=35,"26-35",IF(tbl_EcommerceSales[[#This Row],[Age]]<=45,"36-45",IF(tbl_EcommerceSales[[#This Row],[Age]]<=55,"46-55","56+"))))) -> 18-25
A31: ORD101571 | B31: 45660 | C31: CUST2050 | D31: Manish Agarwal | E31: Female | F31: 23 | G31: Nashik | H31: West | I31: P020 | J31: Resistance Bands | K31: Sports & Fitness | L31: Fitness | M31: 1 | N31: 699 | O31: 0 | P31: 320 | Q31: Net Banking | R31: Delivered | S31: Mobile App | T31: 5 | U31: =M31*N31 -> 699 | V31: =tbl_EcommerceSales[[#This Row],[Gross_Sales]]*tbl_EcommerceSales[[#This Row],[Discount]] -> 0 | W31: =tbl_EcommerceSales[[#This Row],[Gross_Sales]]-tbl_EcommerceSales[[#This Row],[Discount_Amount]] -> 699 | X31: =tbl_EcommerceSales[[#This Row],[Quantity]] * _xlfn.XLOOKUP(tbl_EcommerceSales[[#This Row],[Product_ID]], Product_Master!A:A, Product_Master!F:F) -> 320 | Y31: =tbl_EcommerceSales[[#This Row],[Net_Revenue]]-tbl_EcommerceSales[[#This Row],[Total_Cost]] -> 379 | Z31: =IFERROR(#REF!/tbl_EcommerceSales[[#This Row],[Total_Cost]], 0) -> 0 | AA31: =TEXT(tbl_EcommerceSales[[#This Row],[Order_Date]],"mmm") -> Jan | AB31: =YEAR(tbl_EcommerceSales[[#This Row],[Order_Date]]) -> 2025 | AC31: =IF(tbl_EcommerceSales[[#This Row],[Age]]<18,"Under 18",IF(tbl_EcommerceSales[[#This Row],[Age]]<=25,"18-25",IF(tbl_EcommerceSales[[#This Row],[Age]]<=35,"26-35",IF(tbl_EcommerceSales[[#This Row],[Age]]<=45,"36-45",IF(tbl_EcommerceSales[[#This Row],[Age]]<=55,"46-55","56+"))))) -> 18-25
A32: ORD103305 | B32: 45660 | C32: CUST1100 | D32: Rahul Kumar | E32: Male | F32: 27 | G32: Coimbatore | H32: South | I32: P001 | J32: Wireless Headphones | K32: Electronics | L32: Audio | M32: 1 | N32: 2499 | O32: 0.05 | P32: 1550 | Q32: UPI | R32: Delivered | S32: Website | T32: 5 | U32: =M32*N32 -> 2499 | V32: =tbl_EcommerceSales[[#This Row],[Gross_Sales]]*tbl_EcommerceSales[[#This Row],[Discount]] -> 124.95 | W32: =tbl_EcommerceSales[[#This Row],[Gross_Sales]]-tbl_EcommerceSales[[#This Row],[Discount_Amount]] -> 2374.05 | X32: =tbl_EcommerceSales[[#This Row],[Quantity]] * _xlfn.XLOOKUP(tbl_EcommerceSales[[#This Row],[Product_ID]], Product_Master!A:A, Product_Master!F:F) -> 1550 | Y32: =tbl_EcommerceSales[[#This Row],[Net_Revenue]]-tbl_EcommerceSales[[#This Row],[Total_Cost]] -> 824.05 | Z32: =IFERROR(#REF!/tbl_EcommerceSales[[#This Row],[Total_Cost]], 0) -> 0 | AA32: =TEXT(tbl_EcommerceSales[[#This Row],[Order_Date]],"mmm") -> Jan | AB32: =YEAR(tbl_EcommerceSales[[#This Row],[Order_Date]]) -> 2025 | AC32: =IF(tbl_EcommerceSales[[#This Row],[Age]]<18,"Under 18",IF(tbl_EcommerceSales[[#This Row],[Age]]<=25,"18-25",IF(tbl_EcommerceSales[[#This Row],[Age]]<=35,"26-35",IF(tbl_EcommerceSales[[#This Row],[Age]]<=45,"36-45",IF(tbl_EcommerceSales[[#This Row],[Age]]<=55,"46-55","56+"))))) -> 26-35
A33: ORD104066 | B33: 45661 | C33: CUST2024 | D33: Sanya Malhotra | E33: Female | F33: 18 | G33: Kochi | H33: South | I33: P024 | J33: Perfume | K33: Beauty | L33: Fragrance | M33: 1 | N33: 1799 | O33: 0.1 | P33: 900 | Q33: UPI | R33: Delivered | S33: Mobile App | T33: 3 | U33: =M33*N33 -> 1799 | V33: =tbl_EcommerceSales[[#This Row],[Gross_Sales]]*tbl_EcommerceSales[[#This Row],[Discount]] -> 179.9 | W33: =tbl_EcommerceSales[[#This Row],[Gross_Sales]]-tbl_EcommerceSales[[#This Row],[Discount_Amount]] -> 1619.1 | X33: =tbl_EcommerceSales[[#This Row],[Quantity]] * _xlfn.XLOOKUP(tbl_EcommerceSales[[#This Row],[Product_ID]], Product_Master!A:A, Product_Master!F:F) -> 900 | Y33: =tbl_EcommerceSales[[#This Row],[Net_Revenue]]-tbl_EcommerceSales[[#This Row],[Total_Cost]] -> 719.1 | Z33: =IFERROR(#REF!/tbl_EcommerceSales[[#This Row],[Total_Cost]], 0) -> 0 | AA33: =TEXT(tbl_EcommerceSales[[#This Row],[Order_Date]],"mmm") -> Jan | AB33: =YEAR(tbl_EcommerceSales[[#This Row],[Order_Date]]) -> 2025 | AC33: =IF(tbl_EcommerceSales[[#This Row],[Age]]<18,"Under 18",IF(tbl_EcommerceSales[[#This Row],[Age]]<=25,"18-25",IF(tbl_EcommerceSales[[#This Row],[Age]]<=35,"26-35",IF(tbl_EcommerceSales[[#This Row],[Age]]<=45,"36-45",IF(tbl_EcommerceSales[[#This Row],[Age]]<=55,"46-55","56+"))))) -> 18-25
A34: ORD104229 | B34: 45661 | C34: CUST0960 | D34: Aarav Sharma | E34: Male | F34: 36 | G34: Surat | H34: West | I34: P030 | J34: Self Help Book | K34: Books | L34: Self Development | M34: 4 | N34: 599 | O34: 0.15 | P34: 1040 | Q34: UPI | R34: Delivered | S34: Website | T34: 2 | U34: =M34*N34 -> 2396 | V34: =tbl_EcommerceSales[[#This Row],[Gross_Sales]]*tbl_EcommerceSales[[#This Row],[Discount]] -> 359.4 | W34: =tbl_EcommerceSales[[#This Row],[Gross_Sales]]-tbl_EcommerceSales[[#This Row],[Discount_Amount]] -> 2036.6 | X34: =tbl_EcommerceSales[[#This Row],[Quantity]] * _xlfn.XLOOKUP(tbl_EcommerceSales[[#This Row],[Product_ID]], Product_Master!A:A, Product_Master!F:F) -> 1040 | Y34: =tbl_EcommerceSales[[#This Row],[Net_Revenue]]-tbl_EcommerceSales[[#This Row],[Total_Cost]] -> 996.6 | Z34: =IFERROR(#REF!/tbl_EcommerceSales[[#This Row],[Total_Cost]], 0) -> 0 | AA34: =TEXT(tbl_EcommerceSales[[#This Row],[Order_Date]],"mmm") -> Jan | AB34: =YEAR(tbl_EcommerceSales[[#This Row],[Order_Date]]) -> 2025 | AC34: =IF(tbl_EcommerceSales[[#This Row],[Age]]<18,"Under 18",IF(tbl_EcommerceSales[[#This Row],[Age]]<=25,"18-25",IF(tbl_EcommerceSales[[#This Row],[Age]]<=35,"26-35",IF(tbl_EcommerceSales[[#This Row],[Age]]<=45,"36-45",IF(tbl_EcommerceSales[[#This Row],[Age]]<=55,"46-55","56+"))))) -> 36-45
A35: ORD100717 | B35: 45661 | C35: CUST0460 | D35: Rahul Kumar | E35: Female | F35: 32 | G35: Guwahati | H35: East | I35: P029 | J35: Programming Book | K35: Books | L35: Technology | M35: 1 | N35: 1299 | O35: 0.1 | P35: 610 | Q35: Credit Card | R35: Delivered | S35: Website | T35: 5 | U35: =M35*N35 -> 1299 | V35: =tbl_EcommerceSales[[#This Row],[Gross_Sales]]*tbl_EcommerceSales[[#This Row],[Discount]] -> 129.9 | W35: =tbl_EcommerceSales[[#This Row],[Gross_Sales]]-tbl_EcommerceSales[[#This Row],[Discount_Amount]] -> 1169.1 | X35: =tbl_EcommerceSales[[#This Row],[Quantity]] * _xlfn.XLOOKUP(tbl_EcommerceSales[[#This Row],[Product_ID]], Product_Master!A:A, Product_Master!F:F) -> 610 | Y35: =tbl_EcommerceSales[[#This Row],[Net_Revenue]]-tbl_EcommerceSales[[#This Row],[Total_Cost]] -> 559.1 | Z35: =IFERROR(#REF!/tbl_EcommerceSales[[#This Row],[Total_Cost]], 0) -> 0 | AA35: =TEXT(tbl_EcommerceSales[[#This Row],[Order_Date]],"mmm") -> Jan | AB35: =YEAR(tbl_EcommerceSales[[#This Row],[Order_Date]]) -> 2025 | AC35: =IF(tbl_EcommerceSales[[#This Row],[Age]]<18,"Under 18",IF(tbl_EcommerceSales[[#This Row],[Age]]<=25,"18-25",IF(tbl_EcommerceSales[[#This Row],[Age]]<=35,"26-35",IF(tbl_EcommerceSales[[#This Row],[Age]]<=45,"36-45",IF(tbl_EcommerceSales[[#This Row],[Age]]<=55,"46-55","56+"))))) -> 26-35
A36: ORD100974 | B36: 45661 | C36: CUST0011 | D36: Kiara Chopra | E36: Female | F36: 37 | G36: Kolkata | H36: East | I36: P024 | J36: Perfume | K36: Beauty | L36: Fragrance | M36: 1 | N36: 1799 | O36: 0.2 | P36: 900 | Q36: UPI | R36: Returned | S36: Website | T36: 5 | U36: =M36*N36 -> 1799 | V36: =tbl_EcommerceSales[[#This Row],[Gross_Sales]]*tbl_EcommerceSales[[#This Row],[Discount]] -> 359.8 | W36: =tbl_EcommerceSales[[#This Row],[Gross_Sales]]-tbl_EcommerceSales[[#This Row],[Discount_Amount]] -> 1439.2 | X36: =tbl_EcommerceSales[[#This Row],[Quantity]] * _xlfn.XLOOKUP(tbl_EcommerceSales[[#This Row],[Product_ID]], Product_Master!A:A, Product_Master!F:F) -> 900 | Y36: =tbl_EcommerceSales[[#This Row],[Net_Revenue]]-tbl_EcommerceSales[[#This Row],[Total_Cost]] -> 539.2 | Z36: =IFERROR(#REF!/tbl_EcommerceSales[[#This Row],[Total_Cost]], 0) -> 0 | AA36: =TEXT(tbl_EcommerceSales[[#This Row],[Order_Date]],"mmm") -> Jan | AB36: =YEAR(tbl_EcommerceSales[[#This Row],[Order_Date]]) -> 2025 | AC36: =IF(tbl_EcommerceSales[[#This Row],[Age]]<18,"Under 18",IF(tbl_EcommerceSales[[#This Row],[Age]]<=25,"18-25",IF(tbl_EcommerceSales[[#This Row],[Age]]<=35,"26-35",IF(tbl_EcommerceSales[[#This Row],[Age]]<=45,"36-45",IF(tbl_EcommerceSales[[#This Row],[Age]]<=55,"46-55","56+"))))) -> 36-45
A37: ORD103001 | B37: 45661 | C37: CUST0840 | D37: Sanya Malhotra | E37: Male | F37: 26 | G37: Surat | H37: West | I37: P024 | J37: Perfume | K37: Beauty | L37: Fragrance | M37: 2 | N37: 1799 | O37: 0.2 | P37: 1800 | Q37: UPI | R37: Delivered | S37: Website | T37: 5 | U37: =M37*N37 -> 3598 | V37: =tbl_EcommerceSales[[#This Row],[Gross_Sales]]*tbl_EcommerceSales[[#This Row],[Discount]] -> 719.6 | W37: =tbl_EcommerceSales[[#This Row],[Gross_Sales]]-tbl_EcommerceSales[[#This Row],[Discount_Amount]] -> 2878.4 | X37: =tbl_EcommerceSales[[#This Row],[Quantity]] * _xlfn.XLOOKUP(tbl_EcommerceSales[[#This Row],[Product_ID]], Product_Master!A:A, Product_Master!F:F) -> 1800 | Y37: =tbl_EcommerceSales[[#This Row],[Net_Revenue]]-tbl_EcommerceSales[[#This Row],[Total_Cost]] -> 1078.4 | Z37: =IFERROR(#REF!/tbl_EcommerceSales[[#This Row],[Total_Cost]], 0) -> 0 | AA37: =TEXT(tbl_EcommerceSales[[#This Row],[Order_Date]],"mmm") -> Jan | AB37: =YEAR(tbl_EcommerceSales[[#This Row],[Order_Date]]) -> 2025 | AC37: =IF(tbl_EcommerceSales[[#This Row],[Age]]<18,"Under 18",IF(tbl_EcommerceSales[[#This Row],[Age]]<=25,"18-25",IF(tbl_EcommerceSales[[#This Row],[Age]]<=35,"26-35",IF(tbl_EcommerceSales[[#This Row],[Age]]<=45,"36-45",IF(tbl_EcommerceSales[[#This Row],[Age]]<=55,"46-55","56+"))))) -> 26-35
A38: ORD103955 | B38: 45662 | C38: CUST1401 | D38: Meera Singh | E38: Male | F38: 37 | G38: Kochi | H38: South | I38: P026 | J38: Novel Collection | K38: Books | L38: Fiction | M38: 1 | N38: 899 | O38: 0.05 | P38: 420 | Q38: Credit Card | R38: Delivered | S38: Mobile App | T38: 5 | U38: =M38*N38 -> 899 | V38: =tbl_EcommerceSales[[#This Row],[Gross_Sales]]*tbl_EcommerceSales[[#This Row],[Discount]] -> 44.95 | W38: =tbl_EcommerceSales[[#This Row],[Gross_Sales]]-tbl_EcommerceSales[[#This Row],[Discount_Amount]] -> 854.05 | X38: =tbl_EcommerceSales[[#This Row],[Quantity]] * _xlfn.XLOOKUP(tbl_EcommerceSales[[#This Row],[Product_ID]], Product_Master!A:A, Product_Master!F:F) -> 420 | Y38: =tbl_EcommerceSales[[#This Row],[Net_Revenue]]-tbl_EcommerceSales[[#This Row],[Total_Cost]] -> 434.05 | Z38: =IFERROR(#REF!/tbl_EcommerceSales[[#This Row],[Total_Cost]], 0) -> 0 | AA38: =TEXT(tbl_EcommerceSales[[#This Row],[Order_Date]],"mmm") -> Jan | AB38: =YEAR(tbl_EcommerceSales[[#This Row],[Order_Date]]) -> 2025 | AC38: =IF(tbl_EcommerceSales[[#This Row],[Age]]<18,"Under 18",IF(tbl_EcommerceSales[[#This Row],[Age]]<=25,"18-25",IF(tbl_EcommerceSales[[#This Row],[Age]]<=35,"26-35",IF(tbl_EcommerceSales[[#This Row],[Age]]<=45,"36-45",IF(tbl_EcommerceSales[[#This Row],[Age]]<=55,"46-55","56+"))))) -> 36-45
A39: ORD104005 | B39: 45662 | C39: CUST1988 | D39: Varun Jain | E39: Female | F39: 27 | G39: Kolkata | H39: East | I39: P018 | J39: Cricket Bat | K39: Sports & Fitness | L39: Sports | M39: 1 | N39: 2199 | O39: 0.05 | P39: 1250 | Q39: Credit Card | R39: Delivered | S39: Mobile App | T39: 5 | U39: =M39*N39 -> 2199 | V39: =tbl_EcommerceSales[[#This Row],[Gross_Sales]]*tbl_EcommerceSales[[#This Row],[Discount]] -> 109.95 | W39: =tbl_EcommerceSales[[#This Row],[Gross_Sales]]-tbl_EcommerceSales[[#This Row],[Discount_Amount]] -> 2089.05 | X39: =tbl_EcommerceSales[[#This Row],[Quantity]] * _xlfn.XLOOKUP(tbl_EcommerceSales[[#This Row],[Product_ID]], Product_Master!A:A, Product_Master!F:F) -> 1250 | Y39: =tbl_EcommerceSales[[#This Row],[Net_Revenue]]-tbl_EcommerceSales[[#This Row],[Total_Cost]] -> 839.05 | Z39: =IFERROR(#REF!/tbl_EcommerceSales[[#This Row],[Total_Cost]], 0) -> 0 | AA39: =TEXT(tbl_EcommerceSales[[#This Row],[Order_Date]],"mmm") -> Jan | AB39: =YEAR(tbl_EcommerceSales[[#This Row],[Order_Date]]) -> 2025 | AC39: =IF(tbl_EcommerceSales[[#This Row],[Age]]<18,"Under 18",IF(tbl_EcommerceSales[[#This Row],[Age]]<=25,"18-25",IF(tbl_EcommerceSales[[#This Row],[Age]]<=35,"26-35",IF(tbl_EcommerceSales[[#This Row],[Age]]<=45,"36-45",IF(tbl_EcommerceSales[[#This Row],[Age]]<=55,"46-55","56+"))))) -> 26-35
A40: ORD100306 | B40: 45662 | C40: CUST0421 | D40: Akash Bansal | E40: Female | F40: 44 | G40: Bengaluru | H40: South | I40: P017 | J40: Dumbbell Set | K40: Sports & Fitness | L40: Fitness | M40: 1 | N40: 2499 | O40: 0 | P40: 1450 | Q40: UPI | R40: Delivered | S40: Mobile App | T40: 5 | U40: =M40*N40 -> 2499 | V40: =tbl_EcommerceSales[[#This Row],[Gross_Sales]]*tbl_EcommerceSales[[#This Row],[Discount]] -> 0 | W40: =tbl_EcommerceSales[[#This Row],[Gross_Sales]]-tbl_EcommerceSales[[#This Row],[Discount_Amount]] -> 2499 | X40: =tbl_EcommerceSales[[#This Row],[Quantity]] * _xlfn.XLOOKUP(tbl_EcommerceSales[[#This Row],[Product_ID]], Product_Master!A:A, Product_Master!F:F) -> 1450 | Y40: =tbl_EcommerceSales[[#This Row],[Net_Revenue]]-tbl_EcommerceSales[[#This Row],[Total_Cost]] -> 1049 | Z40: =IFERROR(#REF!/tbl_EcommerceSales[[#This Row],[Total_Cost]], 0) -> 0 | AA40: =TEXT(tbl_EcommerceSales[[#This Row],[Order_Date]],"mmm") -> Jan | AB40: =YEAR(tbl_EcommerceSales[[#This Row],[Order_Date]]) -> 2025 | AC40: =IF(tbl_EcommerceSales[[#This Row],[Age]]<18,"Under 18",IF(tbl_EcommerceSales[[#This Row],[Age]]<=25,"18-25",IF(tbl_EcommerceSales[[#This Row],[Age]]<=35,"26-35",IF(tbl_EcommerceSales[[#This Row],[Age]]<=45,"36-45",IF(tbl_EcommerceSales[[#This Row],[Age]]<=55,"46-55","56+"))))) -> 36-45
A41: ORD103908 | B41: 45662 | C41: CUST0731 | D41: Vansh Chopra | E41: Male | F41: 35 | G41: Nashik | H41: West | I41: P008 | J41: Cotton T-Shirt | K41: Fashion | L41: Clothing | M41: 1 | N41: 799 | O41: 0.1 | P41: 390 | Q41: UPI | R41: Delivered | S41: Website | T41: 3 | U41: =M41*N41 -> 799 | V41: =tbl_EcommerceSales[[#This Row],[Gross_Sales]]*tbl_EcommerceSales[[#This Row],[Discount]] -> 79.9 | W41: =tbl_EcommerceSales[[#This Row],[Gross_Sales]]-tbl_EcommerceSales[[#This Row],[Discount_Amount]] -> 719.1 | X41: =tbl_EcommerceSales[[#This Row],[Quantity]] * _xlfn.XLOOKUP(tbl_EcommerceSales[[#This Row],[Product_ID]], Product_Master!A:A, Product_Master!F:F) -> 390 | Y41: =tbl_EcommerceSales[[#This Row],[Net_Revenue]]-tbl_EcommerceSales[[#This Row],[Total_Cost]] -> 329.1 | Z41: =IFERROR(#REF!/tbl_EcommerceSales[[#This Row],[Total_Cost]], 0) -> 0 | AA41: =TEXT(tbl_EcommerceSales[[#This Row],[Order_Date]],"mmm") -> Jan | AB41: =YEAR(tbl_EcommerceSales[[#This Row],[Order_Date]]) -> 2025 | AC41: =IF(tbl_EcommerceSales[[#This Row],[Age]]<18,"Under 18",IF(tbl_EcommerceSales[[#This Row],[Age]]<=25,"18-25",IF(tbl_EcommerceSales[[#This Row],[Age]]<=35,"26-35",IF(tbl_EcommerceSales[[#This Row],[Age]]<=45,"36-45",IF(tbl_EcommerceSales[[#This Row],[Age]]<=55,"46-55","56+"))))) -> 26-35
A42: ORD102867 | B42: 45662 | C42: CUST0859 | D42: Vansh Chopra | E42: Female | F42: 33 | G42: Dehradun | H42: North | I42: P021 | J42: Face Wash | K42: Beauty | L42: Skincare | M42: 1 | N42: 499 | O42: 0.15 | P42: 220 | Q42: UPI | R42: Delivered | S42: Website | T42: 5 | U42: =M42*N42 -> 499 | V42: =tbl_EcommerceSales[[#This Row],[Gross_Sales]]*tbl_EcommerceSales[[#This Row],[Discount]] -> 74.85 | W42: =tbl_EcommerceSales[[#This Row],[Gross_Sales]]-tbl_EcommerceSales[[#This Row],[Discount_Amount]] -> 424.15 | X42: =tbl_EcommerceSales[[#This Row],[Quantity]] * _xlfn.XLOOKUP(tbl_EcommerceSales[[#This Row],[Product_ID]], Product_Master!A:A, Product_Master!F:F) -> 220 | Y42: =tbl_EcommerceSales[[#This Row],[Net_Revenue]]-tbl_EcommerceSales[[#This Row],[Total_Cost]] -> 204.15 | Z42: =IFERROR(#REF!/tbl_EcommerceSales[[#This Row],[Total_Cost]], 0) -> 0 | AA42: =TEXT(tbl_EcommerceSales[[#This Row],[Order_Date]],"mmm") -> Jan | AB42: =YEAR(tbl_EcommerceSales[[#This Row],[Order_Date]]) -> 2025 | AC42: =IF(tbl_EcommerceSales[[#This Row],[Age]]<18,"Under 18",IF(tbl_EcommerceSales[[#This Row],[Age]]<=25,"18-25",IF(tbl_EcommerceSales[[#This Row],[Age]]<=35,"26-35",IF(tbl_EcommerceSales[[#This Row],[Age]]<=45,"36-45",IF(tbl_EcommerceSales[[#This Row],[Age]]<=55,"46-55","56+"))))) -> 26-35
... A100: ORD101578 | B100: 45669 | C100: CUST0669 | D100: Kavya Patel | E100: Male | F100: 30 | G100: Delhi | H100: North | I100: P030 | J100: Self Help Book | K100: Books | L100: Self Development | M100: 1 | N100: 599 | O100: 0.05 | P100: 260 | Q100: Cash on Delivery | R100: Returned | S100: Mobile App | T100: 5 | U100: =M100*N100 -> 599 | V100: =tbl_EcommerceSales[[#This Row],[Gross_Sales]]*tbl_EcommerceSales[[#This Row],[Discount]] -> 29.95 | W100: =tbl_EcommerceSales[[#This Row],[Gross_Sales]]-tbl_EcommerceSales[[#This Row],[Discount_Amount]] -> 569.05 | X100: =tbl_EcommerceSales[[#This Row],[Quantity]] * _xlfn.XLOOKUP(tbl_EcommerceSales[[#This Row],[Product_ID]], Product_Master!A:A, Product_Master!F:F) -> 260 | Y100: =tbl_EcommerceSales[[#This Row],[Net_Revenue]]-tbl_EcommerceSales[[#This Row],[Total_Cost]] -> 309.05 | Z100: =IFERROR(#REF!/tbl_EcommerceSales[[#This Row],[Total_Cost]], 0) -> 0 | AA100: =TEXT(tbl_EcommerceSales[[#This Row],[Order_Date]],"mmm") -> Jan | AB100: =YEAR(tbl_EcommerceSales[[#This Row],[Order_Date]]) -> 2025 | AC100: =IF(tbl_EcommerceSales[[#This Row],[Age]]<18,"Under 18",IF(tbl_EcommerceSales[[#This Row],[Age]]<=25,"18-25",IF(tbl_EcommerceSales[[#This Row],[Age]]<=35,"26-35",IF(tbl_EcommerceSales[[#This Row],[Age]]<=45,"36-45",IF(tbl_EcommerceSales[[#This Row],[Age]]<=55,"46-55","56+"))))) -> 26-35
A101: ORD102698 | B101: 45669 | C101: CUST2127 | D101: Isha Mehta | E101: Male | F101: 33 | G101: Surat | H101: West | I101: P009 | J101: Denim Jeans | K101: Fashion | L101: Clothing | M101: 1 | N101: 1999 | O101: 0.1 | P101: 1050 | Q101: Debit Card | R101: Cancelled | S101: Mobile App | U101: =M101*N101 -> 1999 | V101: =tbl_EcommerceSales[[#This Row],[Gross_Sales]]*tbl_EcommerceSales[[#This Row],[Discount]] -> 199.9 | W101: =tbl_EcommerceSales[[#This Row],[Gross_Sales]]-tbl_EcommerceSales[[#This Row],[Discount_Amount]] -> 1799.1 | X101: =tbl_EcommerceSales[[#This Row],[Quantity]] * _xlfn.XLOOKUP(tbl_EcommerceSales[[#This Row],[Product_ID]], Product_Master!A:A, Product_Master!F:F) -> 1050 | Y101: =tbl_EcommerceSales[[#This Row],[Net_Revenue]]-tbl_EcommerceSales[[#This Row],[Total_Cost]] -> 749.1 | Z101: =IFERROR(#REF!/tbl_EcommerceSales[[#This Row],[Total_Cost]], 0) -> 0 | AA101: =TEXT(tbl_EcommerceSales[[#This Row],[Order_Date]],"mmm") -> Jan | AB101: =YEAR(tbl_EcommerceSales[[#This Row],[Order_Date]]) -> 2025 | AC101: =IF(tbl_EcommerceSales[[#This Row],[Age]]<18,"Under 18",IF(tbl_EcommerceSales[[#This Row],[Age]]<=25,"18-25",IF(tbl_EcommerceSales[[#This Row],[Age]]<=35,"26-35",IF(tbl_EcommerceSales[[#This Row],[Age]]<=45,"36-45",IF(tbl_EcommerceSales[[#This Row],[Age]]<=55,"46-55","56+"))))) -> 26-35
A102: ORD104272 | B102: 45669 | C102: CUST2008 | D102: Ishaan Malhotra | E102: Male | F102: 39 | G102: Delhi | H102: North | I102: P007 | J102: Running Shoes | K102: Fashion | L102: Footwear | M102: 1 | N102: 2899 | O102: 0.1 | P102: 1700 | Q102: Wallet | R102: Delivered | S102: Mobile App | T102: 5 | U102: =M102*N102 -> 2899 | V102: =tbl_EcommerceSales[[#This Row],[Gross_Sales]]*tbl_EcommerceSales[[#This Row],[Discount]] -> 289.9 | W102: =tbl_EcommerceSales[[#This Row],[Gross_Sales]]-tbl_EcommerceSales[[#This Row],[Discount_Amount]] -> 2609.1 | X102: =tbl_EcommerceSales[[#This Row],[Quantity]] * _xlfn.XLOOKUP(tbl_EcommerceSales[[#This Row],[Product_ID]], Product_Master!A:A, Product_Master!F:F) -> 1700 | Y102: =tbl_EcommerceSales[[#This Row],[Net_Revenue]]-tbl_EcommerceSales[[#This Row],[Total_Cost]] -> 909.1 | Z102: =IFERROR(#REF!/tbl_EcommerceSales[[#This Row],[Total_Cost]], 0) -> 0 | AA102: =TEXT(tbl_EcommerceSales[[#This Row],[Order_Date]],"mmm") -> Jan | AB102: =YEAR(tbl_EcommerceSales[[#This Row],[Order_Date]]) -> 2025 | AC102: =IF(tbl_EcommerceSales[[#This Row],[Age]]<18,"Under 18",IF(tbl_EcommerceSales[[#This Row],[Age]]<=25,"18-25",IF(tbl_EcommerceSales[[#This Row],[Age]]<=35,"26-35",IF(tbl_EcommerceSales[[#This Row],[Age]]<=45,"36-45",IF(tbl_EcommerceSales[[#This Row],[Age]]<=55,"46-55","56+"))))) -> 36-45
A103: ORD103128 | B103: 45669 | C103: CUST0530 | D103: Yash Agarwal | E103: Male | F103: 35 | G103: Kochi | H103: South | I103: P008 | J103: Cotton T-Shirt | K103: Fashion | L103: Clothing | M103: 1 | N103: 799 | O103: 0.1 | P103: 390 | Q103: Credit Card | R103: Delivered | S103: Website | T103: 4 | U103: =M103*N103 -> 799 | V103: =tbl_EcommerceSales[[#This Row],[Gross_Sales]]*tbl_EcommerceSales[[#This Row],[Discount]] -> 79.9 | W103: =tbl_EcommerceSales[[#This Row],[Gross_Sales]]-tbl_EcommerceSales[[#This Row],[Discount_Amount]] -> 719.1 | X103: =tbl_EcommerceSales[[#This Row],[Quantity]] * _xlfn.XLOOKUP(tbl_EcommerceSales[[#This Row],[Product_ID]], Product_Master!A:A, Product_Master!F:F) -> 390 | Y103: =tbl_EcommerceSales[[#This Row],[Net_Revenue]]-tbl_EcommerceSales[[#This Row],[Total_Cost]] -> 329.1 | Z103: =IFERROR(#REF!/tbl_EcommerceSales[[#This Row],[Total_Cost]], 0) -> 0 | AA103: =TEXT(tbl_EcommerceSales[[#This Row],[Order_Date]],"mmm") -> Jan | AB103: =YEAR(tbl_EcommerceSales[[#This Row],[Order_Date]]) -> 2025 | AC103: =IF(tbl_EcommerceSales[[#This Row],[Age]]<18,"Under 18",IF(tbl_EcommerceSales[[#This Row],[Age]]<=25,"18-25",IF(tbl_EcommerceSales[[#This Row],[Age]]<=35,"26-35",IF(tbl_EcommerceSales[[#This Row],[Age]]<=45,"36-45",IF(tbl_EcommerceSales[[#This Row],[Age]]<=55,"46-55","56+"))))) -> 26-35
A104: ORD104246 | B104: 45669 | C104: CUST1268 | D104: Karan Jain | E104: Female | F104: 40 | G104: Pune | H104: West | I104: P005 | J104: Power Bank 20000mAh | K104: Electronics | L104: Accessories | M104: 3 | N104: 1599 | O104: 0.15 | P104: 2760 | Q104: Net Banking | R104: Delivered | S104: Mobile App | T104: 4 | U104: =M104*N104 -> 4797 | V104: =tbl_EcommerceSales[[#This Row],[Gross_Sales]]*tbl_EcommerceSales[[#This Row],[Discount]] -> 719.55 | W104: =tbl_EcommerceSales[[#This Row],[Gross_Sales]]-tbl_EcommerceSales[[#This Row],[Discount_Amount]] -> 4077.45 | X104: =tbl_EcommerceSales[[#This Row],[Quantity]] * _xlfn.XLOOKUP(tbl_EcommerceSales[[#This Row],[Product_ID]], Product_Master!A:A, Product_Master!F:F) -> 2760 | Y104: =tbl_EcommerceSales[[#This Row],[Net_Revenue]]-tbl_EcommerceSales[[#This Row],[Total_Cost]] -> 1317.45 | Z104: =IFERROR(#REF!/tbl_EcommerceSales[[#This Row],[Total_Cost]], 0) -> 0 | AA104: =TEXT(tbl_EcommerceSales[[#This Row],[Order_Date]],"mmm") -> Jan | AB104: =YEAR(tbl_EcommerceSales[[#This Row],[Order_Date]]) -> 2025 | AC104: =IF(tbl_EcommerceSales[[#This Row],[Age]]<18,"Under 18",IF(tbl_EcommerceSales[[#This Row],[Age]]<=25,"18-25",IF(tbl_EcommerceSales[[#This Row],[Age]]<=35,"26-35",IF(tbl_EcommerceSales[[#This Row],[Age]]<=45,"36-45",IF(tbl_EcommerceSales[[#This Row],[Age]]<=55,"46-55","56+"))))) -> 36-45
A105: ORD101389 | B105: 45669 | C105: CUST0168 | D105: Sanya Malhotra | E105: Male | F105: 38 | G105: Ranchi | H105: East | I105: P024 | J105: Perfume | K105: Beauty | L105: Fragrance | M105: 1 | N105: 1799 | O105: 0.1 | P105: 900 | Q105: Credit Card | R105: Delivered | S105: Website | T105: 5 | U105: =M105*N105 -> 1799 | V105: =tbl_EcommerceSales[[#This Row],[Gross_Sales]]*tbl_EcommerceSales[[#This Row],[Discount]] -> 179.9 | W105: =tbl_EcommerceSales[[#This Row],[Gross_Sales]]-tbl_EcommerceSales[[#This Row],[Discount_Amount]] -> 1619.1 | X105: =tbl_EcommerceSales[[#This Row],[Quantity]] * _xlfn.XLOOKUP(tbl_EcommerceSales[[#This Row],[Product_ID]], Product_Master!A:A, Product_Master!F:F) -> 900 | Y105: =tbl_EcommerceSales[[#This Row],[Net_Revenue]]-tbl_EcommerceSales[[#This Row],[Total_Cost]] -> 719.1 | Z105: =IFERROR(#REF!/tbl_EcommerceSales[[#This Row],[Total_Cost]], 0) -> 0 | AA105: =TEXT(tbl_EcommerceSales[[#This Row],[Order_Date]],"mmm") -> Jan | AB105: =YEAR(tbl_EcommerceSales[[#This Row],[Order_Date]]) -> 2025 | AC105: =IF(tbl_EcommerceSales[[#This Row],[Age]]<18,"Under 18",IF(tbl_EcommerceSales[[#This Row],[Age]]<=25,"18-25",IF(tbl_EcommerceSales[[#This Row],[Age]]<=35,"26-35",IF(tbl_EcommerceSales[[#This Row],[Age]]<=45,"36-45",IF(tbl_EcommerceSales[[#This Row],[Age]]<=55,"46-55","56+"))))) -> 36-45
A106: ORD100372 | B106: 45669 | C106: CUST1974 | D106: Simran Gupta | E106: Female | F106: 33 | G106: Kochi | H106: South | I106: P026 | J106: Novel Collection | K106: Books | L106: Fiction | M106: 1 | N106: 899 | O106: 0.2 | P106: 420 | Q106: Credit Card | R106: Delivered | S106: Website | T106: 3 | U106: =M106*N106 -> 899 | V106: =tbl_EcommerceSales[[#This Row],[Gross_Sales]]*tbl_EcommerceSales[[#This Row],[Discount]] -> 179.8 | W106: =tbl_EcommerceSales[[#This Row],[Gross_Sales]]-tbl_EcommerceSales[[#This Row],[Discount_Amount]] -> 719.2 | X106: =tbl_EcommerceSales[[#This Row],[Quantity]] * _xlfn.XLOOKUP(tbl_EcommerceSales[[#This Row],[Product_ID]], Product_Master!A:A, Product_Master!F:F) -> 420 | Y106: =tbl_EcommerceSales[[#This Row],[Net_Revenue]]-tbl_EcommerceSales[[#This Row],[Total_Cost]] -> 299.2 | Z106: =IFERROR(#REF!/tbl_EcommerceSales[[#This Row],[Total_Cost]], 0) -> 0 | AA106: =TEXT(tbl_EcommerceSales[[#This Row],[Order_Date]],"mmm") -> Jan | AB106: =YEAR(tbl_EcommerceSales[[#This Row],[Order_Date]]) -> 2025 | AC106: =IF(tbl_EcommerceSales[[#This Row],[Age]]<18,"Under 18",IF(tbl_EcommerceSales[[#This Row],[Age]]<=25,"18-25",IF(tbl_EcommerceSales[[#This Row],[Age]]<=35,"26-35",IF(tbl_EcommerceSales[[#This Row],[Age]]<=45,"36-45",IF(tbl_EcommerceSales[[#This Row],[Age]]<=55,"46-55","56+"))))) -> 26-35
A107: ORD101706 | B107: 45669 | C107: CUST2101 | D107: Pranav Bansal | E107: Male | F107: 26 | G107: Dehradun | H107: North | I107: P002 | J107: Bluetooth Speaker | K107: Electronics | L107: Audio | M107: 3 | N107: 1899 | O107: 0 | P107: 3360 | Q107: Net Banking | R107: Delivered | S107: Website | T107: 3 | U107: =M107*N107 -> 5697 | V107: =tbl_EcommerceSales[[#This Row],[Gross_Sales]]*tbl_EcommerceSales[[#This Row],[Discount]] -> 0 | W107: =tbl_EcommerceSales[[#This Row],[Gross_Sales]]-tbl_EcommerceSales[[#This Row],[Discount_Amount]] -> 5697 | X107: =tbl_EcommerceSales[[#This Row],[Quantity]] * _xlfn.XLOOKUP(tbl_EcommerceSales[[#This Row],[Product_ID]], Product_Master!A:A, Product_Master!F:F) -> 3360 | Y107: =tbl_EcommerceSales[[#This Row],[Net_Revenue]]-tbl_EcommerceSales[[#This Row],[Total_Cost]] -> 2337 | Z107: =IFERROR(#REF!/tbl_EcommerceSales[[#This Row],[Total_Cost]], 0) -> 0 | AA107: =TEXT(tbl_EcommerceSales[[#This Row],[Order_Date]],"mmm") -> Jan | AB107: =YEAR(tbl_EcommerceSales[[#This Row],[Order_Date]]) -> 2025 | AC107: =IF(tbl_EcommerceSales[[#This Row],[Age]]<18,"Under 18",IF(tbl_EcommerceSales[[#This Row],[Age]]<=25,"18-25",IF(tbl_EcommerceSales[[#This Row],[Age]]<=35,"26-35",IF(tbl_EcommerceSales[[#This Row],[Age]]<=45,"36-45",IF(tbl_EcommerceSales[[#This Row],[Age]]<=55,"46-55","56+"))))) -> 26-35
A108: ORD104600 | B108: 45669 | C108: CUST1608 | D108: Sanya Malhotra | E108: Male | F108: 27 | G108: Mysuru | H108: South | I108: P018 | J108: Cricket Bat | K108: Sports & Fitness | L108: Sports | M108: 2 | N108: 2199 | O108: 0 | P108: 2500 | Q108: Cash on Delivery | R108: Delivered | S108: Mobile App | T108: 4 | U108: =M108*N108 -> 4398 | V108: =tbl_EcommerceSales[[#This Row],[Gross_Sales]]*tbl_EcommerceSales[[#This Row],[Discount]] -> 0 | W108: =tbl_EcommerceSales[[#This Row],[Gross_Sales]]-tbl_EcommerceSales[[#This Row],[Discount_Amount]] -> 4398 | X108: =tbl_EcommerceSales[[#This Row],[Quantity]] * _xlfn.XLOOKUP(tbl_EcommerceSales[[#This Row],[Product_ID]], Product_Master!A:A, Product_Master!F:F) -> 2500 | Y108: =tbl_EcommerceSales[[#This Row],[Net_Revenue]]-tbl_EcommerceSales[[#This Row],[Total_Cost]] -> 1898 | Z108: =IFERROR(#REF!/tbl_EcommerceSales[[#This Row],[Total_Cost]], 0) -> 0 | AA108: =TEXT(tbl_EcommerceSales[[#This Row],[Order_Date]],"mmm") -> Jan | AB108: =YEAR(tbl_EcommerceSales[[#This Row],[Order_Date]]) -> 2025 | AC108: =IF(tbl_EcommerceSales[[#This Row],[Age]]<18,"Under 18",IF(tbl_EcommerceSales[[#This Row],[Age]]<=25,"18-25",IF(tbl_EcommerceSales[[#This Row],[Age]]<=35,"26-35",IF(tbl_EcommerceSales[[#This Row],[Age]]<=45,"36-45",IF(tbl_EcommerceSales[[#This Row],[Age]]<=55,"46-55","56+"))))) -> 26-35
A109: ORD101746 | B109: 45669 | C109: CUST1944 | D109: Ishaan Malhotra | E109: Female | F109: 29 | G109: Dehradun | H109: North | I109: P013 | J109: Non-Stick Cookware Set | K109: Home & Kitchen | L109: Cookware | M109: 1 | N109: 4299 | O109: 0.15 | P109: 2700 | Q109: Debit Card | R109: Returned | S109: Website | T109: 2 | U109: =M109*N109 -> 4299 | V109: =tbl_EcommerceSales[[#This Row],[Gross_Sales]]*tbl_EcommerceSales[[#This Row],[Discount]] -> 644.85 | W109: =tbl_EcommerceSales[[#This Row],[Gross_Sales]]-tbl_EcommerceSales[[#This Row],[Discount_Amount]] -> 3654.15 | X109: =tbl_EcommerceSales[[#This Row],[Quantity]] * _xlfn.XLOOKUP(tbl_EcommerceSales[[#This Row],[Product_ID]], Product_Master!A:A, Product_Master!F:F) -> 2700 | Y109: =tbl_EcommerceSales[[#This Row],[Net_Revenue]]-tbl_EcommerceSales[[#This Row],[Total_Cost]] -> 954.15 | Z109: =IFERROR(#REF!/tbl_EcommerceSales[[#This Row],[Total_Cost]], 0) -> 0 | AA109: =TEXT(tbl_EcommerceSales[[#This Row],[Order_Date]],"mmm") -> Jan | AB109: =YEAR(tbl_EcommerceSales[[#This Row],[Order_Date]]) -> 2025 | AC109: =IF(tbl_EcommerceSales[[#This Row],[Age]]<18,"Under 18",IF(tbl_EcommerceSales[[#This Row],[Age]]<=25,"18-25",IF(tbl_EcommerceSales[[#This Row],[Age]]<=35,"26-35",IF(tbl_EcommerceSales[[#This Row],[Age]]<=45,"36-45",IF(tbl_EcommerceSales[[#This Row],[Age]]<=55,"46-55","56+"))))) -> 26-35
A110: ORD101048 | B110: 45669 | C110: CUST0754 | D110: Yash Agarwal | E110: Male | F110: 31 | G110: Surat | H110: West | I110: P003 | J110: Smart Watch | K110: Electronics | L110: Wearables | M110: 1 | N110: 3299 | O110: 0.1 | P110: 2100 | Q110: Debit Card | R110: Delivered | S110: Mobile App | T110: 4 | U110: =M110*N110 -> 3299 | V110: =tbl_EcommerceSales[[#This Row],[Gross_Sales]]*tbl_EcommerceSales[[#This Row],[Discount]] -> 329.9 | W110: =tbl_EcommerceSales[[#This Row],[Gross_Sales]]-tbl_EcommerceSales[[#This Row],[Discount_Amount]] -> 2969.1 | X110: =tbl_EcommerceSales[[#This Row],[Quantity]] * _xlfn.XLOOKUP(tbl_EcommerceSales[[#This Row],[Product_ID]], Product_Master!A:A, Product_Master!F:F) -> 2100 | Y110: =tbl_EcommerceSales[[#This Row],[Net_Revenue]]-tbl_EcommerceSales[[#This Row],[Total_Cost]] -> 869.1 | Z110: =IFERROR(#REF!/tbl_EcommerceSales[[#This Row],[Total_Cost]], 0) -> 0 | AA110: =TEXT(tbl_EcommerceSales[[#This Row],[Order_Date]],"mmm") -> Jan | AB110: =YEAR(tbl_EcommerceSales[[#This Row],[Order_Date]]) -> 2025 | AC110: =IF(tbl_EcommerceSales[[#This Row],[Age]]<18,"Under 18",IF(tbl_EcommerceSales[[#This Row],[Age]]<=25,"18-25",IF(tbl_EcommerceSales[[#This Row],[Age]]<=35,"26-35",IF(tbl_EcommerceSales[[#This Row],[Age]]<=45,"36-45",IF(tbl_EcommerceSales[[#This Row],[Age]]<=55,"46-55","56+"))))) -> 26-35
A111: ORD100507 | B111: 45669 | C111: CUST1993 | D111: Zoya Singh | E111: Female | F111: 49 | G111: Pune | H111: West | I111: P016 | J111: Yoga Mat | K111: Sports & Fitness | L111: Fitness | M111: 1 | N111: 999 | O111: 0.25 | P111: 520 | Q111: Net Banking | R111: Delivered | S111: Website | T111: 5 | U111: =M111*N111 -> 999 | V111: =tbl_EcommerceSales[[#This Row],[Gross_Sales]]*tbl_EcommerceSales[[#This Row],[Discount]] -> 249.75 | W111: =tbl_EcommerceSales[[#This Row],[Gross_Sales]]-tbl_EcommerceSales[[#This Row],[Discount_Amount]] -> 749.25 | X111: =tbl_EcommerceSales[[#This Row],[Quantity]] * _xlfn.XLOOKUP(tbl_EcommerceSales[[#This Row],[Product_ID]], Product_Master!A:A, Product_Master!F:F) -> 520 | Y111: =tbl_EcommerceSales[[#This Row],[Net_Revenue]]-tbl_EcommerceSales[[#This Row],[Total_Cost]] -> 229.25 | Z111: =IFERROR(#REF!/tbl_EcommerceSales[[#This Row],[Total_Cost]], 0) -> 0 | AA111: =TEXT(tbl_EcommerceSales[[#This Row],[Order_Date]],"mmm") -> Jan | AB111: =YEAR(tbl_EcommerceSales[[#This Row],[Order_Date]]) -> 2025 | AC111: =IF(tbl_EcommerceSales[[#This Row],[Age]]<18,"Under 18",IF(tbl_EcommerceSales[[#This Row],[Age]]<=25,"18-25",IF(tbl_EcommerceSales[[#This Row],[Age]]<=35,"26-35",IF(tbl_EcommerceSales[[#This Row],[Age]]<=45,"36-45",IF(tbl_EcommerceSales[[#This Row],[Age]]<=55,"46-55","56+"))))) -> 46-55
A112: ORD101493 | B112: 45669 | C112: CUST1348 | D112: Varun Jain | E112: Female | F112: 38 | G112: Jaipur | H112: North | I112: P018 | J112: Cricket Bat | K112: Sports & Fitness | L112: Sports | M112: 1 | N112: 2199 | O112: 0.1 | P112: 1250 | Q112: UPI | R112: Delivered | S112: Mobile App | T112: 4 | U112: =M112*N112 -> 2199 | V112: =tbl_EcommerceSales[[#This Row],[Gross_Sales]]*tbl_EcommerceSales[[#This Row],[Discount]] -> 219.9 | W112: =tbl_EcommerceSales[[#This Row],[Gross_Sales]]-tbl_EcommerceSales[[#This Row],[Discount_Amount]] -> 1979.1 | X112: =tbl_EcommerceSales[[#This Row],[Quantity]] * _xlfn.XLOOKUP(tbl_EcommerceSales[[#This Row],[Product_ID]], Product_Master!A:A, Product_Master!F:F) -> 1250 | Y112: =tbl_EcommerceSales[[#This Row],[Net_Revenue]]-tbl_EcommerceSales[[#This Row],[Total_Cost]] -> 729.1 | Z112: =IFERROR(#REF!/tbl_EcommerceSales[[#This Row],[Total_Cost]], 0) -> 0 | AA112: =TEXT(tbl_EcommerceSales[[#This Row],[Order_Date]],"mmm") -> Jan | AB112: =YEAR(tbl_EcommerceSales[[#This Row],[Order_Date]]) -> 2025 | AC112: =IF(tbl_EcommerceSales[[#This Row],[Age]]<18,"Under 18",IF(tbl_EcommerceSales[[#This Row],[Age]]<=25,"18-25",IF(tbl_EcommerceSales[[#This Row],[Age]]<=35,"26-35",IF(tbl_EcommerceSales[[#This Row],[Age]]<=45,"36-45",IF(tbl_EcommerceSales[[#This Row],[Age]]<=55,"46-55","56+"))))) -> 36-45
A113: ORD102807 | B113: 45669 | C113: CUST0234 | D113: Arjun Rao | E113: Female | F113: 42 | G113: Kochi | H113: South | I113: P001 | J113: Wireless Headphones | K113: Electronics | L113: Audio | M113: 4 | N113: 2499 | O113: 0.25 | P113: 6200 | Q113: UPI | R113: Delivered | S113: Website | T113: 5 | U113: =M113*N113 -> 9996 | V113: =tbl_EcommerceSales[[#This Row],[Gross_Sales]]*tbl_EcommerceSales[[#This Row],[Discount]] -> 2499 | W113: =tbl_EcommerceSales[[#This Row],[Gross_Sales]]-tbl_EcommerceSales[[#This Row],[Discount_Amount]] -> 7497 | X113: =tbl_EcommerceSales[[#This Row],[Quantity]] * _xlfn.XLOOKUP(tbl_EcommerceSales[[#This Row],[Product_ID]], Product_Master!A:A, Product_Master!F:F) -> 6200 | Y113: =tbl_EcommerceSales[[#This Row],[Net_Revenue]]-tbl_EcommerceSales[[#This Row],[Total_Cost]] -> 1297 | Z113: =IFERROR(#REF!/tbl_EcommerceSales[[#This Row],[Total_Cost]], 0) -> 0 | AA113: =TEXT(tbl_EcommerceSales[[#This Row],[Order_Date]],"mmm") -> Jan | AB113: =YEAR(tbl_EcommerceSales[[#This Row],[Order_Date]]) -> 2025 | AC113: =IF(tbl_EcommerceSales[[#This Row],[Age]]<18,"Under 18",IF(tbl_EcommerceSales[[#This Row],[Age]]<=25,"18-25",IF(tbl_EcommerceSales[[#This Row],[Age]]<=35,"26-35",IF(tbl_EcommerceSales[[#This Row],[Age]]<=45,"36-45",IF(tbl_EcommerceSales[[#This Row],[Age]]<=55,"46-55","56+"))))) -> 36-45
... A125: ORD101838 | B125: 45670 | C125: CUST0916 | D125: Karan Jain | E125: Male | F125: 27 | G125: Lucknow | H125: North | I125: P001 | J125: Wireless Headphones | K125: Electronics | L125: Audio | M125: 2 | N125: 2499 | O125: 0.3 | P125: 3100 | Q125: Cash on Delivery | R125: Delivered | S125: Mobile App | T125: 5 | U125: =M125*N125 -> 4998 | V125: =tbl_EcommerceSales[[#This Row],[Gross_Sales]]*tbl_EcommerceSales[[#This Row],[Discount]] -> 1499.4 | W125: =tbl_EcommerceSales[[#This Row],[Gross_Sales]]-tbl_EcommerceSales[[#This Row],[Discount_Amount]] -> 3498.6 | X125: =tbl_EcommerceSales[[#This Row],[Quantity]] * _xlfn.XLOOKUP(tbl_EcommerceSales[[#This Row],[Product_ID]], Product_Master!A:A, Product_Master!F:F) -> 3100 | Y125: =tbl_EcommerceSales[[#This Row],[Net_Revenue]]-tbl_EcommerceSales[[#This Row],[Total_Cost]] -> 398.6 | Z125: =IFERROR(#REF!/tbl_EcommerceSales[[#This Row],[Total_Cost]], 0) -> 0 | AA125: =TEXT(tbl_EcommerceSales[[#This Row],[Order_Date]],"mmm") -> Jan | AB125: =YEAR(tbl_EcommerceSales[[#This Row],[Order_Date]]) -> 2025 | AC125: =IF(tbl_EcommerceSales[[#This Row],[Age]]<18,"Under 18",IF(tbl_EcommerceSales[[#This Row],[Age]]<=25,"18-25",IF(tbl_EcommerceSales[[#This Row],[Age]]<=35,"26-35",IF(tbl_EcommerceSales[[#This Row],[Age]]<=45,"36-45",IF(tbl_EcommerceSales[[#This Row],[Age]]<=55,"46-55","56+"))))) -> 26-35
A126: ORD104987 | B126: 45670 | C126: CUST2158 | D126: Aditya Kapoor | E126: Male | F126: 18 | G126: Ahmedabad | H126: West | I126: P019 | J126: Badminton Racket | K126: Sports & Fitness | L126: Sports | M126: 2 | N126: 1499 | O126: 0.2 | P126: 1600 | Q126: Debit Card | R126: Cancelled | S126: Mobile App | U126: =M126*N126 -> 2998 | V126: =tbl_EcommerceSales[[#This Row],[Gross_Sales]]*tbl_EcommerceSales[[#This Row],[Discount]] -> 599.6 | W126: =tbl_EcommerceSales[[#This Row],[Gross_Sales]]-tbl_EcommerceSales[[#This Row],[Discount_Amount]] -> 2398.4 | X126: =tbl_EcommerceSales[[#This Row],[Quantity]] * _xlfn.XLOOKUP(tbl_EcommerceSales[[#This Row],[Product_ID]], Product_Master!A:A, Product_Master!F:F) -> 1600 | Y126: =tbl_EcommerceSales[[#This Row],[Net_Revenue]]-tbl_EcommerceSales[[#This Row],[Total_Cost]] -> 798.4 | Z126: =IFERROR(#REF!/tbl_EcommerceSales[[#This Row],[Total_Cost]], 0) -> 0 | AA126: =TEXT(tbl_EcommerceSales[[#This Row],[Order_Date]],"mmm") -> Jan | AB126: =YEAR(tbl_EcommerceSales[[#This Row],[Order_Date]]) -> 2025 | AC126: =IF(tbl_EcommerceSales[[#This Row],[Age]]<18,"Under 18",IF(tbl_EcommerceSales[[#This Row],[Age]]<=25,"18-25",IF(tbl_EcommerceSales[[#This Row],[Age]]<=35,"26-35",IF(tbl_EcommerceSales[[#This Row],[Age]]<=45,"36-45",IF(tbl_EcommerceSales[[#This Row],[Age]]<=55,"46-55","56+"))))) -> 18-25
A127: ORD104014 | B127: 45670 | C127: CUST1349 | D127: Akash Bansal | E127: Female | F127: 42 | G127: Surat | H127: West | I127: P024 | J127: Perfume | K127: Beauty | L127: Fragrance | M127: 1 | N127: 1799 | O127: 0.2 | P127: 900 | Q127: UPI | R127: Delivered | S127: Mobile App | T127: 4 | U127: =M127*N127 -> 1799 | V127: =tbl_EcommerceSales[[#This Row],[Gross_Sales]]*tbl_EcommerceSales[[#This Row],[Discount]] -> 359.8 | W127: =tbl_EcommerceSales[[#This Row],[Gross_Sales]]-tbl_EcommerceSales[[#This Row],[Discount_Amount]] -> 1439.2 | X127: =tbl_EcommerceSales[[#This Row],[Quantity]] * _xlfn.XLOOKUP(tbl_EcommerceSales[[#This Row],[Product_ID]], Product_Master!A:A, Product_Master!F:F) -> 900 | Y127: =tbl_EcommerceSales[[#This Row],[Net_Revenue]]-tbl_EcommerceSales[[#This Row],[Total_Cost]] -> 539.2 | Z127: =IFERROR(#REF!/tbl_EcommerceSales[[#This Row],[Total_Cost]], 0) -> 0 | AA127: =TEXT(tbl_EcommerceSales[[#This Row],[Order_Date]],"mmm") -> Jan | AB127: =YEAR(tbl_EcommerceSales[[#This Row],[Order_Date]]) -> 2025 | AC127: =IF(tbl_EcommerceSales[[#This Row],[Age]]<18,"Under 18",IF(tbl_EcommerceSales[[#This Row],[Age]]<=25,"18-25",IF(tbl_EcommerceSales[[#This Row],[Age]]<=35,"26-35",IF(tbl_EcommerceSales[[#This Row],[Age]]<=45,"36-45",IF(tbl_EcommerceSales[[#This Row],[Age]]<=55,"46-55","56+"))))) -> 36-45
A128: ORD103810 | B128: 45670 | C128: CUST1266 | D128: Yash Agarwal | E128: Female | F128: 23 | G128: Delhi | H128: North | I128: P018 | J128: Cricket Bat | K128: Sports & Fitness | L128: Sports | M128: 1 | N128: 2199 | O128: 0.1 | P128: 1250 | Q128: UPI | R128: Delivered | S128: Mobile App | T128: 4 | U128: =M128*N128 -> 2199 | V128: =tbl_EcommerceSales[[#This Row],[Gross_Sales]]*tbl_EcommerceSales[[#This Row],[Discount]] -> 219.9 | W128: =tbl_EcommerceSales[[#This Row],[Gross_Sales]]-tbl_EcommerceSales[[#This Row],[Discount_Amount]] -> 1979.1 | X128: =tbl_EcommerceSales[[#This Row],[Quantity]] * _xlfn.XLOOKUP(tbl_EcommerceSales[[#This Row],[Product_ID]], Product_Master!A:A, Product_Master!F:F) -> 1250 | Y128: =tbl_EcommerceSales[[#This Row],[Net_Revenue]]-tbl_EcommerceSales[[#This Row],[Total_Cost]] -> 729.1 | Z128: =IFERROR(#REF!/tbl_EcommerceSales[[#This Row],[Total_Cost]], 0) -> 0 | AA128: =TEXT(tbl_EcommerceSales[[#This Row],[Order_Date]],"mmm") -> Jan | AB128: =YEAR(tbl_EcommerceSales[[#This Row],[Order_Date]]) -> 2025 | AC128: =IF(tbl_EcommerceSales[[#This Row],[Age]]<18,"Under 18",IF(tbl_EcommerceSales[[#This Row],[Age]]<=25,"18-25",IF(tbl_EcommerceSales[[#This Row],[Age]]<=35,"26-35",IF(tbl_EcommerceSales[[#This Row],[Age]]<=45,"36-45",IF(tbl_EcommerceSales[[#This Row],[Age]]<=55,"46-55","56+"))))) -> 18-25
A129: ORD104649 | B129: 45671 | C129: CUST1243 | D129: Vansh Chopra | E129: Female | F129: 29 | G129: Pune | H129: West | I129: P028 | J129: Data Analytics Book | K129: Books | L129: Technology | M129: 1 | N129: 1099 | O129: 0.1 | P129: 520 | Q129: UPI | R129: Delivered | S129: Mobile App | T129: 5 | U129: =M129*N129 -> 1099 | V129: =tbl_EcommerceSales[[#This Row],[Gross_Sales]]*tbl_EcommerceSales[[#This Row],[Discount]] -> 109.9 | W129: =tbl_EcommerceSales[[#This Row],[Gross_Sales]]-tbl_EcommerceSales[[#This Row],[Discount_Amount]] -> 989.1 | X129: =tbl_EcommerceSales[[#This Row],[Quantity]] * _xlfn.XLOOKUP(tbl_EcommerceSales[[#This Row],[Product_ID]], Product_Master!A:A, Product_Master!F:F) -> 520 | Y129: =tbl_EcommerceSales[[#This Row],[Net_Revenue]]-tbl_EcommerceSales[[#This Row],[Total_Cost]] -> 469.1 | Z129: =IFERROR(#REF!/tbl_EcommerceSales[[#This Row],[Total_Cost]], 0) -> 0 | AA129: =TEXT(tbl_EcommerceSales[[#This Row],[Order_Date]],"mmm") -> Jan | AB129: =YEAR(tbl_EcommerceSales[[#This Row],[Order_Date]]) -> 2025 | AC129: =IF(tbl_EcommerceSales[[#This Row],[Age]]<18,"Under 18",IF(tbl_EcommerceSales[[#This Row],[Age]]<=25,"18-25",IF(tbl_EcommerceSales[[#This Row],[Age]]<=35,"26-35",IF(tbl_EcommerceSales[[#This Row],[Age]]<=45,"36-45",IF(tbl_EcommerceSales[[#This Row],[Age]]<=55,"46-55","56+"))))) -> 26-35
A130: ORD101388 | B130: 45671 | C130: CUST0096 | D130: Aarav Sharma | E130: Male | F130: 28 | G130: Bokaro | H130: East | I130: P022 | J130: Sunscreen SPF 50 | K130: Beauty | L130: Skincare | M130: 1 | N130: 799 | O130: 0.1 | P130: 360 | Q130: UPI | R130: Delivered | S130: Website | T130: 5 | U130: =M130*N130 -> 799 | V130: =tbl_EcommerceSales[[#This Row],[Gross_Sales]]*tbl_EcommerceSales[[#This Row],[Discount]] -> 79.9 | W130: =tbl_EcommerceSales[[#This Row],[Gross_Sales]]-tbl_EcommerceSales[[#This Row],[Discount_Amount]] -> 719.1 | X130: =tbl_EcommerceSales[[#This Row],[Quantity]] * _xlfn.XLOOKUP(tbl_EcommerceSales[[#This Row],[Product_ID]], Product_Master!A:A, Product_Master!F:F) -> 360 | Y130: =tbl_EcommerceSales[[#This Row],[Net_Revenue]]-tbl_EcommerceSales[[#This Row],[Total_Cost]] -> 359.1 | Z130: =IFERROR(#REF!/tbl_EcommerceSales[[#This Row],[Total_Cost]], 0) -> 0 | AA130: =TEXT(tbl_EcommerceSales[[#This Row],[Order_Date]],"mmm") -> Jan | AB130: =YEAR(tbl_EcommerceSales[[#This Row],[Order_Date]]) -> 2025 | AC130: =IF(tbl_EcommerceSales[[#This Row],[Age]]<18,"Under 18",IF(tbl_EcommerceSales[[#This Row],[Age]]<=25,"18-25",IF(tbl_EcommerceSales[[#This Row],[Age]]<=35,"26-35",IF(tbl_EcommerceSales[[#This Row],[Age]]<=45,"36-45",IF(tbl_EcommerceSales[[#This Row],[Age]]<=55,"46-55","56+"))))) -> 26-35
A131: ORD101444 | B131: 45671 | C131: CUST0016 | D131: Mohit Sharma | E131: Male | F131: 26 | G131: Chandigarh | H131: North | I131: P030 | J131: Self Help Book | K131: Books | L131: Self Development | M131: 1 | N131: 599 | O131: 0.1 | P131: 260 | Q131: UPI | R131: Delivered | S131: Website | T131: 4 | U131: =M131*N131 -> 599 | V131: =tbl_EcommerceSales[[#This Row],[Gross_Sales]]*tbl_EcommerceSales[[#This Row],[Discount]] -> 59.9 | W131: =tbl_EcommerceSales[[#This Row],[Gross_Sales]]-tbl_EcommerceSales[[#This Row],[Discount_Amount]] -> 539.1 | X131: =tbl_EcommerceSales[[#This Row],[Quantity]] * _xlfn.XLOOKUP(tbl_EcommerceSales[[#This Row],[Product_ID]], Product_Master!A:A, Product_Master!F:F) -> 260 | Y131: =tbl_EcommerceSales[[#This Row],[Net_Revenue]]-tbl_EcommerceSales[[#This Row],[Total_Cost]] -> 279.1 | Z131: =IFERROR(#REF!/tbl_EcommerceSales[[#This Row],[Total_Cost]], 0) -> 0 | AA131: =TEXT(tbl_EcommerceSales[[#This Row],[Order_Date]],"mmm") -> Jan | AB131: =YEAR(tbl_EcommerceSales[[#This Row],[Order_Date]]) -> 2025 | AC131: =IF(tbl_EcommerceSales[[#This Row],[Age]]<18,"Under 18",IF(tbl_EcommerceSales[[#This Row],[Age]]<=25,"18-25",IF(tbl_EcommerceSales[[#This Row],[Age]]<=35,"26-35",IF(tbl_EcommerceSales[[#This Row],[Age]]<=45,"36-45",IF(tbl_EcommerceSales[[#This Row],[Age]]<=55,"46-55","56+"))))) -> 26-35
A132: ORD102011 | B132: 45671 | C132: CUST0441 | D132: Meera Singh | E132: Female | F132: 37 | G132: Delhi | H132: North | I132: P017 | J132: Dumbbell Set | K132: Sports & Fitness | L132: Fitness | M132: 1 | N132: 2499 | O132: 0 | P132: 1450 | Q132: Credit Card | R132: Delivered | S132: Mobile App | T132: 4 | U132: =M132*N132 -> 2499 | V132: =tbl_EcommerceSales[[#This Row],[Gross_Sales]]*tbl_EcommerceSales[[#This Row],[Discount]] -> 0 | W132: =tbl_EcommerceSales[[#This Row],[Gross_Sales]]-tbl_EcommerceSales[[#This Row],[Discount_Amount]] -> 2499 | X132: =tbl_EcommerceSales[[#This Row],[Quantity]] * _xlfn.XLOOKUP(tbl_EcommerceSales[[#This Row],[Product_ID]], Product_Master!A:A, Product_Master!F:F) -> 1450 | Y132: =tbl_EcommerceSales[[#This Row],[Net_Revenue]]-tbl_EcommerceSales[[#This Row],[Total_Cost]] -> 1049 | Z132: =IFERROR(#REF!/tbl_EcommerceSales[[#This Row],[Total_Cost]], 0) -> 0 | AA132: =TEXT(tbl_EcommerceSales[[#This Row],[Order_Date]],"mmm") -> Jan | AB132: =YEAR(tbl_EcommerceSales[[#This Row],[Order_Date]]) -> 2025 | AC132: =IF(tbl_EcommerceSales[[#This Row],[Age]]<18,"Under 18",IF(tbl_EcommerceSales[[#This Row],[Age]]<=25,"18-25",IF(tbl_EcommerceSales[[#This Row],[Age]]<=35,"26-35",IF(tbl_EcommerceSales[[#This Row],[Age]]<=45,"36-45",IF(tbl_EcommerceSales[[#This Row],[Age]]<=55,"46-55","56+"))))) -> 36-45
A133: ORD103594 | B133: 45671 | C133: CUST1810 | D133: Yash Agarwal | E133: Female | F133: 45 | G133: Delhi | H133: North | I133: P017 | J133: Dumbbell Set | K133: Sports & Fitness | L133: Fitness | M133: 3 | N133: 2499 | O133: 0.05 | P133: 4350 | Q133: Credit Card | R133: Delivered | S133: Mobile App | T133: 5 | U133: =M133*N133 -> 7497 | V133: =tbl_EcommerceSales[[#This Row],[Gross_Sales]]*tbl_EcommerceSales[[#This Row],[Discount]] -> 374.85 | W133: =tbl_EcommerceSales[[#This Row],[Gross_Sales]]-tbl_EcommerceSales[[#This Row],[Discount_Amount]] -> 7122.15 | X133: =tbl_EcommerceSales[[#This Row],[Quantity]] * _xlfn.XLOOKUP(tbl_EcommerceSales[[#This Row],[Product_ID]], Product_Master!A:A, Product_Master!F:F) -> 4350 | Y133: =tbl_EcommerceSales[[#This Row],[Net_Revenue]]-tbl_EcommerceSales[[#This Row],[Total_Cost]] -> 2772.15 | Z133: =IFERROR(#REF!/tbl_EcommerceSales[[#This Row],[Total_Cost]], 0) -> 0 | AA133: =TEXT(tbl_EcommerceSales[[#This Row],[Order_Date]],"mmm") -> Jan | AB133: =YEAR(tbl_EcommerceSales[[#This Row],[Order_Date]]) -> 2025 | AC133: =IF(tbl_EcommerceSales[[#This Row],[Age]]<18,"Under 18",IF(tbl_EcommerceSales[[#This Row],[Age]]<=25,"18-25",IF(tbl_EcommerceSales[[#This Row],[Age]]<=35,"26-35",IF(tbl_EcommerceSales[[#This Row],[Age]]<=45,"36-45",IF(tbl_EcommerceSales[[#This Row],[Age]]<=55,"46-55","56+"))))) -> 36-45
A134: ORD100042 | B134: 45671 | C134: CUST2153 | D134: Zoya Singh | E134: Female | F134: 32 | G134: Kolkata | H134: East | I134: P006 | J134: Laptop Backpack | K134: Fashion | L134: Bags | M134: 1 | N134: 1799 | O134: 0 | P134: 950 | Q134: Cash on Delivery | R134: Delivered | S134: Mobile App | T134: 4 | U134: =M134*N134 -> 1799 | V134: =tbl_EcommerceSales[[#This Row],[Gross_Sales]]*tbl_EcommerceSales[[#This Row],[Discount]] -> 0 | W134: =tbl_EcommerceSales[[#This Row],[Gross_Sales]]-tbl_EcommerceSales[[#This Row],[Discount_Amount]] -> 1799 | X134: =tbl_EcommerceSales[[#This Row],[Quantity]] * _xlfn.XLOOKUP(tbl_EcommerceSales[[#This Row],[Product_ID]], Product_Master!A:A, Product_Master!F:F) -> 950 | Y134: =tbl_EcommerceSales[[#This Row],[Net_Revenue]]-tbl_EcommerceSales[[#This Row],[Total_Cost]] -> 849 | Z134: =IFERROR(#REF!/tbl_EcommerceSales[[#This Row],[Total_Cost]], 0) -> 0 | AA134: =TEXT(tbl_EcommerceSales[[#This Row],[Order_Date]],"mmm") -> Jan | AB134: =YEAR(tbl_EcommerceSales[[#This Row],[Order_Date]]) -> 2025 | AC134: =IF(tbl_EcommerceSales[[#This Row],[Age]]<18,"Under 18",IF(tbl_EcommerceSales[[#This Row],[Age]]<=25,"18-25",IF(tbl_EcommerceSales[[#This Row],[Age]]<=35,"26-35",IF(tbl_EcommerceSales[[#This Row],[Age]]<=45,"36-45",IF(tbl_EcommerceSales[[#This Row],[Age]]<=55,"46-55","56+"))))) -> 26-35
A135: ORD104928 | B135: 45671 | C135: CUST1758 | D135: Pooja Kapoor | E135: Male | F135: 29 | G135: Dehradun | H135: North | I135: P013 | J135: Non-Stick Cookware Set | K135: Home & Kitchen | L135: Cookware | M135: 2 | N135: 4299 | O135: 0.05 | P135: 5400 | Q135: Debit Card | R135: Delivered | S135: Mobile App | T135: 3 | U135: =M135*N135 -> 8598 | V135: =tbl_EcommerceSales[[#This Row],[Gross_Sales]]*tbl_EcommerceSales[[#This Row],[Discount]] -> 429.9 | W135: =tbl_EcommerceSales[[#This Row],[Gross_Sales]]-tbl_EcommerceSales[[#This Row],[Discount_Amount]] -> 8168.1 | X135: =tbl_EcommerceSales[[#This Row],[Quantity]] * _xlfn.XLOOKUP(tbl_EcommerceSales[[#This Row],[Product_ID]], Product_Master!A:A, Product_Master!F:F) -> 5400 | Y135: =tbl_EcommerceSales[[#This Row],[Net_Revenue]]-tbl_EcommerceSales[[#This Row],[Total_Cost]] -> 2768.1 | Z135: =IFERROR(#REF!/tbl_EcommerceSales[[#This Row],[Total_Cost]], 0) -> 0 | AA135: =TEXT(tbl_EcommerceSales[[#This Row],[Order_Date]],"mmm") -> Jan | AB135: =YEAR(tbl_EcommerceSales[[#This Row],[Order_Date]]) -> 2025 | AC135: =IF(tbl_EcommerceSales[[#This Row],[Age]]<18,"Under 18",IF(tbl_EcommerceSales[[#This Row],[Age]]<=25,"18-25",IF(tbl_EcommerceSales[[#This Row],[Age]]<=35,"26-35",IF(tbl_EcommerceSales[[#This Row],[Age]]<=45,"36-45",IF(tbl_EcommerceSales[[#This Row],[Age]]<=55,"46-55","56+"))))) -> 26-35
A136: ORD102686 | B136: 45671 | C136: CUST1380 | D136: Varun Jain | E136: Female | F136: 18 | G136: Kolkata | H136: East | I136: P010 | J136: Casual Hoodie | K136: Fashion | L136: Clothing | M136: 1 | N136: 1499 | O136: 0.2 | P136: 780 | Q136: Wallet | R136: Delivered | S136: Website | T136: 5 | U136: =M136*N136 -> 1499 | V136: =tbl_EcommerceSales[[#This Row],[Gross_Sales]]*tbl_EcommerceSales[[#This Row],[Discount]] -> 299.8 | W136: =tbl_EcommerceSales[[#This Row],[Gross_Sales]]-tbl_EcommerceSales[[#This Row],[Discount_Amount]] -> 1199.2 | X136: =tbl_EcommerceSales[[#This Row],[Quantity]] * _xlfn.XLOOKUP(tbl_EcommerceSales[[#This Row],[Product_ID]], Product_Master!A:A, Product_Master!F:F) -> 780 | Y136: =tbl_EcommerceSales[[#This Row],[Net_Revenue]]-tbl_EcommerceSales[[#This Row],[Total_Cost]] -> 419.2 | Z136: =IFERROR(#REF!/tbl_EcommerceSales[[#This Row],[Total_Cost]], 0) -> 0 | AA136: =TEXT(tbl_EcommerceSales[[#This Row],[Order_Date]],"mmm") -> Jan | AB136: =YEAR(tbl_EcommerceSales[[#This Row],[Order_Date]]) -> 2025 | AC136: =IF(tbl_EcommerceSales[[#This Row],[Age]]<18,"Under 18",IF(tbl_EcommerceSales[[#This Row],[Age]]<=25,"18-25",IF(tbl_EcommerceSales[[#This Row],[Age]]<=35,"26-35",IF(tbl_EcommerceSales[[#This Row],[Age]]<=45,"36-45",IF(tbl_EcommerceSales[[#This Row],[Age]]<=55,"46-55","56+"))))) -> 18-25
A137: ORD102872 | B137: 45672 | C137: CUST1764 | D137: Varun Jain | E137: Male | F137: 24 | G137: Jaipur | H137: North | I137: P013 | J137: Non-Stick Cookware Set | K137: Home & Kitchen | L137: Cookware | M137: 1 | N137: 4299 | O137: 0.25 | P137: 2700 | Q137: Cash on Delivery | R137: Delivered | S137: Website | T137: 4 | U137: =M137*N137 -> 4299 | V137: =tbl_EcommerceSales[[#This Row],[Gross_Sales]]*tbl_EcommerceSales[[#This Row],[Discount]] -> 1074.75 | W137: =tbl_EcommerceSales[[#This Row],[Gross_Sales]]-tbl_EcommerceSales[[#This Row],[Discount_Amount]] -> 3224.25 | X137: =tbl_EcommerceSales[[#This Row],[Quantity]] * _xlfn.XLOOKUP(tbl_EcommerceSales[[#This Row],[Product_ID]], Product_Master!A:A, Product_Master!F:F) -> 2700 | Y137: =tbl_EcommerceSales[[#This Row],[Net_Revenue]]-tbl_EcommerceSales[[#This Row],[Total_Cost]] -> 524.25 | Z137: =IFERROR(#REF!/tbl_EcommerceSales[[#This Row],[Total_Cost]], 0) -> 0 | AA137: =TEXT(tbl_EcommerceSales[[#This Row],[Order_Date]],"mmm") -> Jan | AB137: =YEAR(tbl_EcommerceSales[[#This Row],[Order_Date]]) -> 2025 | AC137: =IF(tbl_EcommerceSales[[#This Row],[Age]]<18,"Under 18",IF(tbl_EcommerceSales[[#This Row],[Age]]<=25,"18-25",IF(tbl_EcommerceSales[[#This Row],[Age]]<=35,"26-35",IF(tbl_EcommerceSales[[#This Row],[Age]]<=45,"36-45",IF(tbl_EcommerceSales[[#This Row],[Age]]<=55,"46-55","56+"))))) -> 18-25
A138: ORD100788 | B138: 45672 | C138: CUST0592 | D138: Mohit Sharma | E138: Male | F138: 30 | G138: Nashik | H138: West | I138: P023 | J138: Shampoo | K138: Beauty | L138: Haircare | M138: 1 | N138: 649 | O138: 0.15 | P138: 290 | Q138: Debit Card | R138: Delivered | S138: Website | T138: 4 | U138: =M138*N138 -> 649 | V138: =tbl_EcommerceSales[[#This Row],[Gross_Sales]]*tbl_EcommerceSales[[#This Row],[Discount]] -> 97.35 | W138: =tbl_EcommerceSales[[#This Row],[Gross_Sales]]-tbl_EcommerceSales[[#This Row],[Discount_Amount]] -> 551.65 | X138: =tbl_EcommerceSales[[#This Row],[Quantity]] * _xlfn.XLOOKUP(tbl_EcommerceSales[[#This Row],[Product_ID]], Product_Master!A:A, Product_Master!F:F) -> 290 | Y138: =tbl_EcommerceSales[[#This Row],[Net_Revenue]]-tbl_EcommerceSales[[#This Row],[Total_Cost]] -> 261.65 | Z138: =IFERROR(#REF!/tbl_EcommerceSales[[#This Row],[Total_Cost]], 0) -> 0 | AA138: =TEXT(tbl_EcommerceSales[[#This Row],[Order_Date]],"mmm") -> Jan | AB138: =YEAR(tbl_EcommerceSales[[#This Row],[Order_Date]]) -> 2025 | AC138: =IF(tbl_EcommerceSales[[#This Row],[Age]]<18,"Under 18",IF(tbl_EcommerceSales[[#This Row],[Age]]<=25,"18-25",IF(tbl_EcommerceSales[[#This Row],[Age]]<=35,"26-35",IF(tbl_EcommerceSales[[#This Row],[Age]]<=45,"36-45",IF(tbl_EcommerceSales[[#This Row],[Age]]<=55,"46-55","56+"))))) -> 26-35
... A148: ORD102212 | B148: 45673 | C148: CUST0558 | D148: Aditya Kapoor | E148: Female | F148: 24 | G148: Surat | H148: West | I148: P013 | J148: Non-Stick Cookware Set | K148: Home & Kitchen | L148: Cookware | M148: 2 | N148: 4299 | O148: 0.05 | P148: 5400 | Q148: Credit Card | R148: Delivered | S148: Website | T148: 4 | U148: =M148*N148 -> 8598 | V148: =tbl_EcommerceSales[[#This Row],[Gross_Sales]]*tbl_EcommerceSales[[#This Row],[Discount]] -> 429.9 | W148: =tbl_EcommerceSales[[#This Row],[Gross_Sales]]-tbl_EcommerceSales[[#This Row],[Discount_Amount]] -> 8168.1 | X148: =tbl_EcommerceSales[[#This Row],[Quantity]] * _xlfn.XLOOKUP(tbl_EcommerceSales[[#This Row],[Product_ID]], Product_Master!A:A, Product_Master!F:F) -> 5400 | Y148: =tbl_EcommerceSales[[#This Row],[Net_Revenue]]-tbl_EcommerceSales[[#This Row],[Total_Cost]] -> 2768.1 | Z148: =IFERROR(#REF!/tbl_EcommerceSales[[#This Row],[Total_Cost]], 0) -> 0 | AA148: =TEXT(tbl_EcommerceSales[[#This Row],[Order_Date]],"mmm") -> Jan | AB148: =YEAR(tbl_EcommerceSales[[#This Row],[Order_Date]]) -> 2025 | AC148: =IF(tbl_EcommerceSales[[#This Row],[Age]]<18,"Under 18",IF(tbl_EcommerceSales[[#This Row],[Age]]<=25,"18-25",IF(tbl_EcommerceSales[[#This Row],[Age]]<=35,"26-35",IF(tbl_EcommerceSales[[#This Row],[Age]]<=45,"36-45",IF(tbl_EcommerceSales[[#This Row],[Age]]<=55,"46-55","56+"))))) -> 18-25
A149: ORD102323 | B149: 45673 | C149: CUST0453 | D149: Akash Bansal | E149: Male | F149: 34 | G149: Jaipur | H149: North | I149: P015 | J149: Bedsheet Set | K149: Home & Kitchen | L149: Home Decor | M149: 2 | N149: 1599 | O149: 0.15 | P149: 1700 | Q149: Credit Card | R149: Cancelled | S149: Website | U149: =M149*N149 -> 3198 | V149: =tbl_EcommerceSales[[#This Row],[Gross_Sales]]*tbl_EcommerceSales[[#This Row],[Discount]] -> 479.7 | W149: =tbl_EcommerceSales[[#This Row],[Gross_Sales]]-tbl_EcommerceSales[[#This Row],[Discount_Amount]] -> 2718.3 | X149: =tbl_EcommerceSales[[#This Row],[Quantity]] * _xlfn.XLOOKUP(tbl_EcommerceSales[[#This Row],[Product_ID]], Product_Master!A:A, Product_Master!F:F) -> 1700 | Y149: =tbl_EcommerceSales[[#This Row],[Net_Revenue]]-tbl_EcommerceSales[[#This Row],[Total_Cost]] -> 1018.3 | Z149: =IFERROR(#REF!/tbl_EcommerceSales[[#This Row],[Total_Cost]], 0) -> 0 | AA149: =TEXT(tbl_EcommerceSales[[#This Row],[Order_Date]],"mmm") -> Jan | AB149: =YEAR(tbl_EcommerceSales[[#This Row],[Order_Date]]) -> 2025 | AC149: =IF(tbl_EcommerceSales[[#This Row],[Age]]<18,"Under 18",IF(tbl_EcommerceSales[[#This Row],[Age]]<=25,"18-25",IF(tbl_EcommerceSales[[#This Row],[Age]]<=35,"26-35",IF(tbl_EcommerceSales[[#This Row],[Age]]<=45,"36-45",IF(tbl_EcommerceSales[[#This Row],[Age]]<=55,"46-55","56+"))))) -> 26-35
A150: ORD100357 | B150: 45673 | C150: CUST0875 | D150: Kiara Chopra | E150: Male | F150: 42 | G150: Mysuru | H150: South | I150: P003 | J150: Smart Watch | K150: Electronics | L150: Wearables | M150: 5 | N150: 3299 | O150: 0.05 | P150: 10500 | Q150: UPI | R150: Delivered | S150: Website | T150: 4 | U150: =M150*N150 -> 16495 | V150: =tbl_EcommerceSales[[#This Row],[Gross_Sales]]*tbl_EcommerceSales[[#This Row],[Discount]] -> 824.75 | W150: =tbl_EcommerceSales[[#This Row],[Gross_Sales]]-tbl_EcommerceSales[[#This Row],[Discount_Amount]] -> 15670.25 | X150: =tbl_EcommerceSales[[#This Row],[Quantity]] * _xlfn.XLOOKUP(tbl_EcommerceSales[[#This Row],[Product_ID]], Product_Master!A:A, Product_Master!F:F) -> 10500 | Y150: =tbl_EcommerceSales[[#This Row],[Net_Revenue]]-tbl_EcommerceSales[[#This Row],[Total_Cost]] -> 5170.25 | Z150: =IFERROR(#REF!/tbl_EcommerceSales[[#This Row],[Total_Cost]], 0) -> 0 | AA150: =TEXT(tbl_EcommerceSales[[#This Row],[Order_Date]],"mmm") -> Jan | AB150: =YEAR(tbl_EcommerceSales[[#This Row],[Order_Date]]) -> 2025 | AC150: =IF(tbl_EcommerceSales[[#This Row],[Age]]<18,"Under 18",IF(tbl_EcommerceSales[[#This Row],[Age]]<=25,"18-25",IF(tbl_EcommerceSales[[#This Row],[Age]]<=35,"26-35",IF(tbl_EcommerceSales[[#This Row],[Age]]<=45,"36-45",IF(tbl_EcommerceSales[[#This Row],[Age]]<=55,"46-55","56+"))))) -> 36-45
A151: ORD104580 | B151: 45673 | C151: CUST1333 | D151: Pranav Bansal | E151: Male | F151: 42 | G151: Bengaluru | H151: South | I151: P028 | J151: Data Analytics Book | K151: Books | L151: Technology | M151: 1 | N151: 1099 | O151: 0.1 | P151: 520 | Q151: Cash on Delivery | R151: Delivered | S151: Mobile App | T151: 4 | U151: =M151*N151 -> 1099 | V151: =tbl_EcommerceSales[[#This Row],[Gross_Sales]]*tbl_EcommerceSales[[#This Row],[Discount]] -> 109.9 | W151: =tbl_EcommerceSales[[#This Row],[Gross_Sales]]-tbl_EcommerceSales[[#This Row],[Discount_Amount]] -> 989.1 | X151: =tbl_EcommerceSales[[#This Row],[Quantity]] * _xlfn.XLOOKUP(tbl_EcommerceSales[[#This Row],[Product_ID]], Product_Master!A:A, Product_Master!F:F) -> 520 | Y151: =tbl_EcommerceSales[[#This Row],[Net_Revenue]]-tbl_EcommerceSales[[#This Row],[Total_Cost]] -> 469.1 | Z151: =IFERROR(#REF!/tbl_EcommerceSales[[#This Row],[Total_Cost]], 0) -> 0 | AA151: =TEXT(tbl_EcommerceSales[[#This Row],[Order_Date]],"mmm") -> Jan | AB151: =YEAR(tbl_EcommerceSales[[#This Row],[Order_Date]]) -> 2025 | AC151: =IF(tbl_EcommerceSales[[#This Row],[Age]]<18,"Under 18",IF(tbl_EcommerceSales[[#This Row],[Age]]<=25,"18-25",IF(tbl_EcommerceSales[[#This Row],[Age]]<=35,"26-35",IF(tbl_EcommerceSales[[#This Row],[Age]]<=45,"36-45",IF(tbl_EcommerceSales[[#This Row],[Age]]<=55,"46-55","56+"))))) -> 36-45
A152: ORD101064 | B152: 45673 | C152: CUST0487 | D152: Nisha Saxena | E152: Male | F152: 42 | G152: Bokaro | H152: East | I152: P028 | J152: Data Analytics Book | K152: Books | L152: Technology | M152: 2 | N152: 1099 | O152: 0.05 | P152: 1040 | Q152: UPI | R152: Delivered | S152: Mobile App | T152: 4 | U152: =M152*N152 -> 2198 | V152: =tbl_EcommerceSales[[#This Row],[Gross_Sales]]*tbl_EcommerceSales[[#This Row],[Discount]] -> 109.9 | W152: =tbl_EcommerceSales[[#This Row],[Gross_Sales]]-tbl_EcommerceSales[[#This Row],[Discount_Amount]] -> 2088.1 | X152: =tbl_EcommerceSales[[#This Row],[Quantity]] * _xlfn.XLOOKUP(tbl_EcommerceSales[[#This Row],[Product_ID]], Product_Master!A:A, Product_Master!F:F) -> 1040 | Y152: =tbl_EcommerceSales[[#This Row],[Net_Revenue]]-tbl_EcommerceSales[[#This Row],[Total_Cost]] -> 1048.1 | Z152: =IFERROR(#REF!/tbl_EcommerceSales[[#This Row],[Total_Cost]], 0) -> 0 | AA152: =TEXT(tbl_EcommerceSales[[#This Row],[Order_Date]],"mmm") -> Jan | AB152: =YEAR(tbl_EcommerceSales[[#This Row],[Order_Date]]) -> 2025 | AC152: =IF(tbl_EcommerceSales[[#This Row],[Age]]<18,"Under 18",IF(tbl_EcommerceSales[[#This Row],[Age]]<=25,"18-25",IF(tbl_EcommerceSales[[#This Row],[Age]]<=35,"26-35",IF(tbl_EcommerceSales[[#This Row],[Age]]<=45,"36-45",IF(tbl_EcommerceSales[[#This Row],[Age]]<=55,"46-55","56+"))))) -> 36-45
A153: ORD104152 | B153: 45674 | C153: CUST0229 | D153: Akash Bansal | E153: Female | F153: 34 | G153: Ahmedabad | H153: West | I153: P017 | J153: Dumbbell Set | K153: Sports & Fitness | L153: Fitness | M153: 1 | N153: 2499 | O153: 0.15 | P153: 1450 | Q153: Cash on Delivery | R153: Delivered | S153: Mobile App | T153: 5 | U153: =M153*N153 -> 2499 | V153: =tbl_EcommerceSales[[#This Row],[Gross_Sales]]*tbl_EcommerceSales[[#This Row],[Discount]] -> 374.85 | W153: =tbl_EcommerceSales[[#This Row],[Gross_Sales]]-tbl_EcommerceSales[[#This Row],[Discount_Amount]] -> 2124.15 | X153: =tbl_EcommerceSales[[#This Row],[Quantity]] * _xlfn.XLOOKUP(tbl_EcommerceSales[[#This Row],[Product_ID]], Product_Master!A:A, Product_Master!F:F) -> 1450 | Y153: =tbl_EcommerceSales[[#This Row],[Net_Revenue]]-tbl_EcommerceSales[[#This Row],[Total_Cost]] -> 674.15 | Z153: =IFERROR(#REF!/tbl_EcommerceSales[[#This Row],[Total_Cost]], 0) -> 0 | AA153: =TEXT(tbl_EcommerceSales[[#This Row],[Order_Date]],"mmm") -> Jan | AB153: =YEAR(tbl_EcommerceSales[[#This Row],[Order_Date]]) -> 2025 | AC153: =IF(tbl_EcommerceSales[[#This Row],[Age]]<18,"Under 18",IF(tbl_EcommerceSales[[#This Row],[Age]]<=25,"18-25",IF(tbl_EcommerceSales[[#This Row],[Age]]<=35,"26-35",IF(tbl_EcommerceSales[[#This Row],[Age]]<=45,"36-45",IF(tbl_EcommerceSales[[#This Row],[Age]]<=55,"46-55","56+"))))) -> 26-35
A154: ORD100985 | B154: 45674 | C154: CUST1877 | D154: Pranav Bansal | E154: Male | F154: 39 | G154: Chennai | H154: South | I154: P005 | J154: Power Bank 20000mAh | K154: Electronics | L154: Accessories | M154: 1 | N154: 1599 | O154: 0.15 | P154: 920 | Q154: Credit Card | R154: Delivered | S154: Website | T154: 4 | U154: =M154*N154 -> 1599 | V154: =tbl_EcommerceSales[[#This Row],[Gross_Sales]]*tbl_EcommerceSales[[#This Row],[Discount]] -> 239.85 | W154: =tbl_EcommerceSales[[#This Row],[Gross_Sales]]-tbl_EcommerceSales[[#This Row],[Discount_Amount]] -> 1359.15 | X154: =tbl_EcommerceSales[[#This Row],[Quantity]] * _xlfn.XLOOKUP(tbl_EcommerceSales[[#This Row],[Product_ID]], Product_Master!A:A, Product_Master!F:F) -> 920 | Y154: =tbl_EcommerceSales[[#This Row],[Net_Revenue]]-tbl_EcommerceSales[[#This Row],[Total_Cost]] -> 439.15 | Z154: =IFERROR(#REF!/tbl_EcommerceSales[[#This Row],[Total_Cost]], 0) -> 0 | AA154: =TEXT(tbl_EcommerceSales[[#This Row],[Order_Date]],"mmm") -> Jan | AB154: =YEAR(tbl_EcommerceSales[[#This Row],[Order_Date]]) -> 2025 | AC154: =IF(tbl_EcommerceSales[[#This Row],[Age]]<18,"Under 18",IF(tbl_EcommerceSales[[#This Row],[Age]]<=25,"18-25",IF(tbl_EcommerceSales[[#This Row],[Age]]<=35,"26-35",IF(tbl_EcommerceSales[[#This Row],[Age]]<=45,"36-45",IF(tbl_EcommerceSales[[#This Row],[Age]]<=55,"46-55","56+"))))) -> 36-45
A155: ORD100247 | B155: 45674 | C155: CUST1276 | D155: Ananya Kumar | E155: Female | F155: 61 | G155: Ahmedabad | H155: West | I155: P004 | J155: USB-C Charger | K155: Electronics | L155: Accessories | M155: 2 | N155: 899 | O155: 0.25 | P155: 960 | Q155: Credit Card | R155: Delivered | S155: Mobile App | T155: 4 | U155: =M155*N155 -> 1798 | V155: =tbl_EcommerceSales[[#This Row],[Gross_Sales]]*tbl_EcommerceSales[[#This Row],[Discount]] -> 449.5 | W155: =tbl_EcommerceSales[[#This Row],[Gross_Sales]]-tbl_EcommerceSales[[#This Row],[Discount_Amount]] -> 1348.5 | X155: =tbl_EcommerceSales[[#This Row],[Quantity]] * _xlfn.XLOOKUP(tbl_EcommerceSales[[#This Row],[Product_ID]], Product_Master!A:A, Product_Master!F:F) -> 960 | Y155: =tbl_EcommerceSales[[#This Row],[Net_Revenue]]-tbl_EcommerceSales[[#This Row],[Total_Cost]] -> 388.5 | Z155: =IFERROR(#REF!/tbl_EcommerceSales[[#This Row],[Total_Cost]], 0) -> 0 | AA155: =TEXT(tbl_EcommerceSales[[#This Row],[Order_Date]],"mmm") -> Jan | AB155: =YEAR(tbl_EcommerceSales[[#This Row],[Order_Date]]) -> 2025 | AC155: =IF(tbl_EcommerceSales[[#This Row],[Age]]<18,"Under 18",IF(tbl_EcommerceSales[[#This Row],[Age]]<=25,"18-25",IF(tbl_EcommerceSales[[#This Row],[Age]]<=35,"26-35",IF(tbl_EcommerceSales[[#This Row],[Age]]<=45,"36-45",IF(tbl_EcommerceSales[[#This Row],[Age]]<=55,"46-55","56+"))))) -> 56+
A156: ORD103396 | B156: 45674 | C156: CUST0440 | D156: Ishaan Malhotra | E156: Male | F156: 18 | G156: Amritsar | H156: North | I156: P003 | J156: Smart Watch | K156: Electronics | L156: Wearables | M156: 2 | N156: 3299 | O156: 0.1 | P156: 4200 | Q156: Net Banking | R156: Delivered | S156: Website | T156: 3 | U156: =M156*N156 -> 6598 | V156: =tbl_EcommerceSales[[#This Row],[Gross_Sales]]*tbl_EcommerceSales[[#This Row],[Discount]] -> 659.8 | W156: =tbl_EcommerceSales[[#This Row],[Gross_Sales]]-tbl_EcommerceSales[[#This Row],[Discount_Amount]] -> 5938.2 | X156: =tbl_EcommerceSales[[#This Row],[Quantity]] * _xlfn.XLOOKUP(tbl_EcommerceSales[[#This Row],[Product_ID]], Product_Master!A:A, Product_Master!F:F) -> 4200 | Y156: =tbl_EcommerceSales[[#This Row],[Net_Revenue]]-tbl_EcommerceSales[[#This Row],[Total_Cost]] -> 1738.2 | Z156: =IFERROR(#REF!/tbl_EcommerceSales[[#This Row],[Total_Cost]], 0) -> 0 | AA156: =TEXT(tbl_EcommerceSales[[#This Row],[Order_Date]],"mmm") -> Jan | AB156: =YEAR(tbl_EcommerceSales[[#This Row],[Order_Date]]) -> 2025 | AC156: =IF(tbl_EcommerceSales[[#This Row],[Age]]<18,"Under 18",IF(tbl_EcommerceSales[[#This Row],[Age]]<=25,"18-25",IF(tbl_EcommerceSales[[#This Row],[Age]]<=35,"26-35",IF(tbl_EcommerceSales[[#This Row],[Age]]<=45,"36-45",IF(tbl_EcommerceSales[[#This Row],[Age]]<=55,"46-55","56+"))))) -> 18-25
A157: ORD101889 | B157: 45674 | C157: CUST1252 | D157: Varun Jain | E157: Female | F157: 24 | G157: Bhubaneswar | H157: East | I157: P024 | J157: Perfume | K157: Beauty | L157: Fragrance | M157: 1 | N157: 1799 | O157: 0.1 | P157: 900 | Q157: UPI | R157: Delivered | S157: Mobile App | T157: 5 | U157: =M157*N157 -> 1799 | V157: =tbl_EcommerceSales[[#This Row],[Gross_Sales]]*tbl_EcommerceSales[[#This Row],[Discount]] -> 179.9 | W157: =tbl_EcommerceSales[[#This Row],[Gross_Sales]]-tbl_EcommerceSales[[#This Row],[Discount_Amount]] -> 1619.1 | X157: =tbl_EcommerceSales[[#This Row],[Quantity]] * _xlfn.XLOOKUP(tbl_EcommerceSales[[#This Row],[Product_ID]], Product_Master!A:A, Product_Master!F:F) -> 900 | Y157: =tbl_EcommerceSales[[#This Row],[Net_Revenue]]-tbl_EcommerceSales[[#This Row],[Total_Cost]] -> 719.1 | Z157: =IFERROR(#REF!/tbl_EcommerceSales[[#This Row],[Total_Cost]], 0) -> 0 | AA157: =TEXT(tbl_EcommerceSales[[#This Row],[Order_Date]],"mmm") -> Jan | AB157: =YEAR(tbl_EcommerceSales[[#This Row],[Order_Date]]) -> 2025 | AC157: =IF(tbl_EcommerceSales[[#This Row],[Age]]<18,"Under 18",IF(tbl_EcommerceSales[[#This Row],[Age]]<=25,"18-25",IF(tbl_EcommerceSales[[#This Row],[Age]]<=35,"26-35",IF(tbl_EcommerceSales[[#This Row],[Age]]<=45,"36-45",IF(tbl_EcommerceSales[[#This Row],[Age]]<=55,"46-55","56+"))))) -> 18-25
A158: ORD101028 | B158: 45674 | C158: CUST1105 | D158: Sakshi Mishra | E158: Female | F158: 41 | G158: Chennai | H158: South | I158: P020 | J158: Resistance Bands | K158: Sports & Fitness | L158: Fitness | M158: 1 | N158: 699 | O158: 0.3 | P158: 320 | Q158: Credit Card | R158: Delivered | S158: Mobile App | T158: 5 | U158: =M158*N158 -> 699 | V158: =tbl_EcommerceSales[[#This Row],[Gross_Sales]]*tbl_EcommerceSales[[#This Row],[Discount]] -> 209.7 | W158: =tbl_EcommerceSales[[#This Row],[Gross_Sales]]-tbl_EcommerceSales[[#This Row],[Discount_Amount]] -> 489.3 | X158: =tbl_EcommerceSales[[#This Row],[Quantity]] * _xlfn.XLOOKUP(tbl_EcommerceSales[[#This Row],[Product_ID]], Product_Master!A:A, Product_Master!F:F) -> 320 | Y158: =tbl_EcommerceSales[[#This Row],[Net_Revenue]]-tbl_EcommerceSales[[#This Row],[Total_Cost]] -> 169.3 | Z158: =IFERROR(#REF!/tbl_EcommerceSales[[#This Row],[Total_Cost]], 0) -> 0 | AA158: =TEXT(tbl_EcommerceSales[[#This Row],[Order_Date]],"mmm") -> Jan | AB158: =YEAR(tbl_EcommerceSales[[#This Row],[Order_Date]]) -> 2025 | AC158: =IF(tbl_EcommerceSales[[#This Row],[Age]]<18,"Under 18",IF(tbl_EcommerceSales[[#This Row],[Age]]<=25,"18-25",IF(tbl_EcommerceSales[[#This Row],[Age]]<=35,"26-35",IF(tbl_EcommerceSales[[#This Row],[Age]]<=45,"36-45",IF(tbl_EcommerceSales[[#This Row],[Age]]<=55,"46-55","56+"))))) -> 36-45
A159: ORD101860 | B159: 45674 | C159: CUST1793 | D159: Diya Mishra | E159: Female | F159: 30 | G159: Patna | H159: East | I159: P029 | J159: Programming Book | K159: Books | L159: Technology | M159: 2 | N159: 1299 | O159: 0.1 | P159: 1220 | Q159: UPI | R159: Delivered | S159: Website | T159: 3 | U159: =M159*N159 -> 2598 | V159: =tbl_EcommerceSales[[#This Row],[Gross_Sales]]*tbl_EcommerceSales[[#This Row],[Discount]] -> 259.8 | W159: =tbl_EcommerceSales[[#This Row],[Gross_Sales]]-tbl_EcommerceSales[[#This Row],[Discount_Amount]] -> 2338.2 | X159: =tbl_EcommerceSales[[#This Row],[Quantity]] * _xlfn.XLOOKUP(tbl_EcommerceSales[[#This Row],[Product_ID]], Product_Master!A:A, Product_Master!F:F) -> 1220 | Y159: =tbl_EcommerceSales[[#This Row],[Net_Revenue]]-tbl_EcommerceSales[[#This Row],[Total_Cost]] -> 1118.2 | Z159: =IFERROR(#REF!/tbl_EcommerceSales[[#This Row],[Total_Cost]], 0) -> 0 | AA159: =TEXT(tbl_EcommerceSales[[#This Row],[Order_Date]],"mmm") -> Jan | AB159: =YEAR(tbl_EcommerceSales[[#This Row],[Order_Date]]) -> 2025 | AC159: =IF(tbl_EcommerceSales[[#This Row],[Age]]<18,"Under 18",IF(tbl_EcommerceSales[[#This Row],[Age]]<=25,"18-25",IF(tbl_EcommerceSales[[#This Row],[Age]]<=35,"26-35",IF(tbl_EcommerceSales[[#This Row],[Age]]<=45,"36-45",IF(tbl_EcommerceSales[[#This Row],[Age]]<=55,"46-55","56+"))))) -> 26-35
A160: ORD102785 | B160: 45674 | C160: CUST1691 | D160: Vansh Chopra | E160: Male | F160: 30 | G160: Surat | H160: West | I160: P010 | J160: Casual Hoodie | K160: Fashion | L160: Clothing | M160: 1 | N160: 1499 | O160: 0.3 | P160: 780 | Q160: UPI | R160: Delivered | S160: Mobile App | T160: 5 | U160: =M160*N160 -> 1499 | V160: =tbl_EcommerceSales[[#This Row],[Gross_Sales]]*tbl_EcommerceSales[[#This Row],[Discount]] -> 449.7 | W160: =tbl_EcommerceSales[[#This Row],[Gross_Sales]]-tbl_EcommerceSales[[#This Row],[Discount_Amount]] -> 1049.3 | X160: =tbl_EcommerceSales[[#This Row],[Quantity]] * _xlfn.XLOOKUP(tbl_EcommerceSales[[#This Row],[Product_ID]], Product_Master!A:A, Product_Master!F:F) -> 780 | Y160: =tbl_EcommerceSales[[#This Row],[Net_Revenue]]-tbl_EcommerceSales[[#This Row],[Total_Cost]] -> 269.3 | Z160: =IFERROR(#REF!/tbl_EcommerceSales[[#This Row],[Total_Cost]], 0) -> 0 | AA160: =TEXT(tbl_EcommerceSales[[#This Row],[Order_Date]],"mmm") -> Jan | AB160: =YEAR(tbl_EcommerceSales[[#This Row],[Order_Date]]) -> 2025 | AC160: =IF(tbl_EcommerceSales[[#This Row],[Age]]<18,"Under 18",IF(tbl_EcommerceSales[[#This Row],[Age]]<=25,"18-25",IF(tbl_EcommerceSales[[#This Row],[Age]]<=35,"26-35",IF(tbl_EcommerceSales[[#This Row],[Age]]<=45,"36-45",IF(tbl_EcommerceSales[[#This Row],[Age]]<=55,"46-55","56+"))))) -> 26-35
A161: ORD103164 | B161: 45674 | C161: CUST1760 | D161: Aarav Sharma | E161: Male | F161: 32 | G161: Chennai | H161: South | I161: P002 | J161: Bluetooth Speaker | K161: Electronics | L161: Audio | M161: 1 | N161: 1899 | O161: 0.1 | P161: 1120 | Q161: Debit Card | R161: Delivered | S161: Mobile App | T161: 5 | U161: =M161*N161 -> 1899 | V161: =tbl_EcommerceSales[[#This Row],[Gross_Sales]]*tbl_EcommerceSales[[#This Row],[Discount]] -> 189.9 | W161: =tbl_EcommerceSales[[#This Row],[Gross_Sales]]-tbl_EcommerceSales[[#This Row],[Discount_Amount]] -> 1709.1 | X161: =tbl_EcommerceSales[[#This Row],[Quantity]] * _xlfn.XLOOKUP(tbl_EcommerceSales[[#This Row],[Product_ID]], Product_Master!A:A, Product_Master!F:F) -> 1120 | Y161: =tbl_EcommerceSales[[#This Row],[Net_Revenue]]-tbl_EcommerceSales[[#This Row],[Total_Cost]] -> 589.1 | Z161: =IFERROR(#REF!/tbl_EcommerceSales[[#This Row],[Total_Cost]], 0) -> 0 | AA161: =TEXT(tbl_EcommerceSales[[#This Row],[Order_Date]],"mmm") -> Jan | AB161: =YEAR(tbl_EcommerceSales[[#This Row],[Order_Date]]) -> 2025 | AC161: =IF(tbl_EcommerceSales[[#This Row],[Age]]<18,"Under 18",IF(tbl_EcommerceSales[[#This Row],[Age]]<=25,"18-25",IF(tbl_EcommerceSales[[#This Row],[Age]]<=35,"26-35",IF(tbl_EcommerceSales[[#This Row],[Age]]<=45,"36-45",IF(tbl_EcommerceSales[[#This Row],[Age]]<=55,"46-55","56+"))))) -> 26-35
A162: ORD101255 | B162: 45674 | C162: CUST1776 | D162: Mohit Sharma | E162: Female | F162: 19 | G162: Surat | H162: West | I162: P024 | J162: Perfume | K162: Beauty | L162: Fragrance | M162: 1 | N162: 1799 | O162: 0.2 | P162: 900 | Q162: UPI | R162: Cancelled | S162: Mobile App | U162: =M162*N162 -> 1799 | V162: =tbl_EcommerceSales[[#This Row],[Gross_Sales]]*tbl_EcommerceSales[[#This Row],[Discount]] -> 359.8 | W162: =tbl_EcommerceSales[[#This Row],[Gross_Sales]]-tbl_EcommerceSales[[#This Row],[Discount_Amount]] -> 1439.2 | X162: =tbl_EcommerceSales[[#This Row],[Quantity]] * _xlfn.XLOOKUP(tbl_EcommerceSales[[#This Row],[Product_ID]], Product_Master!A:A, Product_Master!F:F) -> 900 | Y162: =tbl_EcommerceSales[[#This Row],[Net_Revenue]]-tbl_EcommerceSales[[#This Row],[Total_Cost]] -> 539.2 | Z162: =IFERROR(#REF!/tbl_EcommerceSales[[#This Row],[Total_Cost]], 0) -> 0 | AA162: =TEXT(tbl_EcommerceSales[[#This Row],[Order_Date]],"mmm") -> Jan | AB162: =YEAR(tbl_EcommerceSales[[#This Row],[Order_Date]]) -> 2025 | AC162: =IF(tbl_EcommerceSales[[#This Row],[Age]]<18,"Under 18",IF(tbl_EcommerceSales[[#This Row],[Age]]<=25,"18-25",IF(tbl_EcommerceSales[[#This Row],[Age]]<=35,"26-35",IF(tbl_EcommerceSales[[#This Row],[Age]]<=45,"36-45",IF(tbl_EcommerceSales[[#This Row],[Age]]<=55,"46-55","56+"))))) -> 18-25
A163: ORD102951 | B163: 45674 | C163: CUST1482 | D163: Arjun Rao | E163: Female | F163: 21 | G163: Ahmedabad | H163: West | I163: P005 | J163: Power Bank 20000mAh | K163: Electronics | L163: Accessories | M163: 2 | N163: 1599 | O163: 0.1 | P163: 1840 | Q163: Debit Card | R163: Delivered | S163: Website | T163: 2 | U163: =M163*N163 -> 3198 | V163: =tbl_EcommerceSales[[#This Row],[Gross_Sales]]*tbl_EcommerceSales[[#This Row],[Discount]] -> 319.8 | W163: =tbl_EcommerceSales[[#This Row],[Gross_Sales]]-tbl_EcommerceSales[[#This Row],[Discount_Amount]] -> 2878.2 | X163: =tbl_EcommerceSales[[#This Row],[Quantity]] * _xlfn.XLOOKUP(tbl_EcommerceSales[[#This Row],[Product_ID]], Product_Master!A:A, Product_Master!F:F) -> 1840 | Y163: =tbl_EcommerceSales[[#This Row],[Net_Revenue]]-tbl_EcommerceSales[[#This Row],[Total_Cost]] -> 1038.2 | Z163: =IFERROR(#REF!/tbl_EcommerceSales[[#This Row],[Total_Cost]], 0) -> 0 | AA163: =TEXT(tbl_EcommerceSales[[#This Row],[Order_Date]],"mmm") -> Jan | AB163: =YEAR(tbl_EcommerceSales[[#This Row],[Order_Date]]) -> 2025 | AC163: =IF(tbl_EcommerceSales[[#This Row],[Age]]<18,"Under 18",IF(tbl_EcommerceSales[[#This Row],[Age]]<=25,"18-25",IF(tbl_EcommerceSales[[#This Row],[Age]]<=35,"26-35",IF(tbl_EcommerceSales[[#This Row],[Age]]<=45,"36-45",IF(tbl_EcommerceSales[[#This Row],[Age]]<=55,"46-55","56+"))))) -> 18-25
A164: ORD101045 | B164: 45674 | C164: CUST0034 | D164: Manish Agarwal | E164: Male | F164: 33 | G164: Bokaro | H164: East | I164: P008 | J164: Cotton T-Shirt | K164: Fashion | L164: Clothing | M164: 2 | N164: 799 | O164: 0.05 | P164: 780 | Q164: Net Banking | R164: Delivered | S164: Mobile App | T164: 4 | U164: =M164*N164 -> 1598 | V164: =tbl_EcommerceSales[[#This Row],[Gross_Sales]]*tbl_EcommerceSales[[#This Row],[Discount]] -> 79.9 | W164: =tbl_EcommerceSales[[#This Row],[Gross_Sales]]-tbl_EcommerceSales[[#This Row],[Discount_Amount]] -> 1518.1 | X164: =tbl_EcommerceSales[[#This Row],[Quantity]] * _xlfn.XLOOKUP(tbl_EcommerceSales[[#This Row],[Product_ID]], Product_Master!A:A, Product_Master!F:F) -> 780 | Y164: =tbl_EcommerceSales[[#This Row],[Net_Revenue]]-tbl_EcommerceSales[[#This Row],[Total_Cost]] -> 738.1 | Z164: =IFERROR(#REF!/tbl_EcommerceSales[[#This Row],[Total_Cost]], 0) -> 0 | AA164: =TEXT(tbl_EcommerceSales[[#This Row],[Order_Date]],"mmm") -> Jan | AB164: =YEAR(tbl_EcommerceSales[[#This Row],[Order_Date]]) -> 2025 | AC164: =IF(tbl_EcommerceSales[[#This Row],[Age]]<18,"Under 18",IF(tbl_EcommerceSales[[#This Row],[Age]]<=25,"18-25",IF(tbl_EcommerceSales[[#This Row],[Age]]<=35,"26-35",IF(tbl_EcommerceSales[[#This Row],[Age]]<=45,"36-45",IF(tbl_EcommerceSales[[#This Row],[Age]]<=55,"46-55","56+"))))) -> 26-35
A165: ORD101234 | B165: 45674 | C165: CUST0950 | D165: Simran Gupta | E165: Female | F165: 39 | G165: Hyderabad | H165: South | I165: P007 | J165: Running Shoes | K165: Fashion | L165: Footwear | M165: 1 | N165: 2899 | O165: 0.05 | P165: 1700 | Q165: Debit Card | R165: Delivered | S165: Website | T165: 4 | U165: =M165*N165 -> 2899 | V165: =tbl_EcommerceSales[[#This Row],[Gross_Sales]]*tbl_EcommerceSales[[#This Row],[Discount]] -> 144.95 | W165: =tbl_EcommerceSales[[#This Row],[Gross_Sales]]-tbl_EcommerceSales[[#This Row],[Discount_Amount]] -> 2754.05 | X165: =tbl_EcommerceSales[[#This Row],[Quantity]] * _xlfn.XLOOKUP(tbl_EcommerceSales[[#This Row],[Product_ID]], Product_Master!A:A, Product_Master!F:F) -> 1700 | Y165: =tbl_EcommerceSales[[#This Row],[Net_Revenue]]-tbl_EcommerceSales[[#This Row],[Total_Cost]] -> 1054.05 | Z165: =IFERROR(#REF!/tbl_EcommerceSales[[#This Row],[Total_Cost]], 0) -> 0 | AA165: =TEXT(tbl_EcommerceSales[[#This Row],[Order_Date]],"mmm") -> Jan | AB165: =YEAR(tbl_EcommerceSales[[#This Row],[Order_Date]]) -> 2025 | AC165: =IF(tbl_EcommerceSales[[#This Row],[Age]]<18,"Under 18",IF(tbl_EcommerceSales[[#This Row],[Age]]<=25,"18-25",IF(tbl_EcommerceSales[[#This Row],[Age]]<=35,"26-35",IF(tbl_EcommerceSales[[#This Row],[Age]]<=45,"36-45",IF(tbl_EcommerceSales[[#This Row],[Age]]<=55,"46-55","56+"))))) -> 36-45
A166: ORD103357 | B166: 45675 | C166: CUST0267 | D166: Kiara Chopra | E166: Female | F166: 27 | G166: Chennai | H166: South | I166: P010 | J166: Casual Hoodie | K166: Fashion | L166: Clothing | M166: 1 | N166: 1499 | O166: 0 | P166: 780 | Q166: Credit Card | R166: Delivered | S166: Mobile App | T166: 5 | U166: =M166*N166 -> 1499 | V166: =tbl_EcommerceSales[[#This Row],[Gross_Sales]]*tbl_EcommerceSales[[#This Row],[Discount]] -> 0 | W166: =tbl_EcommerceSales[[#This Row],[Gross_Sales]]-tbl_EcommerceSales[[#This Row],[Discount_Amount]] -> 1499 | X166: =tbl_EcommerceSales[[#This Row],[Quantity]] * _xlfn.XLOOKUP(tbl_EcommerceSales[[#This Row],[Product_ID]], Product_Master!A:A, Product_Master!F:F) -> 780 | Y166: =tbl_EcommerceSales[[#This Row],[Net_Revenue]]-tbl_EcommerceSales[[#This Row],[Total_Cost]] -> 719 | Z166: =IFERROR(#REF!/tbl_EcommerceSales[[#This Row],[Total_Cost]], 0) -> 0 | AA166: =TEXT(tbl_EcommerceSales[[#This Row],[Order_Date]],"mmm") -> Jan | AB166: =YEAR(tbl_EcommerceSales[[#This Row],[Order_Date]]) -> 2025 | AC166: =IF(tbl_EcommerceSales[[#This Row],[Age]]<18,"Under 18",IF(tbl_EcommerceSales[[#This Row],[Age]]<=25,"18-25",IF(tbl_EcommerceSales[[#This Row],[Age]]<=35,"26-35",IF(tbl_EcommerceSales[[#This Row],[Age]]<=45,"36-45",IF(tbl_EcommerceSales[[#This Row],[Age]]<=55,"46-55","56+"))))) -> 26-35
A167: ORD100897 | B167: 45675 | C167: CUST1309 | D167: Kavya Patel | E167: Male | F167: 41 | G167: Jaipur | H167: North | I167: P004 | J167: USB-C Charger | K167: Electronics | L167: Accessories | M167: 4 | N167: 899 | O167: 0.25 | P167: 1920 | Q167: UPI | R167: Delivered | S167: Mobile App | T167: 3 | U167: =M167*N167 -> 3596 | V167: =tbl_EcommerceSales[[#This Row],[Gross_Sales]]*tbl_EcommerceSales[[#This Row],[Discount]] -> 899 | W167: =tbl_EcommerceSales[[#This Row],[Gross_Sales]]-tbl_EcommerceSales[[#This Row],[Discount_Amount]] -> 2697 | X167: =tbl_EcommerceSales[[#This Row],[Quantity]] * _xlfn.XLOOKUP(tbl_EcommerceSales[[#This Row],[Product_ID]], Product_Master!A:A, Product_Master!F:F) -> 1920 | Y167: =tbl_EcommerceSales[[#This Row],[Net_Revenue]]-tbl_EcommerceSales[[#This Row],[Total_Cost]] -> 777 | Z167: =IFERROR(#REF!/tbl_EcommerceSales[[#This Row],[Total_Cost]], 0) -> 0 | AA167: =TEXT(tbl_EcommerceSales[[#This Row],[Order_Date]],"mmm") -> Jan | AB167: =YEAR(tbl_EcommerceSales[[#This Row],[Order_Date]]) -> 2025 | AC167: =IF(tbl_EcommerceSales[[#This Row],[Age]]<18,"Under 18",IF(tbl_EcommerceSales[[#This Row],[Age]]<=25,"18-25",IF(tbl_EcommerceSales[[#This Row],[Age]]<=35,"26-35",IF(tbl_EcommerceSales[[#This Row],[Age]]<=45,"36-45",IF(tbl_EcommerceSales[[#This Row],[Age]]<=55,"46-55","56+"))))) -> 36-45
A168: ORD100270 | B168: 45675 | C168: CUST0701 | D168: Kavya Patel | E168: Male | F168: 31 | G168: Lucknow | H168: North | I168: P005 | J168: Power Bank 20000mAh | K168: Electronics | L168: Accessories | M168: 1 | N168: 1599 | O168: 0.05 | P168: 920 | Q168: Cash on Delivery | R168: Delivered | S168: Mobile App | T168: 1 | U168: =M168*N168 -> 1599 | V168: =tbl_EcommerceSales[[#This Row],[Gross_Sales]]*tbl_EcommerceSales[[#This Row],[Discount]] -> 79.95 | W168: =tbl_EcommerceSales[[#This Row],[Gross_Sales]]-tbl_EcommerceSales[[#This Row],[Discount_Amount]] -> 1519.05 | X168: =tbl_EcommerceSales[[#This Row],[Quantity]] * _xlfn.XLOOKUP(tbl_EcommerceSales[[#This Row],[Product_ID]], Product_Master!A:A, Product_Master!F:F) -> 920 | Y168: =tbl_EcommerceSales[[#This Row],[Net_Revenue]]-tbl_EcommerceSales[[#This Row],[Total_Cost]] -> 599.05 | Z168: =IFERROR(#REF!/tbl_EcommerceSales[[#This Row],[Total_Cost]], 0) -> 0 | AA168: =TEXT(tbl_EcommerceSales[[#This Row],[Order_Date]],"mmm") -> Jan | AB168: =YEAR(tbl_EcommerceSales[[#This Row],[Order_Date]]) -> 2025 | AC168: =IF(tbl_EcommerceSales[[#This Row],[Age]]<18,"Under 18",IF(tbl_EcommerceSales[[#This Row],[Age]]<=25,"18-25",IF(tbl_EcommerceSales[[#This Row],[Age]]<=35,"26-35",IF(tbl_EcommerceSales[[#This Row],[Age]]<=45,"36-45",IF(tbl_EcommerceSales[[#This Row],[Age]]<=55,"46-55","56+"))))) -> 26-35
A169: ORD103744 | B169: 45675 | C169: CUST0446 | D169: Pooja Kapoor | E169: Male | F169: 29 | G169: Delhi | H169: North | I169: P009 | J169: Denim Jeans | K169: Fashion | L169: Clothing | M169: 3 | N169: 1999 | O169: 0.1 | P169: 3150 | Q169: Cash on Delivery | R169: Delivered | S169: Mobile App | T169: 4 | U169: =M169*N169 -> 5997 | V169: =tbl_EcommerceSales[[#This Row],[Gross_Sales]]*tbl_EcommerceSales[[#This Row],[Discount]] -> 599.7 | W169: =tbl_EcommerceSales[[#This Row],[Gross_Sales]]-tbl_EcommerceSales[[#This Row],[Discount_Amount]] -> 5397.3 | X169: =tbl_EcommerceSales[[#This Row],[Quantity]] * _xlfn.XLOOKUP(tbl_EcommerceSales[[#This Row],[Product_ID]], Product_Master!A:A, Product_Master!F:F) -> 3150 | Y169: =tbl_EcommerceSales[[#This Row],[Net_Revenue]]-tbl_EcommerceSales[[#This Row],[Total_Cost]] -> 2247.3 | Z169: =IFERROR(#REF!/tbl_EcommerceSales[[#This Row],[Total_Cost]], 0) -> 0 | AA169: =TEXT(tbl_EcommerceSales[[#This Row],[Order_Date]],"mmm") -> Jan | AB169: =YEAR(tbl_EcommerceSales[[#This Row],[Order_Date]]) -> 2025 | AC169: =IF(tbl_EcommerceSales[[#This Row],[Age]]<18,"Under 18",IF(tbl_EcommerceSales[[#This Row],[Age]]<=25,"18-25",IF(tbl_EcommerceSales[[#This Row],[Age]]<=35,"26-35",IF(tbl_EcommerceSales[[#This Row],[Age]]<=45,"36-45",IF(tbl_EcommerceSales[[#This Row],[Age]]<=55,"46-55","56+"))))) -> 26-35
A170: ORD104989 | B170: 45675 | C170: CUST0300 | D170: Rahul Kumar | E170: Male | F170: 33 | G170: Chandigarh | H170: North | I170: P003 | J170: Smart Watch | K170: Electronics | L170: Wearables | M170: 1 | N170: 3299 | O170: 0.1 | P170: 2100 | Q170: Net Banking | R170: Delivered | S170: Mobile App | T170: 5 | U170: =M170*N170 -> 3299 | V170: =tbl_EcommerceSales[[#This Row],[Gross_Sales]]*tbl_EcommerceSales[[#This Row],[Discount]] -> 329.9 | W170: =tbl_EcommerceSales[[#This Row],[Gross_Sales]]-tbl_EcommerceSales[[#This Row],[Discount_Amount]] -> 2969.1 | X170: =tbl_EcommerceSales[[#This Row],[Quantity]] * _xlfn.XLOOKUP(tbl_EcommerceSales[[#This Row],[Product_ID]], Product_Master!A:A, Product_Master!F:F) -> 2100 | Y170: =tbl_EcommerceSales[[#This Row],[Net_Revenue]]-tbl_EcommerceSales[[#This Row],[Total_Cost]] -> 869.1 | Z170: =IFERROR(#REF!/tbl_EcommerceSales[[#This Row],[Total_Cost]], 0) -> 0 | AA170: =TEXT(tbl_EcommerceSales[[#This Row],[Order_Date]],"mmm") -> Jan | AB170: =YEAR(tbl_EcommerceSales[[#This Row],[Order_Date]]) -> 2025 | AC170: =IF(tbl_EcommerceSales[[#This Row],[Age]]<18,"Under 18",IF(tbl_EcommerceSales[[#This Row],[Age]]<=25,"18-25",IF(tbl_EcommerceSales[[#This Row],[Age]]<=35,"26-35",IF(tbl_EcommerceSales[[#This Row],[Age]]<=45,"36-45",IF(tbl_EcommerceSales[[#This Row],[Age]]<=55,"46-55","56+"))))) -> 26-35
A171: ORD103582 | B171: 45676 | C171: CUST1672 | D171: Sanya Malhotra | E171: Female | F171: 30 | G171: Mumbai | H171: West | I171: P025 | J171: Moisturizer | K171: Beauty | L171: Skincare | M171: 2 | N171: 699 | O171: 0.1 | P171: 620 | Q171: Debit Card | R171: Delivered | S171: Website | T171: 4 | U171: =M171*N171 -> 1398 | V171: =tbl_EcommerceSales[[#This Row],[Gross_Sales]]*tbl_EcommerceSales[[#This Row],[Discount]] -> 139.8 | W171: =tbl_EcommerceSales[[#This Row],[Gross_Sales]]-tbl_EcommerceSales[[#This Row],[Discount_Amount]] -> 1258.2 | X171: =tbl_EcommerceSales[[#This Row],[Quantity]] * _xlfn.XLOOKUP(tbl_EcommerceSales[[#This Row],[Product_ID]], Product_Master!A:A, Product_Master!F:F) -> 620 | Y171: =tbl_EcommerceSales[[#This Row],[Net_Revenue]]-tbl_EcommerceSales[[#This Row],[Total_Cost]] -> 638.2 | Z171: =IFERROR(#REF!/tbl_EcommerceSales[[#This Row],[Total_Cost]], 0) -> 0 | AA171: =TEXT(tbl_EcommerceSales[[#This Row],[Order_Date]],"mmm") -> Jan | AB171: =YEAR(tbl_EcommerceSales[[#This Row],[Order_Date]]) -> 2025 | AC171: =IF(tbl_EcommerceSales[[#This Row],[Age]]<18,"Under 18",IF(tbl_EcommerceSales[[#This Row],[Age]]<=25,"18-25",IF(tbl_EcommerceSales[[#This Row],[Age]]<=35,"26-35",IF(tbl_EcommerceSales[[#This Row],[Age]]<=45,"36-45",IF(tbl_EcommerceSales[[#This Row],[Age]]<=55,"46-55","56+"))))) -> 26-35
A172: ORD101976 | B172: 45676 | C172: CUST0396 | D172: Rahul Kumar | E172: Female | F172: 33 | G172: Surat | H172: West | I172: P017 | J172: Dumbbell Set | K172: Sports & Fitness | L172: Fitness | M172: 3 | N172: 2499 | O172: 0.3 | P172: 4350 | Q172: Debit Card | R172: Delivered | S172: Mobile App | T172: 3 | U172: =M172*N172 -> 7497 | V172: =tbl_EcommerceSales[[#This Row],[Gross_Sales]]*tbl_EcommerceSales[[#This Row],[Discount]] -> 2249.1 | W172: =tbl_EcommerceSales[[#This Row],[Gross_Sales]]-tbl_EcommerceSales[[#This Row],[Discount_Amount]] -> 5247.9 | X172: =tbl_EcommerceSales[[#This Row],[Quantity]] * _xlfn.XLOOKUP(tbl_EcommerceSales[[#This Row],[Product_ID]], Product_Master!A:A, Product_Master!F:F) -> 4350 | Y172: =tbl_EcommerceSales[[#This Row],[Net_Revenue]]-tbl_EcommerceSales[[#This Row],[Total_Cost]] -> 897.9 | Z172: =IFERROR(#REF!/tbl_EcommerceSales[[#This Row],[Total_Cost]], 0) -> 0 | AA172: =TEXT(tbl_EcommerceSales[[#This Row],[Order_Date]],"mmm") -> Jan | AB172: =YEAR(tbl_EcommerceSales[[#This Row],[Order_Date]]) -> 2025 | AC172: =IF(tbl_EcommerceSales[[#This Row],[Age]]<18,"Under 18",IF(tbl_EcommerceSales[[#This Row],[Age]]<=25,"18-25",IF(tbl_EcommerceSales[[#This Row],[Age]]<=35,"26-35",IF(tbl_EcommerceSales[[#This Row],[Age]]<=45,"36-45",IF(tbl_EcommerceSales[[#This Row],[Age]]<=55,"46-55","56+"))))) -> 26-35
A173: ORD102614 | B173: 45676 | C173: CUST1707 | D173: Kiara Chopra | E173: Male | F173: 41 | G173: Chennai | H173: South | I173: P014 | J173: Table Lamp | K173: Home & Kitchen | L173: Home Decor | M173: 2 | N173: 1299 | O173: 0.05 | P173: 1380 | Q173: UPI | R173: Delivered | S173: Mobile App | T173: 5 | U173: =M173*N173 -> 2598 | V173: =tbl_EcommerceSales[[#This Row],[Gross_Sales]]*tbl_EcommerceSales[[#This Row],[Discount]] -> 129.9 | W173: =tbl_EcommerceSales[[#This Row],[Gross_Sales]]-tbl_EcommerceSales[[#This Row],[Discount_Amount]] -> 2468.1 | X173: =tbl_EcommerceSales[[#This Row],[Quantity]] * _xlfn.XLOOKUP(tbl_EcommerceSales[[#This Row],[Product_ID]], Product_Master!A:A, Product_Master!F:F) -> 1380 | Y173: =tbl_EcommerceSales[[#This Row],[Net_Revenue]]-tbl_EcommerceSales[[#This Row],[Total_Cost]] -> 1088.1 | Z173: =IFERROR(#REF!/tbl_EcommerceSales[[#This Row],[Total_Cost]], 0) -> 0 | AA173: =TEXT(tbl_EcommerceSales[[#This Row],[Order_Date]],"mmm") -> Jan | AB173: =YEAR(tbl_EcommerceSales[[#This Row],[Order_Date]]) -> 2025 | AC173: =IF(tbl_EcommerceSales[[#This Row],[Age]]<18,"Under 18",IF(tbl_EcommerceSales[[#This Row],[Age]]<=25,"18-25",IF(tbl_EcommerceSales[[#This Row],[Age]]<=35,"26-35",IF(tbl_EcommerceSales[[#This Row],[Age]]<=45,"36-45",IF(tbl_EcommerceSales[[#This Row],[Age]]<=55,"46-55","56+"))))) -> 36-45
A174: ORD102055 | B174: 45676 | C174: CUST1943 | D174: Aditi Saxena | E174: Male | F174: 18 | G174: Kolkata | H174: East | I174: P007 | J174: Running Shoes | K174: Fashion | L174: Footwear | M174: 1 | N174: 2899 | O174: 0.15 | P174: 1700 | Q174: UPI | R174: Delivered | S174: Mobile App | T174: 4 | U174: =M174*N174 -> 2899 | V174: =tbl_EcommerceSales[[#This Row],[Gross_Sales]]*tbl_EcommerceSales[[#This Row],[Discount]] -> 434.85 | W174: =tbl_EcommerceSales[[#This Row],[Gross_Sales]]-tbl_EcommerceSales[[#This Row],[Discount_Amount]] -> 2464.15 | X174: =tbl_EcommerceSales[[#This Row],[Quantity]] * _xlfn.XLOOKUP(tbl_EcommerceSales[[#This Row],[Product_ID]], Product_Master!A:A, Product_Master!F:F) -> 1700 | Y174: =tbl_EcommerceSales[[#This Row],[Net_Revenue]]-tbl_EcommerceSales[[#This Row],[Total_Cost]] -> 764.15 | Z174: =IFERROR(#REF!/tbl_EcommerceSales[[#This Row],[Total_Cost]], 0) -> 0 | AA174: =TEXT(tbl_EcommerceSales[[#This Row],[Order_Date]],"mmm") -> Jan | AB174: =YEAR(tbl_EcommerceSales[[#This Row],[Order_Date]]) -> 2025 | AC174: =IF(tbl_EcommerceSales[[#This Row],[Age]]<18,"Under 18",IF(tbl_EcommerceSales[[#This Row],[Age]]<=25,"18-25",IF(tbl_EcommerceSales[[#This Row],[Age]]<=35,"26-35",IF(tbl_EcommerceSales[[#This Row],[Age]]<=45,"36-45",IF(tbl_EcommerceSales[[#This Row],[Age]]<=55,"46-55","56+"))))) -> 18-25
... A197: ORD101589 | B197: 45678 | C197: CUST1188 | D197: Varun Jain | E197: Female | F197: 18 | G197: Bengaluru | H197: South | I197: P002 | J197: Bluetooth Speaker | K197: Electronics | L197: Audio | M197: 3 | N197: 1899 | O197: 0.1 | P197: 3360 | Q197: Cash on Delivery | R197: Delivered | S197: Website | T197: 5 | U197: =M197*N197 -> 5697 | V197: =tbl_EcommerceSales[[#This Row],[Gross_Sales]]*tbl_EcommerceSales[[#This Row],[Discount]] -> 569.7 | W197: =tbl_EcommerceSales[[#This Row],[Gross_Sales]]-tbl_EcommerceSales[[#This Row],[Discount_Amount]] -> 5127.3 | X197: =tbl_EcommerceSales[[#This Row],[Quantity]] * _xlfn.XLOOKUP(tbl_EcommerceSales[[#This Row],[Product_ID]], Product_Master!A:A, Product_Master!F:F) -> 3360 | Y197: =tbl_EcommerceSales[[#This Row],[Net_Revenue]]-tbl_EcommerceSales[[#This Row],[Total_Cost]] -> 1767.3 | Z197: =IFERROR(#REF!/tbl_EcommerceSales[[#This Row],[Total_Cost]], 0) -> 0 | AA197: =TEXT(tbl_EcommerceSales[[#This Row],[Order_Date]],"mmm") -> Jan | AB197: =YEAR(tbl_EcommerceSales[[#This Row],[Order_Date]]) -> 2025 | AC197: =IF(tbl_EcommerceSales[[#This Row],[Age]]<18,"Under 18",IF(tbl_EcommerceSales[[#This Row],[Age]]<=25,"18-25",IF(tbl_EcommerceSales[[#This Row],[Age]]<=35,"26-35",IF(tbl_EcommerceSales[[#This Row],[Age]]<=45,"36-45",IF(tbl_EcommerceSales[[#This Row],[Age]]<=55,"46-55","56+"))))) -> 18-25
A198: ORD101856 | B198: 45678 | C198: CUST0050 | D198: Yash Agarwal | E198: Female | F198: 38 | G198: Patna | H198: East | I198: P025 | J198: Moisturizer | K198: Beauty | L198: Skincare | M198: 1 | N198: 699 | O198: 0 | P198: 310 | Q198: Cash on Delivery | R198: Cancelled | S198: Website | U198: =M198*N198 -> 699 | V198: =tbl_EcommerceSales[[#This Row],[Gross_Sales]]*tbl_EcommerceSales[[#This Row],[Discount]] -> 0 | W198: =tbl_EcommerceSales[[#This Row],[Gross_Sales]]-tbl_EcommerceSales[[#This Row],[Discount_Amount]] -> 699 | X198: =tbl_EcommerceSales[[#This Row],[Quantity]] * _xlfn.XLOOKUP(tbl_EcommerceSales[[#This Row],[Product_ID]], Product_Master!A:A, Product_Master!F:F) -> 310 | Y198: =tbl_EcommerceSales[[#This Row],[Net_Revenue]]-tbl_EcommerceSales[[#This Row],[Total_Cost]] -> 389 | Z198: =IFERROR(#REF!/tbl_EcommerceSales[[#This Row],[Total_Cost]], 0) -> 0 | AA198: =TEXT(tbl_EcommerceSales[[#This Row],[Order_Date]],"mmm") -> Jan | AB198: =YEAR(tbl_EcommerceSales[[#This Row],[Order_Date]]) -> 2025 | AC198: =IF(tbl_EcommerceSales[[#This Row],[Age]]<18,"Under 18",IF(tbl_EcommerceSales[[#This Row],[Age]]<=25,"18-25",IF(tbl_EcommerceSales[[#This Row],[Age]]<=35,"26-35",IF(tbl_EcommerceSales[[#This Row],[Age]]<=45,"36-45",IF(tbl_EcommerceSales[[#This Row],[Age]]<=55,"46-55","56+"))))) -> 36-45
A199: ORD103310 | B199: 45678 | C199: CUST1030 | D199: Kabir Gupta | E199: Female | F199: 29 | G199: Kochi | H199: South | I199: P014 | J199: Table Lamp | K199: Home & Kitchen | L199: Home Decor | M199: 2 | N199: 1299 | O199: 0.05 | P199: 1380 | Q199: Credit Card | R199: Delivered | S199: Website | T199: 5 | U199: =M199*N199 -> 2598 | V199: =tbl_EcommerceSales[[#This Row],[Gross_Sales]]*tbl_EcommerceSales[[#This Row],[Discount]] -> 129.9 | W199: =tbl_EcommerceSales[[#This Row],[Gross_Sales]]-tbl_EcommerceSales[[#This Row],[Discount_Amount]] -> 2468.1 | X199: =tbl_EcommerceSales[[#This Row],[Quantity]] * _xlfn.XLOOKUP(tbl_EcommerceSales[[#This Row],[Product_ID]], Product_Master!A:A, Product_Master!F:F) -> 1380 | Y199: =tbl_EcommerceSales[[#This Row],[Net_Revenue]]-tbl_EcommerceSales[[#This Row],[Total_Cost]] -> 1088.1 | Z199: =IFERROR(#REF!/tbl_EcommerceSales[[#This Row],[Total_Cost]], 0) -> 0 | AA199: =TEXT(tbl_EcommerceSales[[#This Row],[Order_Date]],"mmm") -> Jan | AB199: =YEAR(tbl_EcommerceSales[[#This Row],[Order_Date]]) -> 2025 | AC199: =IF(tbl_EcommerceSales[[#This Row],[Age]]<18,"Under 18",IF(tbl_EcommerceSales[[#This Row],[Age]]<=25,"18-25",IF(tbl_EcommerceSales[[#This Row],[Age]]<=35,"26-35",IF(tbl_EcommerceSales[[#This Row],[Age]]<=45,"36-45",IF(tbl_EcommerceSales[[#This Row],[Age]]<=55,"46-55","56+"))))) -> 26-35
A200: ORD102125 | B200: 45678 | C200: CUST2056 | D200: Sanya Malhotra | E200: Male | F200: 25 | G200: Kolkata | H200: East | I200: P029 | J200: Programming Book | K200: Books | L200: Technology | M200: 3 | N200: 1299 | O200: 0.1 | P200: 1830 | Q200: UPI | R200: Delivered | S200: Mobile App | T200: 4 | U200: =M200*N200 -> 3897 | V200: =tbl_EcommerceSales[[#This Row],[Gross_Sales]]*tbl_EcommerceSales[[#This Row],[Discount]] -> 389.7 | W200: =tbl_EcommerceSales[[#This Row],[Gross_Sales]]-tbl_EcommerceSales[[#This Row],[Discount_Amount]] -> 3507.3 | X200: =tbl_EcommerceSales[[#This Row],[Quantity]] * _xlfn.XLOOKUP(tbl_EcommerceSales[[#This Row],[Product_ID]], Product_Master!A:A, Product_Master!F:F) -> 1830 | Y200: =tbl_EcommerceSales[[#This Row],[Net_Revenue]]-tbl_EcommerceSales[[#This Row],[Total_Cost]] -> 1677.3 | Z200: =IFERROR(#REF!/tbl_EcommerceSales[[#This Row],[Total_Cost]], 0) -> 0 | AA200: =TEXT(tbl_EcommerceSales[[#This Row],[Order_Date]],"mmm") -> Jan | AB200: =YEAR(tbl_EcommerceSales[[#This Row],[Order_Date]]) -> 2025 | AC200: =IF(tbl_EcommerceSales[[#This Row],[Age]]<18,"Under 18",IF(tbl_EcommerceSales[[#This Row],[Age]]<=25,"18-25",IF(tbl_EcommerceSales[[#This Row],[Age]]<=35,"26-35",IF(tbl_EcommerceSales[[#This Row],[Age]]<=45,"36-45",IF(tbl_EcommerceSales[[#This Row],[Age]]<=55,"46-55","56+"))))) -> 18-25
A201: ORD101431 | B201: 45678 | C201: CUST1941 | D201: Pranav Bansal | E201: Male | F201: 19 | G201: Mumbai | H201: West | I201: P022 | J201: Sunscreen SPF 50 | K201: Beauty | L201: Skincare | M201: 1 | N201: 799 | O201: 0.1 | P201: 360 | Q201: UPI | R201: Delivered | S201: Mobile App | T201: 1 | U201: =M201*N201 -> 799 | V201: =tbl_EcommerceSales[[#This Row],[Gross_Sales]]*tbl_EcommerceSales[[#This Row],[Discount]] -> 79.9 | W201: =tbl_EcommerceSales[[#This Row],[Gross_Sales]]-tbl_EcommerceSales[[#This Row],[Discount_Amount]] -> 719.1 | X201: =tbl_EcommerceSales[[#This Row],[Quantity]] * _xlfn.XLOOKUP(tbl_EcommerceSales[[#This Row],[Product_ID]], Product_Master!A:A, Product_Master!F:F) -> 360 | Y201: =tbl_EcommerceSales[[#This Row],[Net_Revenue]]-tbl_EcommerceSales[[#This Row],[Total_Cost]] -> 359.1 | Z201: =IFERROR(#REF!/tbl_EcommerceSales[[#This Row],[Total_Cost]], 0) -> 0 | AA201: =TEXT(tbl_EcommerceSales[[#This Row],[Order_Date]],"mmm") -> Jan | AB201: =YEAR(tbl_EcommerceSales[[#This Row],[Order_Date]]) -> 2025 | AC201: =IF(tbl_EcommerceSales[[#This Row],[Age]]<18,"Under 18",IF(tbl_EcommerceSales[[#This Row],[Age]]<=25,"18-25",IF(tbl_EcommerceSales[[#This Row],[Age]]<=35,"26-35",IF(tbl_EcommerceSales[[#This Row],[Age]]<=45,"36-45",IF(tbl_EcommerceSales[[#This Row],[Age]]<=55,"46-55","56+"))))) -> 18-25
A202: ORD100006 | B202: 45678 | C202: CUST0410 | D202: Rohan Rao | E202: Male | F202: 22 | G202: Ranchi | H202: East | I202: P010 | J202: Casual Hoodie | K202: Fashion | L202: Clothing | M202: 1 | N202: 1499 | O202: 0.1 | P202: 780 | Q202: Wallet | R202: Returned | S202: Mobile App | T202: 5 | U202: =M202*N202 -> 1499 | V202: =tbl_EcommerceSales[[#This Row],[Gross_Sales]]*tbl_EcommerceSales[[#This Row],[Discount]] -> 149.9 | W202: =tbl_EcommerceSales[[#This Row],[Gross_Sales]]-tbl_EcommerceSales[[#This Row],[Discount_Amount]] -> 1349.1 | X202: =tbl_EcommerceSales[[#This Row],[Quantity]] * _xlfn.XLOOKUP(tbl_EcommerceSales[[#This Row],[Product_ID]], Product_Master!A:A, Product_Master!F:F) -> 780 | Y202: =tbl_EcommerceSales[[#This Row],[Net_Revenue]]-tbl_EcommerceSales[[#This Row],[Total_Cost]] -> 569.1 | Z202: =IFERROR(#REF!/tbl_EcommerceSales[[#This Row],[Total_Cost]], 0) -> 0 | AA202: =TEXT(tbl_EcommerceSales[[#This Row],[Order_Date]],"mmm") -> Jan | AB202: =YEAR(tbl_EcommerceSales[[#This Row],[Order_Date]]) -> 2025 | AC202: =IF(tbl_EcommerceSales[[#This Row],[Age]]<18,"Under 18",IF(tbl_EcommerceSales[[#This Row],[Age]]<=25,"18-25",IF(tbl_EcommerceSales[[#This Row],[Age]]<=35,"26-35",IF(tbl_EcommerceSales[[#This Row],[Age]]<=45,"36-45",IF(tbl_EcommerceSales[[#This Row],[Age]]<=55,"46-55","56+"))))) -> 18-25
A203: ORD104860 | B203: 45678 | C203: CUST0331 | D203: Kiara Chopra | E203: Female | F203: 41 | G203: Mysuru | H203: South | I203: P002 | J203: Bluetooth Speaker | K203: Electronics | L203: Audio | M203: 1 | N203: 1899 | O203: 0.25 | P203: 1120 | Q203: Debit Card | R203: Delivered | S203: Mobile App | T203: 5 | U203: =M203*N203 -> 1899 | V203: =tbl_EcommerceSales[[#This Row],[Gross_Sales]]*tbl_EcommerceSales[[#This Row],[Discount]] -> 474.75 | W203: =tbl_EcommerceSales[[#This Row],[Gross_Sales]]-tbl_EcommerceSales[[#This Row],[Discount_Amount]] -> 1424.25 | X203: =tbl_EcommerceSales[[#This Row],[Quantity]] * _xlfn.XLOOKUP(tbl_EcommerceSales[[#This Row],[Product_ID]], Product_Master!A:A, Product_Master!F:F) -> 1120 | Y203: =tbl_EcommerceSales[[#This Row],[Net_Revenue]]-tbl_EcommerceSales[[#This Row],[Total_Cost]] -> 304.25 | Z203: =IFERROR(#REF!/tbl_EcommerceSales[[#This Row],[Total_Cost]], 0) -> 0 | AA203: =TEXT(tbl_EcommerceSales[[#This Row],[Order_Date]],"mmm") -> Jan | AB203: =YEAR(tbl_EcommerceSales[[#This Row],[Order_Date]]) -> 2025 | AC203: =IF(tbl_EcommerceSales[[#This Row],[Age]]<18,"Under 18",IF(tbl_EcommerceSales[[#This Row],[Age]]<=25,"18-25",IF(tbl_EcommerceSales[[#This Row],[Age]]<=35,"26-35",IF(tbl_EcommerceSales[[#This Row],[Age]]<=45,"36-45",IF(tbl_EcommerceSales[[#This Row],[Age]]<=55,"46-55","56+"))))) -> 36-45
A204: ORD102603 | B204: 45679 | C204: CUST0185 | D204: Meera Singh | E204: Female | F204: 42 | G204: Mysuru | H204: South | I204: P019 | J204: Badminton Racket | K204: Sports & Fitness | L204: Sports | M204: 2 | N204: 1499 | O204: 0.1 | P204: 1600 | Q204: Credit Card | R204: Delivered | S204: Website | T204: 3 | U204: =M204*N204 -> 2998 | V204: =tbl_EcommerceSales[[#This Row],[Gross_Sales]]*tbl_EcommerceSales[[#This Row],[Discount]] -> 299.8 | W204: =tbl_EcommerceSales[[#This Row],[Gross_Sales]]-tbl_EcommerceSales[[#This Row],[Discount_Amount]] -> 2698.2 | X204: =tbl_EcommerceSales[[#This Row],[Quantity]] * _xlfn.XLOOKUP(tbl_EcommerceSales[[#This Row],[Product_ID]], Product_Master!A:A, Product_Master!F:F) -> 1600 | Y204: =tbl_EcommerceSales[[#This Row],[Net_Revenue]]-tbl_EcommerceSales[[#This Row],[Total_Cost]] -> 1098.2 | Z204: =IFERROR(#REF!/tbl_EcommerceSales[[#This Row],[Total_Cost]], 0) -> 0 | AA204: =TEXT(tbl_EcommerceSales[[#This Row],[Order_Date]],"mmm") -> Jan | AB204: =YEAR(tbl_EcommerceSales[[#This Row],[Order_Date]]) -> 2025 | AC204: =IF(tbl_EcommerceSales[[#This Row],[Age]]<18,"Under 18",IF(tbl_EcommerceSales[[#This Row],[Age]]<=25,"18-25",IF(tbl_EcommerceSales[[#This Row],[Age]]<=35,"26-35",IF(tbl_EcommerceSales[[#This Row],[Age]]<=45,"36-45",IF(tbl_EcommerceSales[[#This Row],[Age]]<=55,"46-55","56+"))))) -> 36-45
A205: ORD104300 | B205: 45679 | C205: CUST2186 | D205: Arjun Rao | E205: Female | F205: 29 | G205: Lucknow | H205: North | I205: P010 | J205: Casual Hoodie | K205: Fashion | L205: Clothing | M205: 4 | N205: 1499 | O205: 0.05 | P205: 3120 | Q205: Cash on Delivery | R205: Delivered | S205: Mobile App | T205: 3 | U205: =M205*N205 -> 5996 | V205: =tbl_EcommerceSales[[#This Row],[Gross_Sales]]*tbl_EcommerceSales[[#This Row],[Discount]] -> 299.8 | W205: =tbl_EcommerceSales[[#This Row],[Gross_Sales]]-tbl_EcommerceSales[[#This Row],[Discount_Amount]] -> 5696.2 | X205: =tbl_EcommerceSales[[#This Row],[Quantity]] * _xlfn.XLOOKUP(tbl_EcommerceSales[[#This Row],[Product_ID]], Product_Master!A:A, Product_Master!F:F) -> 3120 | Y205: =tbl_EcommerceSales[[#This Row],[Net_Revenue]]-tbl_EcommerceSales[[#This Row],[Total_Cost]] -> 2576.2 | Z205: =IFERROR(#REF!/tbl_EcommerceSales[[#This Row],[Total_Cost]], 0) -> 0 | AA205: =TEXT(tbl_EcommerceSales[[#This Row],[Order_Date]],"mmm") -> Jan | AB205: =YEAR(tbl_EcommerceSales[[#This Row],[Order_Date]]) -> 2025 | AC205: =IF(tbl_EcommerceSales[[#This Row],[Age]]<18,"Under 18",IF(tbl_EcommerceSales[[#This Row],[Age]]<=25,"18-25",IF(tbl_EcommerceSales[[#This Row],[Age]]<=35,"26-35",IF(tbl_EcommerceSales[[#This Row],[Age]]<=45,"36-45",IF(tbl_EcommerceSales[[#This Row],[Age]]<=55,"46-55","56+"))))) -> 26-35
A206: ORD100026 | B206: 45679 | C206: CUST1018 | D206: Rohan Rao | E206: Male | F206: 22 | G206: Dehradun | H206: North | I206: P018 | J206: Cricket Bat | K206: Sports & Fitness | L206: Sports | M206: 2 | N206: 2199 | O206: 0.1 | P206: 2500 | Q206: Net Banking | R206: Delivered | S206: Website | T206: 4 | U206: =M206*N206 -> 4398 | V206: =tbl_EcommerceSales[[#This Row],[Gross_Sales]]*tbl_EcommerceSales[[#This Row],[Discount]] -> 439.8 | W206: =tbl_EcommerceSales[[#This Row],[Gross_Sales]]-tbl_EcommerceSales[[#This Row],[Discount_Amount]] -> 3958.2 | X206: =tbl_EcommerceSales[[#This Row],[Quantity]] * _xlfn.XLOOKUP(tbl_EcommerceSales[[#This Row],[Product_ID]], Product_Master!A:A, Product_Master!F:F) -> 2500 | Y206: =tbl_EcommerceSales[[#This Row],[Net_Revenue]]-tbl_EcommerceSales[[#This Row],[Total_Cost]] -> 1458.2 | Z206: =IFERROR(#REF!/tbl_EcommerceSales[[#This Row],[Total_Cost]], 0) -> 0 | AA206: =TEXT(tbl_EcommerceSales[[#This Row],[Order_Date]],"mmm") -> Jan | AB206: =YEAR(tbl_EcommerceSales[[#This Row],[Order_Date]]) -> 2025 | AC206: =IF(tbl_EcommerceSales[[#This Row],[Age]]<18,"Under 18",IF(tbl_EcommerceSales[[#This Row],[Age]]<=25,"18-25",IF(tbl_EcommerceSales[[#This Row],[Age]]<=35,"26-35",IF(tbl_EcommerceSales[[#This Row],[Age]]<=45,"36-45",IF(tbl_EcommerceSales[[#This Row],[Age]]<=55,"46-55","56+"))))) -> 18-25
A207: ORD103983 | B207: 45679 | C207: CUST0952 | D207: Ishaan Malhotra | E207: Male | F207: 28 | G207: Chandigarh | H207: North | I207: P016 | J207: Yoga Mat | K207: Sports & Fitness | L207: Fitness | M207: 2 | N207: 999 | O207: 0.25 | P207: 1040 | Q207: Credit Card | R207: Delivered | S207: Mobile App | T207: 5 | U207: =M207*N207 -> 1998 | V207: =tbl_EcommerceSales[[#This Row],[Gross_Sales]]*tbl_EcommerceSales[[#This Row],[Discount]] -> 499.5 | W207: =tbl_EcommerceSales[[#This Row],[Gross_Sales]]-tbl_EcommerceSales[[#This Row],[Discount_Amount]] -> 1498.5 | X207: =tbl_EcommerceSales[[#This Row],[Quantity]] * _xlfn.XLOOKUP(tbl_EcommerceSales[[#This Row],[Product_ID]], Product_Master!A:A, Product_Master!F:F) -> 1040 | Y207: =tbl_EcommerceSales[[#This Row],[Net_Revenue]]-tbl_EcommerceSales[[#This Row],[Total_Cost]] -> 458.5 | Z207: =IFERROR(#REF!/tbl_EcommerceSales[[#This Row],[Total_Cost]], 0) -> 0 | AA207: =TEXT(tbl_EcommerceSales[[#This Row],[Order_Date]],"mmm") -> Jan | AB207: =YEAR(tbl_EcommerceSales[[#This Row],[Order_Date]]) -> 2025 | AC207: =IF(tbl_EcommerceSales[[#This Row],[Age]]<18,"Under 18",IF(tbl_EcommerceSales[[#This Row],[Age]]<=25,"18-25",IF(tbl_EcommerceSales[[#This Row],[Age]]<=35,"26-35",IF(tbl_EcommerceSales[[#This Row],[Age]]<=45,"36-45",IF(tbl_EcommerceSales[[#This Row],[Age]]<=55,"46-55","56+"))))) -> 26-35
A208: ORD101287 | B208: 45679 | C208: CUST0869 | D208: Akash Bansal | E208: Male | F208: 34 | G208: Guwahati | H208: East | I208: P006 | J208: Laptop Backpack | K208: Fashion | L208: Bags | M208: 1 | N208: 1799 | O208: 0.1 | P208: 950 | Q208: UPI | R208: Delivered | S208: Website | T208: 5 | U208: =M208*N208 -> 1799 | V208: =tbl_EcommerceSales[[#This Row],[Gross_Sales]]*tbl_EcommerceSales[[#This Row],[Discount]] -> 179.9 | W208: =tbl_EcommerceSales[[#This Row],[Gross_Sales]]-tbl_EcommerceSales[[#This Row],[Discount_Amount]] -> 1619.1 | X208: =tbl_EcommerceSales[[#This Row],[Quantity]] * _xlfn.XLOOKUP(tbl_EcommerceSales[[#This Row],[Product_ID]], Product_Master!A:A, Product_Master!F:F) -> 950 | Y208: =tbl_EcommerceSales[[#This Row],[Net_Revenue]]-tbl_EcommerceSales[[#This Row],[Total_Cost]] -> 669.1 | Z208: =IFERROR(#REF!/tbl_EcommerceSales[[#This Row],[Total_Cost]], 0) -> 0 | AA208: =TEXT(tbl_EcommerceSales[[#This Row],[Order_Date]],"mmm") -> Jan | AB208: =YEAR(tbl_EcommerceSales[[#This Row],[Order_Date]]) -> 2025 | AC208: =IF(tbl_EcommerceSales[[#This Row],[Age]]<18,"Under 18",IF(tbl_EcommerceSales[[#This Row],[Age]]<=25,"18-25",IF(tbl_EcommerceSales[[#This Row],[Age]]<=35,"26-35",IF(tbl_EcommerceSales[[#This Row],[Age]]<=45,"36-45",IF(tbl_EcommerceSales[[#This Row],[Age]]<=55,"46-55","56+"))))) -> 26-35
A209: ORD103116 | B209: 45679 | C209: CUST1355 | D209: Kiara Chopra | E209: Male | F209: 29 | G209: Guwahati | H209: East | I209: P002 | J209: Bluetooth Speaker | K209: Electronics | L209: Audio | M209: 1 | N209: 1899 | O209: 0.05 | P209: 1120 | Q209: UPI | R209: Delivered | S209: Mobile App | T209: 4 | U209: =M209*N209 -> 1899 | V209: =tbl_EcommerceSales[[#This Row],[Gross_Sales]]*tbl_EcommerceSales[[#This Row],[Discount]] -> 94.95 | W209: =tbl_EcommerceSales[[#This Row],[Gross_Sales]]-tbl_EcommerceSales[[#This Row],[Discount_Amount]] -> 1804.05 | X209: =tbl_EcommerceSales[[#This Row],[Quantity]] * _xlfn.XLOOKUP(tbl_EcommerceSales[[#This Row],[Product_ID]], Product_Master!A:A, Product_Master!F:F) -> 1120 | Y209: =tbl_EcommerceSales[[#This Row],[Net_Revenue]]-tbl_EcommerceSales[[#This Row],[Total_Cost]] -> 684.05 | Z209: =IFERROR(#REF!/tbl_EcommerceSales[[#This Row],[Total_Cost]], 0) -> 0 | AA209: =TEXT(tbl_EcommerceSales[[#This Row],[Order_Date]],"mmm") -> Jan | AB209: =YEAR(tbl_EcommerceSales[[#This Row],[Order_Date]]) -> 2025 | AC209: =IF(tbl_EcommerceSales[[#This Row],[Age]]<18,"Under 18",IF(tbl_EcommerceSales[[#This Row],[Age]]<=25,"18-25",IF(tbl_EcommerceSales[[#This Row],[Age]]<=35,"26-35",IF(tbl_EcommerceSales[[#This Row],[Age]]<=45,"36-45",IF(tbl_EcommerceSales[[#This Row],[Age]]<=55,"46-55","56+"))))) -> 26-35
A210: ORD102148 | B210: 45679 | C210: CUST1603 | D210: Riya Verma | E210: Female | F210: 20 | G210: Dehradun | H210: North | I210: P002 | J210: Bluetooth Speaker | K210: Electronics | L210: Audio | M210: 2 | N210: 1899 | O210: 0.15 | P210: 2240 | Q210: UPI | R210: Delivered | S210: Website | T210: 4 | U210: =M210*N210 -> 3798 | V210: =tbl_EcommerceSales[[#This Row],[Gross_Sales]]*tbl_EcommerceSales[[#This Row],[Discount]] -> 569.7 | W210: =tbl_EcommerceSales[[#This Row],[Gross_Sales]]-tbl_EcommerceSales[[#This Row],[Discount_Amount]] -> 3228.3 | X210: =tbl_EcommerceSales[[#This Row],[Quantity]] * _xlfn.XLOOKUP(tbl_EcommerceSales[[#This Row],[Product_ID]], Product_Master!A:A, Product_Master!F:F) -> 2240 | Y210: =tbl_EcommerceSales[[#This Row],[Net_Revenue]]-tbl_EcommerceSales[[#This Row],[Total_Cost]] -> 988.3 | Z210: =IFERROR(#REF!/tbl_EcommerceSales[[#This Row],[Total_Cost]], 0) -> 0 | AA210: =TEXT(tbl_EcommerceSales[[#This Row],[Order_Date]],"mmm") -> Jan | AB210: =YEAR(tbl_EcommerceSales[[#This Row],[Order_Date]]) -> 2025 | AC210: =IF(tbl_EcommerceSales[[#This Row],[Age]]<18,"Under 18",IF(tbl_EcommerceSales[[#This Row],[Age]]<=25,"18-25",IF(tbl_EcommerceSales[[#This Row],[Age]]<=35,"26-35",IF(tbl_EcommerceSales[[#This Row],[Age]]<=45,"36-45",IF(tbl_EcommerceSales[[#This Row],[Age]]<=55,"46-55","56+"))))) -> 18-25
A211: ORD100231 | B211: 45679 | C211: CUST1788 | D211: Ananya Kumar | E211: Female | F211: 40 | G211: Bhubaneswar | H211: East | I211: P002 | J211: Bluetooth Speaker | K211: Electronics | L211: Audio | M211: 1 | N211: 1899 | O211: 0 | P211: 1120 | Q211: Wallet | R211: Cancelled | S211: Mobile App | U211: =M211*N211 -> 1899 | V211: =tbl_EcommerceSales[[#This Row],[Gross_Sales]]*tbl_EcommerceSales[[#This Row],[Discount]] -> 0 | W211: =tbl_EcommerceSales[[#This Row],[Gross_Sales]]-tbl_EcommerceSales[[#This Row],[Discount_Amount]] -> 1899 | X211: =tbl_EcommerceSales[[#This Row],[Quantity]] * _xlfn.XLOOKUP(tbl_EcommerceSales[[#This Row],[Product_ID]], Product_Master!A:A, Product_Master!F:F) -> 1120 | Y211: =tbl_EcommerceSales[[#This Row],[Net_Revenue]]-tbl_EcommerceSales[[#This Row],[Total_Cost]] -> 779 | Z211: =IFERROR(#REF!/tbl_EcommerceSales[[#This Row],[Total_Cost]], 0) -> 0 | AA211: =TEXT(tbl_EcommerceSales[[#This Row],[Order_Date]],"mmm") -> Jan | AB211: =YEAR(tbl_EcommerceSales[[#This Row],[Order_Date]]) -> 2025 | AC211: =IF(tbl_EcommerceSales[[#This Row],[Age]]<18,"Under 18",IF(tbl_EcommerceSales[[#This Row],[Age]]<=25,"18-25",IF(tbl_EcommerceSales[[#This Row],[Age]]<=35,"26-35",IF(tbl_EcommerceSales[[#This Row],[Age]]<=45,"36-45",IF(tbl_EcommerceSales[[#This Row],[Age]]<=55,"46-55","56+"))))) -> 36-45
...

Sheet Product_Master
A1: Product_ID | B1: Product_Name | C1: Category | D1: Sub_Category | E1: Unit_Price | F1: Unit_Cost
A2: P001 | B2: Wireless Headphones | C2: Electronics | D2: Audio | E2: 2499 | F2: 1550
A3: P002 | B3: Bluetooth Speaker | C3: Electronics | D3: Audio | E3: 1899 | F3: 1120
A4: P003 | B4: Smart Watch | C4: Electronics | D4: Wearables | E4: 3299 | F4: 2100
A5: P004 | B5: USB-C Charger | C5: Electronics | D5: Accessories | E5: 899 | F5: 480
A6: P005 | B6: Power Bank 20000mAh | C6: Electronics | D6: Accessories | E6: 1599 | F6: 920
A7: P006 | B7: Laptop Backpack | C7: Fashion | D7: Bags | E7: 1799 | F7: 950
A8: P007 | B8: Running Shoes | C8: Fashion | D8: Footwear | E8: 2899 | F8: 1700
A9: P008 | B9: Cotton T-Shirt | C9: Fashion | D9: Clothing | E9: 799 | F9: 390
A10: P009 | B10: Denim Jeans | C10: Fashion | D10: Clothing | E10: 1999 | F10: 1050
A11: P010 | B11: Casual Hoodie | C11: Fashion | D11: Clothing | E11: 1499 | F11: 780
A12: P011 | B12: Coffee Maker | C12: Home & Kitchen | D12: Kitchen | E12: 3499 | F12: 2250
A13: P012 | B13: Air Fryer | C13: Home & Kitchen | D13: Kitchen | E13: 5999 | F13: 3900
... A31: P030 | B31: Self Help Book | C31: Books | D31: Self Development | E31: 599 | F31: 260

Sheet Data_Dictionary
A1: Column | B1: Description
A2: Order_ID | B2: Unique order identifier
A3: Order_Date | B3: Date the order was placed
A4: Customer_ID | B4: Unique customer identifier
A5: Customer_Name | B5: Customer full name
A6: Gender | B6: Customer gender
A7: Age | B7: Customer age
A8: City | B8: Customer city
A9: Region | B9: Customer region
A10: Product_ID | B10: Unique product identifier
A11: Product_Name | B11: Product name
A12: Category | B12: Main product category
... A23: Rating | B23: Customer rating from 1 to 5
